Workbook

Sheet LUNES 15
B1: =B155 -> 46188
B2: VENTA PUBLICO
B3: PRODUCTO | C3: $ COMPRA | D3: $ VENTA | E3: CANT | F3: $ | G3: CORTESIAS | I3: PRODUCTO | M3: $ COMPRA | N3: $ VENTA | O3: CANT | P3: $ | Q3: CORTESIAS
B4: MEDIA LAGER | C4: 15 | D4: 30 | F4: =E4*D4 -> 0 | H4: =G4*C4 -> 0 | I4: CIGARRO | M4: 6 | N4: 10 | P4: =O4*N4 -> 0
B5: MEDIA AZUL | C5: 14 | D5: 30 | F5: =E5*D5 -> 0 | H5: =G5*C5 -> 0 | I5: CACAHUATE | M5: 13 | N5: 25 | P5: =O5*N5 -> 0 | R5: =Q5*M5 -> 0
B6: MEDIA VICTORIA | C6: 17 | D6: 35 | F6: =E6*D6 -> 0 | H6: =G6*C6 -> 0 | I6: CHICARRON | M6: 11 | N6: 35 | P6: =O6*N6 -> 0 | R6: =Q6*M6 -> 0
B7: MEDIA CORONA | C7: 17 | D7: 35 | F7: =E7*D7 -> 0 | H7: =G7*C7 -> 0 | I7: SEMILLAS | M7: 10 | N7: 15 | P7: =O7*N7 -> 0 | R7: =Q7*M7 -> 0
B8: MEGA LAGER | C8: 37 | D8: 70 | F8: =E8*D8 -> 0 | H8: =G8*C8 -> 0 | I8: CANCION | M8: 0 | N8: 10 | P8: =O8*N8 -> 0 | R8: =Q8*M8 -> 0
B9: MEGA ROJA | C9: 35 | D9: 60 | F9: =E9*D9 -> 0 | H9: =G9*C9 -> 0 | I9: PAPAS | M9: 14.8 | N9: 35 | P9: =O9*N9 -> 0 | R9: =Q9*M9 -> 0
B10: MEGA AZUL | C10: 35 | D10: 60 | F10: =E10*D10 -> 0 | H10: =G10*C10 -> 0 | I10: COCA 355 | M10: 13 | N10: 20 | P10: =O10*N10 -> 0 | R10: =Q10*M10 -> 0
B11: MEGA VICTORIA | C11: 41 | D11: 80 | F11: =E11*D11 -> 0 | H11: =G11*C11 -> 0 | I11: PEÑAFIEL 355 | M11: 11 | N11: 20 | P11: =O11*N11 -> 0 | R11: =Q11*M11 -> 0
B12: MEGA CORONA | C12: 41 | D12: 80 | F12: =E12*D12 -> 0 | H12: =G12*C12 -> 0 | I12: TORONJA 355 | M12: 10 | N12: 20 | P12: =O12*N12 -> 0 | R12: =Q12*M12 -> 0
B13: CUBO MEDIA LAGER (6) | C13: =14*6 -> 84 | D13: 160 | F13: =E13*D13 -> 0 | I13: BOOS | M13: 40 | N13: 60 | P13: =O13*N13 -> 0
B14: CUBO MEDIA AZUL (6) | C14: =14*6 -> 84 | D14: 160 | F14: =E14*D14 -> 0 | I14: NEWMIX PALOMA | M14: 25 | N14: 45 | P14: =O14*N14 -> 0
B15: CUBO MEDIA VICTORIA (6) | C15: =17*6 -> 102 | D15: 180 | F15: =E15*D15 -> 0 | I15: NEWMIX VAMPIRO | M15: 25 | N15: 45 | P15: =O15*N15 -> 0
B16: CUBO MEDIA CORONA (6) | C16: =17*6 -> 102 | D16: 180 | F16: =E16*D16 -> 0 | I16: CLAMATO (Botella) | M16: 35 | N16: 50 | P16: =O16*N16 -> 0 | R16: =Q16*M16 -> 0
B17: PROMO MEGA LAGER (3) | C17: =37*3 -> 111 | D17: 195 | F17: =E17*D17 -> 0 | I17: CLAMATO (Preparado vaso) | M17: 27 | N17: 45 | P17: =O17*N17 -> 0 | R17: =Q17*M17 -> 0
B18: PROMO MEGA ROJA (3) | C18: =35*3 -> 105 | D18: 165 | F18: =E18*D18 -> 0 | I18: PREPARADO SALSAS (Vaso) | M18: 10 | N18: 25 | P18: =O18*N18 -> 0 | R18: =Q18*M18 -> 0
B19: PROMO MEGA AZUL (3) | C19: =35*3 -> 105 | D19: 165 | F19: =E19*D19 -> 0 | I19: SOPA | M19: 14 | N19: 35 | P19: =O19*N19 -> 0 | R19: =Q19*M19 -> 0
B20: PROMO MEGA VICTORIA (3) | C20: =41*3 -> 123 | D20: 225 | F20: =E20*D20 -> 0 | I20: BOTANA JAMON | M20: 40 | N20: 70 | P20: =O20*N20 -> 0 | R20: =Q20*M20 -> 0
B21: PROMO MEGA CORONA (3) | C21: =41*3 -> 123 | D21: 225 | F21: =E21*D21 -> 0 | I21: MANGUITO | M21: 8 | N21: 15 | P21: =O21*N21 -> 0 | R21: =Q21*M21 -> 0
B22: MICHE LAGER (2 MEDIAS) | C22: 40 | D22: 95 | F22: =E22*D22 -> 0 | I22: CHICLES | M22: 28 | N22: 50 | P22: =O22*N22 -> 0 | R22: =Q22*M22 -> 0
B23: MICHE AZUL (2 MEDIAS) | C23: 40 | D23: 95 | F23: =E23*D23 -> 0 | H23: =G23*C23 -> 0 | I23: DESCORCHE | N23: 300 | P23: =O23*N23 -> 0
B24: MICHE VICTORIA (2 MEDIAS) | C24: 45 | D24: 95 | F24: =E24*D24 -> 0 | H24: =G24*C24 -> 0 | I24: SALSA VALENTINA (CHICA) | M24: 17 | N24: 35 | P24: =O24*N24 -> 0 | R24: =Q24*M24 -> 0
B25: MICHE CORONA (2 MEDIAS) | C25: 45 | D25: 95 | F25: =E25*D25 -> 0 | H25: =G25*C25 -> 0 | I25: VASO ROTO | N25: 35 | P25: =O25*N25 -> 0
B26: COPA $50 | C26: 25 | D26: 50 | F26: =E26*D26 -> 0 | H26: =G26*C26 -> 0 | P26: =O26*N26 -> 0
B27: COPA $70 | C27: 30 | D27: 70 | F27: =E27*D27 -> 0 | H27: =G27*C27 -> 0 | P27: =O27*N27 -> 0
B28: COPA $100 | C28: 50 | D28: 100 | F28: =E28*D28 -> 0 | H28: =G28*C28 -> 0 | P28: =O28*N28 -> 0
B29: COPA $120 | C29: 70 | D29: 120 | F29: =E29*D29 -> 0 | H29: =G29*C29 -> 0 | P29: =O29*N29 -> 0
B30: COPA $150 | C30: 100 | D30: 150 | F30: =E30*D30 -> 0 | H30: =G30*C30 -> 0 | P30: =O30*N30 -> 0
B31: AZULITO | C31: 40 | D31: 95 | F31: =E31*D31 -> 0 | H31: =G31*C31 -> 0 | P31: =O31*N31 -> 0
B32: TOTAL DE VENTA | G32: =SUM(F4:F31,P4:P31) -> 0 | I32: TOTAL DE CORTESIAS | Q32: =SUM(H4:H31,R4:R31) -> 0
B34: =B155 -> 46188
B35: VENTA PERSONAL
B36: PRODUCTO | C36: $ COMPRA | D36: $ VENTA | E36: ELOY | G36: NUBIA | I36: MARCE | K36: ISELA | O36: VIKY | Q36: 4 | S36: 5 | U36: 6 | W36: 7
E37: CANT | F37: $ | G37: CANT | H37: $ | I37: CANT | J37: $ | K37: CANT | L37: $ | O37: CANT | P37: $ | Q37: CANT | R37: $ | S37: CANT | T37: $ | U37: CANT | V37: $ | W37: CANT | X37: $
B38: MEDIA LAGER | C38: 15 | D38: 30 | F38: =E38*C38 -> 0 | H38: =G38*C38 -> 0 | J38: =I38*C38 -> 0 | L38: =K38*C38 -> 0 | P38: =O38*C38 -> 0 | R38: =Q38*C38 -> 0 | T38: =S38*C38 -> 0 | V38: =U38*C38 -> 0 | X38: =W38*C38 -> 0
B39: MEDIA AZUL | C39: 14 | D39: 30 | F39: =E39*C39 -> 0 | H39: =G39*C39 -> 0 | J39: =I39*C39 -> 0 | L39: =K39*C39 -> 0 | P39: =O39*C39 -> 0 | R39: =Q39*C39 -> 0 | T39: =S39*C39 -> 0 | V39: =U39*C39 -> 0 | X39: =W39*C39 -> 0
B40: MEDIA VICTORIA | C40: 17 | D40: 35 | F40: =E40*C40 -> 0 | H40: =G40*C40 -> 0 | J40: =I40*C40 -> 0 | L40: =K40*C40 -> 0 | P40: =O40*C40 -> 0 | R40: =Q40*C40 -> 0 | T40: =S40*C40 -> 0 | V40: =U40*C40 -> 0 | X40: =W40*C40 -> 0
B41: MEDIA CORONA | C41: 17 | D41: 35 | F41: 1 | H41: =G41*C41 -> 0 | J41: =I41*C41 -> 0 | L41: =K41*C41 -> 0 | P41: =O41*C41 -> 0 | R41: =Q41*C41 -> 0 | T41: =S41*C41 -> 0 | V41: =U41*C41 -> 0 | X41: =W41*C41 -> 0
B42: MEGA LAGER | C42: 37 | D42: 70 | F42: =E42*C42 -> 0 | H42: =G42*C42 -> 0 | J42: =I42*C42 -> 0 | L42: =K42*C42 -> 0 | P42: =O42*C42 -> 0 | R42: =Q42*C42 -> 0 | T42: =S42*C42 -> 0 | V42: =U42*C42 -> 0 | X42: =W42*C42 -> 0
B43: MEGA ROJA | C43: 35 | D43: 60 | F43: =E43*C43 -> 0 | H43: =G43*C43 -> 0 | J43: =I43*C43 -> 0 | L43: =K43*C43 -> 0 | P43: =O43*C43 -> 0 | R43: =Q43*C43 -> 0 | T43: =S43*C43 -> 0 | V43: =U43*C43 -> 0 | X43: =W43*C43 -> 0
B44: MEGA AZUL | C44: 35 | D44: 60 | F44: =E44*C44 -> 0 | H44: =G44*C44 -> 0 | J44: =I44*C44 -> 0 | L44: =K44*C44 -> 0 | P44: =O44*C44 -> 0 | R44: =Q44*C44 -> 0 | T44: =S44*C44 -> 0 | V44: =U44*C44 -> 0 | X44: =W44*C44 -> 0
B45: MEGA VICTORIA | C45: 41 | D45: 80 | F45: =E45*C45 -> 0 | H45: =G45*C45 -> 0 | J45: =I45*C45 -> 0 | L45: =K45*C45 -> 0 | P45: =O45*C45 -> 0 | R45: =Q45*C45 -> 0 | T45: =S45*C45 -> 0 | V45: =U45*C45 -> 0 | X45: =W45*C45 -> 0
B46: MEGA CORONA | C46: 41 | D46: 80 | F46: =E46*C46 -> 0 | H46: =G46*C46 -> 0 | J46: =I46*C46 -> 0 | L46: =K46*C46 -> 0 | P46: =O46*C46 -> 0 | R46: =Q46*C46 -> 0 | T46: =S46*C46 -> 0 | V46: =U46*C46 -> 0 | X46: =W46*C46 -> 0
B47: CIGARRO | C47: 6 | D47: 10 | F47: =E47*C47 -> 0 | H47: =G47*C47 -> 0 | J47: =I47*C47 -> 0 | L47: =K47*C47 -> 0 | P47: =O47*C47 -> 0 | R47: =Q47*C47 -> 0 | T47: =S47*C47 -> 0 | V47: =U47*C47 -> 0 | X47: =W47*C47 -> 0
B48: CACAHUATE | C48: 13 | D48: 25 | F48: =E48*C48 -> 0 | H48: =G48*C48 -> 0 | J48: =I48*C48 -> 0 | L48: =K48*C48 -> 0 | P48: =O48*C48 -> 0 | R48: =Q48*C48 -> 0 | T48: =S48*C48 -> 0 | V48: =U48*C48 -> 0 | X48: =W48*C48 -> 0
B49: CHICARRON | C49: 11 | D49: 35 | F49: =E49*C49 -> 0 | H49: =G49*C49 -> 0 | J49: =I49*C49 -> 0 | L49: =K49*C49 -> 0 | P49: =O49*C49 -> 0 | R49: =Q49*C49 -> 0 | T49: =S49*C49 -> 0 | V49: =U49*C49 -> 0 | X49: =W49*C49 -> 0
B50: SEMILLAS | C50: 10 | D50: 15 | F50: =E50*C50 -> 0 | H50: =G50*C50 -> 0 | J50: =I50*C50 -> 0 | L50: =K50*C50 -> 0 | P50: =O50*C50 -> 0 | R50: =Q50*C50 -> 0 | T50: =S50*C50 -> 0 | V50: =U50*C50 -> 0 | X50: =W50*C50 -> 0
B51: PAPAS | C51: 14.8 | D51: 35 | F51: =E51*C51 -> 0 | H51: =G51*C51 -> 0 | J51: =I51*C51 -> 0 | L51: =K51*C51 -> 0 | P51: =O51*C51 -> 0 | R51: =Q51*C51 -> 0 | T51: =S51*C51 -> 0 | V51: =U51*C51 -> 0 | X51: =W51*C51 -> 0
B52: COCA 355 | C52: 13 | D52: 20 | F52: =E52*C52 -> 0 | H52: =G52*C52 -> 0 | J52: =I52*C52 -> 0 | L52: =K52*C52 -> 0 | P52: =O52*C52 -> 0 | R52: =Q52*C52 -> 0 | T52: =S52*C52 -> 0 | V52: =U52*C52 -> 0 | X52: =W52*C52 -> 0
B53: PEÑAFIEL 355 | C53: 11 | D53: 20 | F53: =E53*C53 -> 0 | H53: =G53*C53 -> 0 | J53: =I53*C53 -> 0 | L53: =K53*C53 -> 0 | P53: =O53*C53 -> 0 | R53: =Q53*C53 -> 0 | T53: =S53*C53 -> 0 | V53: =U53*C53 -> 0 | X53: =W53*C53 -> 0
... B62: CHICLES | C62: 28 | D62: 50 | F62: =E62*C62 -> 0 | H62: =G62*C62 -> 0 | J62: =I62*C62 -> 0 | L62: =K62*C62 -> 0 | P62: =O62*C62 -> 0 | R62: =Q62*C62 -> 0 | T62: =S62*C62 -> 0 | V62: =U62*C62 -> 0 | X62: =W62*C62 -> 0
F63: =E63*C63 -> 0 | H63: =G63*C63 -> 0 | J63: =I63*C63 -> 0 | L63: =K63*C63 -> 0 | P63: =O63*C63 -> 0 | R63: =Q63*C63 -> 0 | T63: =S63*C63 -> 0 | V63: =U63*C63 -> 0 | X63: =W63*C63 -> 0
F64: =E64*C64 -> 0 | H64: =G64*C64 -> 0 | J64: =I64*C64 -> 0 | L64: =K64*C64 -> 0 | P64: =O64*C64 -> 0 | R64: =Q64*C64 -> 0 | T64: =S64*C64 -> 0 | V64: =U64*C64 -> 0 | X64: =W64*C64 -> 0
F65: =E65*C65 -> 0 | H65: =G65*C65 -> 0 | J65: =I65*C65 -> 0 | L65: =K65*C65 -> 0 | P65: =O65*C65 -> 0 | R65: =Q65*C65 -> 0 | T65: =S65*C65 -> 0 | V65: =U65*C65 -> 0 | X65: =W65*C65 -> 0
E66: =E36 -> ELOY | F66: =SUM(F38:F65) -> 1 | G66: =G36 -> NUBIA | H66: =SUM(H38:H65) -> 0 | I66: =I36 -> MARCE | J66: =SUM(J38:J65) -> 0 | K66: =K36 -> ISELA | L66: =SUM(L38:L65) -> 0 | O66: =O36 -> VIKY | P66: =SUM(P38:P65) -> 0 | Q66: =Q36 -> 4 | R66: =SUM(R38:R65) -> 0 | S66: =S36 -> 5 | T66: =SUM(T38:T65) -> 0 | U66: =U36 -> 6 | V66: =SUM(V38:V65) -> 0 | W66: =W36 -> 7 | X66: =SUM(X38:X65) -> 0
B68: =B155 -> 46188
B69: VENTA DE FICHAS
B70: NOMBRE | E70: PRECIO | F70: PRODUCTO | H70: 60 | I70: 80 | J70: TOTAL | K70: VENTA | O70: COMISION | Q70: VENTA TOTAL
B71: =G36 -> NUBIA | E71: 120 | F71: MEDIA LAGER | J71: =H71+I71 -> 0 | K71: =J71*E71 -> 0 | O71: =H71*H70+I71*I70 -> 0
F72: MEDIA AZUL | J72: =H72+I72 -> 0 | K72: =J72*E71 -> 0 | O72: =H72*H70+I72*I70 -> 0
B73: PAGO DE COMISION | E73: 300 | F73: MEGA LAGER | K73: =H73*E73 -> 0 | O73: =H73*150 -> 0
B74: =O71+O72+O73+O74+O75 -> 0 | F74: MEGA AZUL | K74: =H74*E73 -> 0 | O74: =H74*150 -> 0 | Q74: =K71+K72+K73+K74+K75 -> 0
F75: MEGA ROJA | K75: =H75*E73 -> 0 | O75: =H75*150 -> 0
B76: NOMBRE | E76: PRECIO | F76: PRODUCTO | H76: 60 | I76: 80 | J76: TOTAL | K76: VENTA | O76: COMISION | Q76: VENTA TOTAL
B77: =I36 -> MARCE | E77: 120 | F77: MEDIA LAGER | J77: =H77+I77 -> 0 | K77: =J77*E77 -> 0 | O77: =H77*H76+I77*I76 -> 0
F78: MEDIA AZUL | J78: =H78+I78 -> 0 | K78: =J78*E77 -> 0 | O78: =H78*H76+I78*I76 -> 0
B79: PAGO DE COMISION | E79: 300 | F79: MEGA LAGER | K79: =H79*E79 -> 0 | O79: =H79*150 -> 0
B80: =O77+O78+O79+O80+O81 -> 0 | F80: MEGA AZUL | K80: =H80*E79 -> 0 | O80: =H80*150 -> 0 | Q80: =K77+K78+K79+K80+K81 -> 0
F81: MEGA ROJA | K81: =H81*E79 -> 0 | O81: =H81*150 -> 0
B82: NOMBRE | E82: PRECIO | F82: PRODUCTO | H82: 60 | I82: 80 | J82: TOTAL | K82: VENTA | O82: COMISION | Q82: VENTA TOTAL
B83: =K36 -> ISELA | E83: 120 | F83: MEDIA LAGER | J83: =H83+I83 -> 0 | K83: =J83*E83 -> 0 | O83: =H83*H82+I83*I82 -> 0
F84: MEDIA AZUL | J84: =H84+I84 -> 0 | K84: =J84*E83 -> 0 | O84: =H84*H82+I84*I82 -> 0
B85: PAGO DE COMISION | E85: 300 | F85: MEGA LAGER | K85: =H85*E85 -> 0 | O85: =H85*150 -> 0
B86: =O83+O84+O85+O86+O87 -> 0 | F86: MEGA AZUL | K86: =H86*E85 -> 0 | O86: =H86*150 -> 0 | Q86: =K83+K84+K85+K86+K87 -> 0
F87: MEGA ROJA | K87: =H87*E85 -> 0 | O87: =H87*150 -> 0
B88: NOMBRE | E88: PRECIO | F88: PRODUCTO | H88: 60 | I88: 80 | J88: TOTAL | K88: VENTA | O88: COMISION | Q88: VENTA TOTAL
B89: =O36 -> VIKY | E89: 120 | F89: MEDIA LAGER | J89: =H89+I89 -> 0 | K89: =J89*E89 -> 0 | O89: =H89*H88+I89*I88 -> 0
F90: MEDIA AZUL | J90: =H90+I90 -> 0 | K90: =J90*E89 -> 0 | O90: =H90*H88+I90*I88 -> 0
B91: PAGO DE COMISION | E91: 300 | F91: MEGA LAGER | K91: =H91*E91 -> 0 | O91: =H91*150 -> 0
B92: =O89+O90+O91+O92+O93 -> 0 | F92: MEGA AZUL | K92: =H92*E91 -> 0 | O92: =H92*150 -> 0 | Q92: =K89+K90+K91+K92+K93 -> 0
F93: MEGA ROJA | K93: =H93*E91 -> 0 | O93: =H93*150 -> 0
B94: NOMBRE | E94: PRECIO | F94: PRODUCTO | H94: 60 | I94: 80 | J94: TOTAL | K94: VENTA | O94: COMISION | Q94: VENTA TOTAL
B95: =Q36 -> 4 | E95: 120 | F95: MEDIA LAGER | J95: =H95+I95 -> 0 | K95: =J95*E95 -> 0 | O95: =H95*H94+I95*I94 -> 0
F96: MEDIA AZUL | J96: =H96+I96 -> 0 | K96: =J96*E95 -> 0 | O96: =H96*H94+I96*I94 -> 0
B97: PAGO DE COMISION | E97: 300 | F97: MEGA LAGER | K97: =H97*E97 -> 0 | O97: =H97*150 -> 0
B98: =O95+O96+O97+O98+O99 -> 0 | F98: MEGA AZUL | K98: =H98*E97 -> 0 | O98: =H98*150 -> 0 | Q98: =K95+K96+K97+K98+K99 -> 0
F99: MEGA ROJA | K99: =H99*E97 -> 0 | O99: =H99*150 -> 0
B100: NOMBRE | E100: PRECIO | F100: PRODUCTO | H100: 60 | I100: 80 | J100: TOTAL | K100: VENTA | O100: COMISION | Q100: VENTA TOTAL
B101: =S36 -> 5 | E101: 120 | F101: MEDIA LAGER | J101: =H101+I101 -> 0 | K101: =J101*E101 -> 0 | O101: =H101*H100+I101*I100 -> 0
F102: MEDIA AZUL | J102: =H102+I102 -> 0 | K102: =J102*E101 -> 0 | O102: =H102*H100+I102*I100 -> 0
B103: PAGO DE COMISION | E103: 300 | F103: MEGA LAGER | K103: =H103*E103 -> 0 | O103: =H103*150 -> 0
B104: =O101+O102+O103+O104+O105 -> 0 | F104: MEGA AZUL | K104: =H104*E103 -> 0 | O104: =H104*150 -> 0 | Q104: =K101+K102+K103+K104+K105 -> 0
F105: MEGA ROJA | K105: =H105*E103 -> 0 | O105: =H105*150 -> 0
B106: NOMBRE | E106: PRECIO | F106: PRODUCTO | H106: 60 | I106: 80 | J106: TOTAL | K106: VENTA | O106: COMISION | Q106: VENTA TOTAL
B107: =U36 -> 6 | E107: 120 | F107: MEDIA LAGER | J107: =H107+I107 -> 0 | K107: =J107*E107 -> 0 | O107: =H107*H106+I107*I106 -> 0
F108: MEDIA AZUL | J108: =H108+I108 -> 0 | K108: =J108*E107 -> 0 | O108: =H108*H106+I108*I106 -> 0
B109: PAGO DE COMISION | E109: 300 | F109: MEGA LAGER | K109: =H109*E109 -> 0 | O109: =H109*150 -> 0
B110: =O107+O108+O109+O110+O111 -> 0 | F110: MEGA AZUL | K110: =H110*E109 -> 0 | O110: =H110*150 -> 0 | Q110: =K107+K108+K109+K110+K111 -> 0
...

Sheet DOMINGO 14
B1: =B155 -> 46187
B2: VENTA PUBLICO
B3: PRODUCTO | C3: $ COMPRA | D3: $ VENTA | E3: CANT | F3: $ | G3: CORTESIAS | I3: PRODUCTO | M3: $ COMPRA | N3: $ VENTA | O3: CANT | P3: $ | Q3: CORTESIAS
B4: MEDIA LAGER | C4: 15 | D4: 30 | F4: =E4*D4 -> 0 | H4: =G4*C4 -> 0 | I4: CIGARRO | M4: 6 | N4: 10 | P4: =O4*N4 -> 0
B5: MEDIA AZUL | C5: 14 | D5: 30 | F5: =E5*D5 -> 0 | H5: =G5*C5 -> 0 | I5: CACAHUATE | M5: 13 | N5: 25 | P5: =O5*N5 -> 0 | R5: =Q5*M5 -> 0
B6: MEDIA VICTORIA | C6: 17 | D6: 35 | F6: =E6*D6 -> 0 | H6: =G6*C6 -> 0 | I6: CHICARRON | M6: 11 | N6: 35 | P6: =O6*N6 -> 0 | R6: =Q6*M6 -> 0
B7: MEDIA CORONA | C7: 17 | D7: 35 | F7: =E7*D7 -> 0 | H7: =G7*C7 -> 0 | I7: SEMILLAS | M7: 10 | N7: 15 | P7: =O7*N7 -> 0 | R7: =Q7*M7 -> 0
B8: MEGA LAGER | C8: 37 | D8: 70 | F8: =E8*D8 -> 0 | H8: =G8*C8 -> 0 | I8: CANCION | M8: 0 | N8: 10 | P8: =O8*N8 -> 0 | R8: =Q8*M8 -> 0
B9: MEGA ROJA | C9: 35 | D9: 60 | F9: =E9*D9 -> 0 | H9: =G9*C9 -> 0 | I9: PAPAS | M9: 14.8 | N9: 35 | P9: =O9*N9 -> 0 | R9: =Q9*M9 -> 0
B10: MEGA AZUL | C10: 35 | D10: 60 | F10: =E10*D10 -> 0 | H10: =G10*C10 -> 0 | I10: COCA 355 | M10: 13 | N10: 20 | P10: =O10*N10 -> 0 | R10: =Q10*M10 -> 0
B11: MEGA VICTORIA | C11: 41 | D11: 80 | F11: =E11*D11 -> 0 | H11: =G11*C11 -> 0 | I11: PEÑAFIEL 355 | M11: 11 | N11: 20 | P11: =O11*N11 -> 0 | R11: =Q11*M11 -> 0
B12: MEGA CORONA | C12: 41 | D12: 80 | F12: =E12*D12 -> 0 | H12: =G12*C12 -> 0 | I12: TORONJA 355 | M12: 10 | N12: 20 | P12: =O12*N12 -> 0 | R12: =Q12*M12 -> 0
B13: CUBO MEDIA LAGER (6) | C13: =14*6 -> 84 | D13: 160 | F13: =E13*D13 -> 0 | I13: BOOS | M13: 40 | N13: 60 | P13: =O13*N13 -> 0
B14: CUBO MEDIA AZUL (6) | C14: =14*6 -> 84 | D14: 160 | F14: =E14*D14 -> 0 | I14: NEWMIX PALOMA | M14: 25 | N14: 45 | P14: =O14*N14 -> 0
B15: CUBO MEDIA VICTORIA (6) | C15: =17*6 -> 102 | D15: 180 | F15: =E15*D15 -> 0 | I15: NEWMIX VAMPIRO | M15: 25 | N15: 45 | P15: =O15*N15 -> 0
B16: CUBO MEDIA CORONA (6) | C16: =17*6 -> 102 | D16: 180 | F16: =E16*D16 -> 0 | I16: CLAMATO (Botella) | M16: 35 | N16: 50 | P16: =O16*N16 -> 0 | R16: =Q16*M16 -> 0
B17: PROMO MEGA LAGER (3) | C17: =37*3 -> 111 | D17: 195 | F17: =E17*D17 -> 0 | I17: CLAMATO (Preparado vaso) | M17: 27 | N17: 45 | P17: =O17*N17 -> 0 | R17: =Q17*M17 -> 0
B18: PROMO MEGA ROJA (3) | C18: =35*3 -> 105 | D18: 165 | F18: =E18*D18 -> 0 | I18: PREPARADO SALSAS (Vaso) | M18: 10 | N18: 25 | P18: =O18*N18 -> 0 | R18: =Q18*M18 -> 0
B19: PROMO MEGA AZUL (3) | C19: =35*3 -> 105 | D19: 165 | F19: =E19*D19 -> 0 | I19: SOPA | M19: 14 | N19: 35 | P19: =O19*N19 -> 0 | R19: =Q19*M19 -> 0
B20: PROMO MEGA VICTORIA (3) | C20: =41*3 -> 123 | D20: 225 | F20: =E20*D20 -> 0 | I20: BOTANA JAMON | M20: 40 | N20: 70 | P20: =O20*N20 -> 0 | R20: =Q20*M20 -> 0
B21: PROMO MEGA CORONA (3) | C21: =41*3 -> 123 | D21: 225 | F21: =E21*D21 -> 0 | I21: MANGUITO | M21: 8 | N21: 15 | P21: =O21*N21 -> 0 | R21: =Q21*M21 -> 0
B22: MICHE LAGER (2 MEDIAS) | C22: 40 | D22: 95 | F22: =E22*D22 -> 0 | I22: CHICLES | M22: 28 | N22: 50 | P22: =O22*N22 -> 0 | R22: =Q22*M22 -> 0
B23: MICHE AZUL (2 MEDIAS) | C23: 40 | D23: 95 | F23: =E23*D23 -> 0 | H23: =G23*C23 -> 0 | I23: DESCORCHE | N23: 300 | P23: =O23*N23 -> 0
B24: MICHE VICTORIA (2 MEDIAS) | C24: 45 | D24: 95 | F24: =E24*D24 -> 0 | H24: =G24*C24 -> 0 | I24: SALSA VALENTINA (CHICA) | M24: 17 | N24: 35 | P24: =O24*N24 -> 0 | R24: =Q24*M24 -> 0
B25: MICHE CORONA (2 MEDIAS) | C25: 45 | D25: 95 | F25: =E25*D25 -> 0 | H25: =G25*C25 -> 0 | I25: VASO ROTO | N25: 35 | P25: =O25*N25 -> 0
B26: COPA $50 | C26: 25 | D26: 50 | F26: =E26*D26 -> 0 | H26: =G26*C26 -> 0 | P26: =O26*N26 -> 0
B27: COPA $70 | C27: 30 | D27: 70 | F27: =E27*D27 -> 0 | H27: =G27*C27 -> 0 | P27: =O27*N27 -> 0
B28: COPA $100 | C28: 50 | D28: 100 | F28: =E28*D28 -> 0 | H28: =G28*C28 -> 0 | P28: =O28*N28 -> 0
B29: COPA $120 | C29: 70 | D29: 120 | F29: =E29*D29 -> 0 | H29: =G29*C29 -> 0 | P29: =O29*N29 -> 0
B30: COPA $150 | C30: 100 | D30: 150 | F30: =E30*D30 -> 0 | H30: =G30*C30 -> 0 | P30: =O30*N30 -> 0
B31: AZULITO | C31: 40 | D31: 95 | F31: =E31*D31 -> 0 | H31: =G31*C31 -> 0 | P31: =O31*N31 -> 0
B32: TOTAL DE VENTA | G32: =SUM(F4:F31,P4:P31) -> 0 | I32: TOTAL DE CORTESIAS | Q32: =SUM(H4:H31,R4:R31) -> 0
B34: =B155 -> 46187
B35: VENTA PERSONAL
B36: PRODUCTO | C36: $ COMPRA | D36: $ VENTA | E36: ELOY | G36: NUBIA | I36: MARCE | K36: ISELA | O36: VIKY | Q36: 4 | S36: 5 | U36: 6 | W36: 7
E37: CANT | F37: $ | G37: CANT | H37: $ | I37: CANT | J37: $ | K37: CANT | L37: $ | O37: CANT | P37: $ | Q37: CANT | R37: $ | S37: CANT | T37: $ | U37: CANT | V37: $ | W37: CANT | X37: $
B38: MEDIA LAGER | C38: 15 | D38: 30 | F38: =E38*C38 -> 0 | H38: =G38*C38 -> 0 | J38: =I38*C38 -> 0 | L38: =K38*C38 -> 0 | P38: =O38*C38 -> 0 | R38: =Q38*C38 -> 0 | T38: =S38*C38 -> 0 | V38: =U38*C38 -> 0 | X38: =W38*C38 -> 0
B39: MEDIA AZUL | C39: 14 | D39: 30 | F39: =E39*C39 -> 0 | H39: =G39*C39 -> 0 | J39: =I39*C39 -> 0 | L39: =K39*C39 -> 0 | P39: =O39*C39 -> 0 | R39: =Q39*C39 -> 0 | T39: =S39*C39 -> 0 | V39: =U39*C39 -> 0 | X39: =W39*C39 -> 0
B40: MEDIA VICTORIA | C40: 17 | D40: 35 | F40: =E40*C40 -> 0 | H40: =G40*C40 -> 0 | J40: =I40*C40 -> 0 | L40: =K40*C40 -> 0 | P40: =O40*C40 -> 0 | R40: =Q40*C40 -> 0 | T40: =S40*C40 -> 0 | V40: =U40*C40 -> 0 | X40: =W40*C40 -> 0
B41: MEDIA CORONA | C41: 17 | D41: 35 | F41: 1 | H41: =G41*C41 -> 0 | J41: =I41*C41 -> 0 | L41: =K41*C41 -> 0 | P41: =O41*C41 -> 0 | R41: =Q41*C41 -> 0 | T41: =S41*C41 -> 0 | V41: =U41*C41 -> 0 | X41: =W41*C41 -> 0
B42: MEGA LAGER | C42: 37 | D42: 70 | F42: =E42*C42 -> 0 | H42: =G42*C42 -> 0 | J42: =I42*C42 -> 0 | L42: =K42*C42 -> 0 | P42: =O42*C42 -> 0 | R42: =Q42*C42 -> 0 | T42: =S42*C42 -> 0 | V42: =U42*C42 -> 0 | X42: =W42*C42 -> 0
B43: MEGA ROJA | C43: 35 | D43: 60 | F43: =E43*C43 -> 0 | H43: =G43*C43 -> 0 | J43: =I43*C43 -> 0 | L43: =K43*C43 -> 0 | P43: =O43*C43 -> 0 | R43: =Q43*C43 -> 0 | T43: =S43*C43 -> 0 | V43: =U43*C43 -> 0 | X43: =W43*C43 -> 0
B44: MEGA AZUL | C44: 35 | D44: 60 | F44: =E44*C44 -> 0 | H44: =G44*C44 -> 0 | J44: =I44*C44 -> 0 | L44: =K44*C44 -> 0 | P44: =O44*C44 -> 0 | R44: =Q44*C44 -> 0 | T44: =S44*C44 -> 0 | V44: =U44*C44 -> 0 | X44: =W44*C44 -> 0
B45: MEGA VICTORIA | C45: 41 | D45: 80 | F45: =E45*C45 -> 0 | H45: =G45*C45 -> 0 | J45: =I45*C45 -> 0 | L45: =K45*C45 -> 0 | P45: =O45*C45 -> 0 | R45: =Q45*C45 -> 0 | T45: =S45*C45 -> 0 | V45: =U45*C45 -> 0 | X45: =W45*C45 -> 0
B46: MEGA CORONA | C46: 41 | D46: 80 | F46: =E46*C46 -> 0 | H46: =G46*C46 -> 0 | J46: =I46*C46 -> 0 | L46: =K46*C46 -> 0 | P46: =O46*C46 -> 0 | R46: =Q46*C46 -> 0 | T46: =S46*C46 -> 0 | V46: =U46*C46 -> 0 | X46: =W46*C46 -> 0
B47: CIGARRO | C47: 6 | D47: 10 | F47: =E47*C47 -> 0 | H47: =G47*C47 -> 0 | J47: =I47*C47 -> 0 | L47: =K47*C47 -> 0 | P47: =O47*C47 -> 0 | R47: =Q47*C47 -> 0 | T47: =S47*C47 -> 0 | V47: =U47*C47 -> 0 | X47: =W47*C47 -> 0
B48: CACAHUATE | C48: 13 | D48: 25 | F48: =E48*C48 -> 0 | H48: =G48*C48 -> 0 | J48: =I48*C48 -> 0 | L48: =K48*C48 -> 0 | P48: =O48*C48 -> 0 | R48: =Q48*C48 -> 0 | T48: =S48*C48 -> 0 | V48: =U48*C48 -> 0 | X48: =W48*C48 -> 0
B49: CHICARRON | C49: 11 | D49: 35 | F49: =E49*C49 -> 0 | H49: =G49*C49 -> 0 | J49: =I49*C49 -> 0 | L49: =K49*C49 -> 0 | P49: =O49*C49 -> 0 | R49: =Q49*C49 -> 0 | T49: =S49*C49 -> 0 | V49: =U49*C49 -> 0 | X49: =W49*C49 -> 0
B50: SEMILLAS | C50: 10 | D50: 15 | F50: =E50*C50 -> 0 | H50: =G50*C50 -> 0 | J50: =I50*C50 -> 0 | L50: =K50*C50 -> 0 | P50: =O50*C50 -> 0 | R50: =Q50*C50 -> 0 | T50: =S50*C50 -> 0 | V50: =U50*C50 -> 0 | X50: =W50*C50 -> 0
B51: PAPAS | C51: 14.8 | D51: 35 | F51: =E51*C51 -> 0 | H51: =G51*C51 -> 0 | J51: =I51*C51 -> 0 | L51: =K51*C51 -> 0 | P51: =O51*C51 -> 0 | R51: =Q51*C51 -> 0 | T51: =S51*C51 -> 0 | V51: =U51*C51 -> 0 | X51: =W51*C51 -> 0
B52: COCA 355 | C52: 13 | D52: 20 | F52: =E52*C52 -> 0 | H52: =G52*C52 -> 0 | J52: =I52*C52 -> 0 | L52: =K52*C52 -> 0 | P52: =O52*C52 -> 0 | R52: =Q52*C52 -> 0 | T52: =S52*C52 -> 0 | V52: =U52*C52 -> 0 | X52: =W52*C52 -> 0
B53: PEÑAFIEL 355 | C53: 11 | D53: 20 | F53: =E53*C53 -> 0 | H53: =G53*C53 -> 0 | J53: =I53*C53 -> 0 | L53: =K53*C53 -> 0 | P53: =O53*C53 -> 0 | R53: =Q53*C53 -> 0 | T53: =S53*C53 -> 0 | V53: =U53*C53 -> 0 | X53: =W53*C53 -> 0
... B62: CHICLES | C62: 28 | D62: 50 | F62: =E62*C62 -> 0 | H62: =G62*C62 -> 0 | J62: =I62*C62 -> 0 | L62: =K62*C62 -> 0 | P62: =O62*C62 -> 0 | R62: =Q62*C62 -> 0 | T62: =S62*C62 -> 0 | V62: =U62*C62 -> 0 | X62: =W62*C62 -> 0
F63: =E63*C63 -> 0 | H63: =G63*C63 -> 0 | J63: =I63*C63 -> 0 | L63: =K63*C63 -> 0 | P63: =O63*C63 -> 0 | R63: =Q63*C63 -> 0 | T63: =S63*C63 -> 0 | V63: =U63*C63 -> 0 | X63: =W63*C63 -> 0
F64: =E64*C64 -> 0 | H64: =G64*C64 -> 0 | J64: =I64*C64 -> 0 | L64: =K64*C64 -> 0 | P64: =O64*C64 -> 0 | R64: =Q64*C64 -> 0 | T64: =S64*C64 -> 0 | V64: =U64*C64 -> 0 | X64: =W64*C64 -> 0
F65: =E65*C65 -> 0 | H65: =G65*C65 -> 0 | J65: =I65*C65 -> 0 | L65: =K65*C65 -> 0 | P65: =O65*C65 -> 0 | R65: =Q65*C65 -> 0 | T65: =S65*C65 -> 0 | V65: =U65*C65 -> 0 | X65: =W65*C65 -> 0
E66: =E36 -> ELOY | F66: =SUM(F38:F65) -> 1 | G66: =G36 -> NUBIA | H66: =SUM(H38:H65) -> 0 | I66: =I36 -> MARCE | J66: =SUM(J38:J65) -> 0 | K66: =K36 -> ISELA | L66: =SUM(L38:L65) -> 0 | O66: =O36 -> VIKY | P66: =SUM(P38:P65) -> 0 | Q66: =Q36 -> 4 | R66: =SUM(R38:R65) -> 0 | S66: =S36 -> 5 | T66: =SUM(T38:T65) -> 0 | U66: =U36 -> 6 | V66: =SUM(V38:V65) -> 0 | W66: =W36 -> 7 | X66: =SUM(X38:X65) -> 0
B68: =B155 -> 46187
B69: VENTA DE FICHAS
B70: NOMBRE | E70: PRECIO | F70: PRODUCTO | H70: 60 | I70: 80 | J70: TOTAL | K70: VENTA | O70: COMISION | Q70: VENTA TOTAL
B71: =G36 -> NUBIA | E71: 120 | F71: MEDIA LAGER | J71: =H71+I71 -> 0 | K71: =J71*E71 -> 0 | O71: =H71*H70+I71*I70 -> 0
F72: MEDIA AZUL | J72: =H72+I72 -> 0 | K72: =J72*E71 -> 0 | O72: =H72*H70+I72*I70 -> 0
B73: PAGO DE COMISION | E73: 300 | F73: MEGA LAGER | K73: =H73*E73 -> 0 | O73: =H73*150 -> 0
B74: =O71+O72+O73+O74+O75 -> 0 | F74: MEGA AZUL | K74: =H74*E73 -> 0 | O74: =H74*150 -> 0 | Q74: =K71+K72+K73+K74+K75 -> 0
F75: MEGA ROJA | K75: =H75*E73 -> 0 | O75: =H75*150 -> 0
B76: NOMBRE | E76: PRECIO | F76: PRODUCTO | H76: 60 | I76: 80 | J76: TOTAL | K76: VENTA | O76: COMISION | Q76: VENTA TOTAL
B77: =I36 -> MARCE | E77: 120 | F77: MEDIA LAGER | J77: =H77+I77 -> 0 | K77: =J77*E77 -> 0 | O77: =H77*H76+I77*I76 -> 0
F78: MEDIA AZUL | J78: =H78+I78 -> 0 | K78: =J78*E77 -> 0 | O78: =H78*H76+I78*I76 -> 0
B79: PAGO DE COMISION | E79: 300 | F79: MEGA LAGER | K79: =H79*E79 -> 0 | O79: =H79*150 -> 0
B80: =O77+O78+O79+O80+O81 -> 0 | F80: MEGA AZUL | K80: =H80*E79 -> 0 | O80: =H80*150 -> 0 | Q80: =K77+K78+K79+K80+K81 -> 0
F81: MEGA ROJA | K81: =H81*E79 -> 0 | O81: =H81*150 -> 0
B82: NOMBRE | E82: PRECIO | F82: PRODUCTO | H82: 60 | I82: 80 | J82: TOTAL | K82: VENTA | O82: COMISION | Q82: VENTA TOTAL
B83: =K36 -> ISELA | E83: 120 | F83: MEDIA LAGER | J83: =H83+I83 -> 0 | K83: =J83*E83 -> 0 | O83: =H83*H82+I83*I82 -> 0
F84: MEDIA AZUL | J84: =H84+I84 -> 0 | K84: =J84*E83 -> 0 | O84: =H84*H82+I84*I82 -> 0
B85: PAGO DE COMISION | E85: 300 | F85: MEGA LAGER | K85: =H85*E85 -> 0 | O85: =H85*150 -> 0
B86: =O83+O84+O85+O86+O87 -> 0 | F86: MEGA AZUL | K86: =H86*E85 -> 0 | O86: =H86*150 -> 0 | Q86: =K83+K84+K85+K86+K87 -> 0
F87: MEGA ROJA | K87: =H87*E85 -> 0 | O87: =H87*150 -> 0
B88: NOMBRE | E88: PRECIO | F88: PRODUCTO | H88: 60 | I88: 80 | J88: TOTAL | K88: VENTA | O88: COMISION | Q88: VENTA TOTAL
B89: =O36 -> VIKY | E89: 120 | F89: MEDIA LAGER | J89: =H89+I89 -> 0 | K89: =J89*E89 -> 0 | O89: =H89*H88+I89*I88 -> 0
F90: MEDIA AZUL | J90: =H90+I90 -> 0 | K90: =J90*E89 -> 0 | O90: =H90*H88+I90*I88 -> 0
B91: PAGO DE COMISION | E91: 300 | F91: MEGA LAGER | K91: =H91*E91 -> 0 | O91: =H91*150 -> 0
B92: =O89+O90+O91+O92+O93 -> 0 | F92: MEGA AZUL | K92: =H92*E91 -> 0 | O92: =H92*150 -> 0 | Q92: =K89+K90+K91+K92+K93 -> 0
F93: MEGA ROJA | K93: =H93*E91 -> 0 | O93: =H93*150 -> 0
B94: NOMBRE | E94: PRECIO | F94: PRODUCTO | H94: 60 | I94: 80 | J94: TOTAL | K94: VENTA | O94: COMISION | Q94: VENTA TOTAL
B95: =Q36 -> 4 | E95: 120 | F95: MEDIA LAGER | J95: =H95+I95 -> 0 | K95: =J95*E95 -> 0 | O95: =H95*H94+I95*I94 -> 0
F96: MEDIA AZUL | J96: =H96+I96 -> 0 | K96: =J96*E95 -> 0 | O96: =H96*H94+I96*I94 -> 0
B97: PAGO DE COMISION | E97: 300 | F97: MEGA LAGER | K97: =H97*E97 -> 0 | O97: =H97*150 -> 0
B98: =O95+O96+O97+O98+O99 -> 0 | F98: MEGA AZUL | K98: =H98*E97 -> 0 | O98: =H98*150 -> 0 | Q98: =K95+K96+K97+K98+K99 -> 0
F99: MEGA ROJA | K99: =H99*E97 -> 0 | O99: =H99*150 -> 0
B100: NOMBRE | E100: PRECIO | F100: PRODUCTO | H100: 60 | I100: 80 | J100: TOTAL | K100: VENTA | O100: COMISION | Q100: VENTA TOTAL
B101: =S36 -> 5 | E101: 120 | F101: MEDIA LAGER | J101: =H101+I101 -> 0 | K101: =J101*E101 -> 0 | O101: =H101*H100+I101*I100 -> 0
F102: MEDIA AZUL | J102: =H102+I102 -> 0 | K102: =J102*E101 -> 0 | O102: =H102*H100+I102*I100 -> 0
B103: PAGO DE COMISION | E103: 300 | F103: MEGA LAGER | K103: =H103*E103 -> 0 | O103: =H103*150 -> 0
B104: =O101+O102+O103+O104+O105 -> 0 | F104: MEGA AZUL | K104: =H104*E103 -> 0 | O104: =H104*150 -> 0 | Q104: =K101+K102+K103+K104+K105 -> 0
F105: MEGA ROJA | K105: =H105*E103 -> 0 | O105: =H105*150 -> 0
B106: NOMBRE | E106: PRECIO | F106: PRODUCTO | H106: 60 | I106: 80 | J106: TOTAL | K106: VENTA | O106: COMISION | Q106: VENTA TOTAL
B107: =U36 -> 6 | E107: 120 | F107: MEDIA LAGER | J107: =H107+I107 -> 0 | K107: =J107*E107 -> 0 | O107: =H107*H106+I107*I106 -> 0
F108: MEDIA AZUL | J108: =H108+I108 -> 0 | K108: =J108*E107 -> 0 | O108: =H108*H106+I108*I106 -> 0
B109: PAGO DE COMISION | E109: 300 | F109: MEGA LAGER | K109: =H109*E109 -> 0 | O109: =H109*150 -> 0
B110: =O107+O108+O109+O110+O111 -> 0 | F110: MEGA AZUL | K110: =H110*E109 -> 0 | O110: =H110*150 -> 0 | Q110: =K107+K108+K109+K110+K111 -> 0
...

Sheet SABADO 13
B1: =B155 -> 46185
B2: VENTA PUBLICO
B3: PRODUCTO | C3: $ COMPRA | D3: $ VENTA | E3: CANT | F3: $ | G3: CORTESIAS | I3: PRODUCTO | M3: $ COMPRA | N3: $ VENTA | O3: CANT | P3: $ | Q3: CORTESIAS
B4: MEDIA LAGER | C4: 15 | D4: 30 | F4: =E4*D4 -> 0 | H4: =G4*C4 -> 0 | I4: CIGARRO | M4: 6 | N4: 10 | P4: =O4*N4 -> 0
B5: MEDIA AZUL | C5: 14 | D5: 30 | F5: =E5*D5 -> 0 | H5: =G5*C5 -> 0 | I5: CACAHUATE | M5: 13 | N5: 25 | P5: =O5*N5 -> 0 | R5: =Q5*M5 -> 0
B6: MEDIA VICTORIA | C6: 17 | D6: 35 | F6: =E6*D6 -> 0 | H6: =G6*C6 -> 0 | I6: CHICARRON | M6: 11 | N6: 35 | P6: =O6*N6 -> 0 | R6: =Q6*M6 -> 0
B7: MEDIA CORONA | C7: 17 | D7: 35 | F7: =E7*D7 -> 0 | H7: =G7*C7 -> 0 | I7: SEMILLAS | M7: 10 | N7: 15 | P7: =O7*N7 -> 0 | R7: =Q7*M7 -> 0
B8: MEGA LAGER | C8: 37 | D8: 70 | F8: =E8*D8 -> 0 | H8: =G8*C8 -> 0 | I8: CANCION | M8: 0 | N8: 10 | P8: =O8*N8 -> 0 | R8: =Q8*M8 -> 0
B9: MEGA ROJA | C9: 35 | D9: 60 | F9: =E9*D9 -> 0 | H9: =G9*C9 -> 0 | I9: PAPAS | M9: 14.8 | N9: 35 | P9: =O9*N9 -> 0 | R9: =Q9*M9 -> 0
B10: MEGA AZUL | C10: 35 | D10: 60 | F10: =E10*D10 -> 0 | H10: =G10*C10 -> 0 | I10: COCA 355 | M10: 13 | N10: 20 | P10: =O10*N10 -> 0 | R10: =Q10*M10 -> 0
B11: MEGA VICTORIA | C11: 41 | D11: 80 | F11: =E11*D11 -> 0 | H11: =G11*C11 -> 0 | I11: PEÑAFIEL 355 | M11: 11 | N11: 20 | P11: =O11*N11 -> 0 | R11: =Q11*M11 -> 0
B12: MEGA CORONA | C12: 41 | D12: 80 | F12: =E12*D12 -> 0 | H12: =G12*C12 -> 0 | I12: TORONJA 355 | M12: 10 | N12: 20 | P12: =O12*N12 -> 0 | R12: =Q12*M12 -> 0
B13: CUBO MEDIA LAGER (6) | C13: =14*6 -> 84 | D13: 160 | F13: =E13*D13 -> 0 | I13: BOOS | M13: 40 | N13: 60 | P13: =O13*N13 -> 0
B14: CUBO MEDIA AZUL (6) | C14: =14*6 -> 84 | D14: 160 | F14: =E14*D14 -> 0 | I14: NEWMIX PALOMA | M14: 25 | N14: 45 | P14: =O14*N14 -> 0
B15: CUBO MEDIA VICTORIA (6) | C15: =17*6 -> 102 | D15: 180 | F15: =E15*D15 -> 0 | I15: NEWMIX VAMPIRO | M15: 25 | N15: 45 | P15: =O15*N15 -> 0
B16: CUBO MEDIA CORONA (6) | C16: =17*6 -> 102 | D16: 180 | F16: =E16*D16 -> 0 | I16: CLAMATO (Botella) | M16: 35 | N16: 50 | P16: =O16*N16 -> 0 | R16: =Q16*M16 -> 0
B17: PROMO MEGA LAGER (3) | C17: =37*3 -> 111 | D17: 195 | F17: =E17*D17 -> 0 | I17: CLAMATO (Preparado vaso) | M17: 27 | N17: 45 | P17: =O17*N17 -> 0 | R17: =Q17*M17 -> 0
B18: PROMO MEGA ROJA (3) | C18: =35*3 -> 105 | D18: 165 | F18: =E18*D18 -> 0 | I18: PREPARADO SALSAS (Vaso) | M18: 10 | N18: 25 | P18: =O18*N18 -> 0 | R18: =Q18*M18 -> 0
B19: PROMO MEGA AZUL (3) | C19: =35*3 -> 105 | D19: 165 | F19: =E19*D19 -> 0 | I19: SOPA | M19: 14 | N19: 35 | P19: =O19*N19 -> 0 | R19: =Q19*M19 -> 0
B20: PROMO MEGA VICTORIA (3) | C20: =41*3 -> 123 | D20: 225 | F20: =E20*D20 -> 0 | I20: BOTANA JAMON | M20: 40 | N20: 70 | P20: =O20*N20 -> 0 | R20: =Q20*M20 -> 0
B21: PROMO MEGA CORONA (3) | C21: =41*3 -> 123 | D21: 225 | F21: =E21*D21 -> 0 | I21: MANGUITO | M21: 8 | N21: 15 | P21: =O21*N21 -> 0 | R21: =Q21*M21 -> 0
B22: MICHE LAGER (2 MEDIAS) | C22: 40 | D22: 95 | F22: =E22*D22 -> 0 | I22: CHICLES | M22: 28 | N22: 50 | P22: =O22*N22 -> 0 | R22: =Q22*M22 -> 0
B23: MICHE AZUL (2 MEDIAS) | C23: 40 | D23: 95 | F23: =E23*D23 -> 0 | H23: =G23*C23 -> 0 | I23: DESCORCHE | N23: 300 | P23: =O23*N23 -> 0
B24: MICHE VICTORIA (2 MEDIAS) | C24: 45 | D24: 95 | F24: =E24*D24 -> 0 | H24: =G24*C24 -> 0 | I24: SALSA VALENTINA (CHICA) | M24: 17 | N24: 35 | P24: =O24*N24 -> 0 | R24: =Q24*M24 -> 0
B25: MICHE CORONA (2 MEDIAS) | C25: 45 | D25: 95 | F25: =E25*D25 -> 0 | H25: =G25*C25 -> 0 | I25: VASO ROTO | N25: 35 | P25: =O25*N25 -> 0
B26: COPA $50 | C26: 25 | D26: 50 | F26: =E26*D26 -> 0 | H26: =G26*C26 -> 0 | P26: =O26*N26 -> 0
B27: COPA $70 | C27: 30 | D27: 70 | F27: =E27*D27 -> 0 | H27: =G27*C27 -> 0 | P27: =O27*N27 -> 0
B28: COPA $100 | C28: 50 | D28: 100 | F28: =E28*D28 -> 0 | H28: =G28*C28 -> 0 | P28: =O28*N28 -> 0
B29: COPA $120 | C29: 70 | D29: 120 | F29: =E29*D29 -> 0 | H29: =G29*C29 -> 0 | P29: =O29*N29 -> 0
B30: COPA $150 | C30: 100 | D30: 150 | F30: =E30*D30 -> 0 | H30: =G30*C30 -> 0 | P30: =O30*N30 -> 0
B31: AZULITO | C31: 40 | D31: 95 | F31: =E31*D31 -> 0 | H31: =G31*C31 -> 0 | P31: =O31*N31 -> 0
B32: TOTAL DE VENTA | G32: =SUM(F4:F31,P4:P31) -> 0 | I32: TOTAL DE CORTESIAS | Q32: =SUM(H4:H31,R4:R31) -> 0
B34: =B155 -> 46185
B35: VENTA PERSONAL
B36: PRODUCTO | C36: $ COMPRA | D36: $ VENTA | E36: ELOY | G36: NUBIA | I36: MARCE | K36: ISELA | O36: VIKY | Q36: 4 | S36: 5 | U36: 6 | W36: 7
E37: CANT | F37: $ | G37: CANT | H37: $ | I37: CANT | J37: $ | K37: CANT | L37: $ | O37: CANT | P37: $ | Q37: CANT | R37: $ | S37: CANT | T37: $ | U37: CANT | V37: $ | W37: CANT | X37: $
B38: MEDIA LAGER | C38: 15 | D38: 30 | F38: =E38*C38 -> 0 | H38: =G38*C38 -> 0 | J38: =I38*C38 -> 0 | L38: =K38*C38 -> 0 | P38: =O38*C38 -> 0 | R38: =Q38*C38 -> 0 | T38: =S38*C38 -> 0 | V38: =U38*C38 -> 0 | X38: =W38*C38 -> 0
B39: MEDIA AZUL | C39: 14 | D39: 30 | F39: =E39*C39 -> 0 | H39: =G39*C39 -> 0 | J39: =I39*C39 -> 0 | L39: =K39*C39 -> 0 | P39: =O39*C39 -> 0 | R39: =Q39*C39 -> 0 | T39: =S39*C39 -> 0 | V39: =U39*C39 -> 0 | X39: =W39*C39 -> 0
B40: MEDIA VICTORIA | C40: 17 | D40: 35 | F40: =E40*C40 -> 0 | H40: =G40*C40 -> 0 | J40: =I40*C40 -> 0 | L40: =K40*C40 -> 0 | P40: =O40*C40 -> 0 | R40: =Q40*C40 -> 0 | T40: =S40*C40 -> 0 | V40: =U40*C40 -> 0 | X40: =W40*C40 -> 0
B41: MEDIA CORONA | C41: 17 | D41: 35 | F41: 1 | H41: =G41*C41 -> 0 | J41: =I41*C41 -> 0 | L41: =K41*C41 -> 0 | P41: =O41*C41 -> 0 | R41: =Q41*C41 -> 0 | T41: =S41*C41 -> 0 | V41: =U41*C41 -> 0 | X41: =W41*C41 -> 0
B42: MEGA LAGER | C42: 37 | D42: 70 | F42: =E42*C42 -> 0 | H42: =G42*C42 -> 0 | J42: =I42*C42 -> 0 | L42: =K42*C42 -> 0 | P42: =O42*C42 -> 0 | R42: =Q42*C42 -> 0 | T42: =S42*C42 -> 0 | V42: =U42*C42 -> 0 | X42: =W42*C42 -> 0
B43: MEGA ROJA | C43: 35 | D43: 60 | F43: =E43*C43 -> 0 | H43: =G43*C43 -> 0 | J43: =I43*C43 -> 0 | L43: =K43*C43 -> 0 | P43: =O43*C43 -> 0 | R43: =Q43*C43 -> 0 | T43: =S43*C43 -> 0 | V43: =U43*C43 -> 0 | X43: =W43*C43 -> 0
B44: MEGA AZUL | C44: 35 | D44: 60 | F44: =E44*C44 -> 0 | H44: =G44*C44 -> 0 | J44: =I44*C44 -> 0 | L44: =K44*C44 -> 0 | P44: =O44*C44 -> 0 | R44: =Q44*C44 -> 0 | T44: =S44*C44 -> 0 | V44: =U44*C44 -> 0 | X44: =W44*C44 -> 0
B45: MEGA VICTORIA | C45: 41 | D45: 80 | F45: =E45*C45 -> 0 | H45: =G45*C45 -> 0 | J45: =I45*C45 -> 0 | L45: =K45*C45 -> 0 | P45: =O45*C45 -> 0 | R45: =Q45*C45 -> 0 | T45: =S45*C45 -> 0 | V45: =U45*C45 -> 0 | X45: =W45*C45 -> 0
B46: MEGA CORONA | C46: 41 | D46: 80 | F46: =E46*C46 -> 0 | H46: =G46*C46 -> 0 | J46: =I46*C46 -> 0 | L46: =K46*C46 -> 0 | P46: =O46*C46 -> 0 | R46: =Q46*C46 -> 0 | T46: =S46*C46 -> 0 | V46: =U46*C46 -> 0 | X46: =W46*C46 -> 0
B47: CIGARRO | C47: 6 | D47: 10 | F47: =E47*C47 -> 0 | H47: =G47*C47 -> 0 | J47: =I47*C47 -> 0 | L47: =K47*C47 -> 0 | P47: =O47*C47 -> 0 | R47: =Q47*C47 -> 0 | T47: =S47*C47 -> 0 | V47: =U47*C47 -> 0 | X47: =W47*C47 -> 0
B48: CACAHUATE | C48: 13 | D48: 25 | F48: =E48*C48 -> 0 | H48: =G48*C48 -> 0 | J48: =I48*C48 -> 0 | L48: =K48*C48 -> 0 | P48: =O48*C48 -> 0 | R48: =Q48*C48 -> 0 | T48: =S48*C48 -> 0 | V48: =U48*C48 -> 0 | X48: =W48*C48 -> 0
B49: CHICARRON | C49: 11 | D49: 35 | F49: =E49*C49 -> 0 | H49: =G49*C49 -> 0 | J49: =I49*C49 -> 0 | L49: =K49*C49 -> 0 | P49: =O49*C49 -> 0 | R49: =Q49*C49 -> 0 | T49: =S49*C49 -> 0 | V49: =U49*C49 -> 0 | X49: =W49*C49 -> 0
B50: SEMILLAS | C50: 10 | D50: 15 | F50: =E50*C50 -> 0 | H50: =G50*C50 -> 0 | J50: =I50*C50 -> 0 | L50: =K50*C50 -> 0 | P50: =O50*C50 -> 0 | R50: =Q50*C50 -> 0 | T50: =S50*C50 -> 0 | V50: =U50*C50 -> 0 | X50: =W50*C50 -> 0
B51: PAPAS | C51: 14.8 | D51: 35 | F51: =E51*C51 -> 0 | H51: =G51*C51 -> 0 | J51: =I51*C51 -> 0 | L51: =K51*C51 -> 0 | P51: =O51*C51 -> 0 | R51: =Q51*C51 -> 0 | T51: =S51*C51 -> 0 | V51: =U51*C51 -> 0 | X51: =W51*C51 -> 0
B52: COCA 355 | C52: 13 | D52: 20 | F52: =E52*C52 -> 0 | H52: =G52*C52 -> 0 | J52: =I52*C52 -> 0 | L52: =K52*C52 -> 0 | P52: =O52*C52 -> 0 | R52: =Q52*C52 -> 0 | T52: =S52*C52 -> 0 | V52: =U52*C52 -> 0 | X52: =W52*C52 -> 0
B53: PEÑAFIEL 355 | C53: 11 | D53: 20 | F53: =E53*C53 -> 0 | H53: =G53*C53 -> 0 | J53: =I53*C53 -> 0 | L53: =K53*C53 -> 0 | P53: =O53*C53 -> 0 | R53: =Q53*C53 -> 0 | T53: =S53*C53 -> 0 | V53: =U53*C53 -> 0 | X53: =W53*C53 -> 0
... B62: CHICLES | C62: 28 | D62: 50 | F62: =E62*C62 -> 0 | H62: =G62*C62 -> 0 | J62: =I62*C62 -> 0 | L62: =K62*C62 -> 0 | P62: =O62*C62 -> 0 | R62: =Q62*C62 -> 0 | T62: =S62*C62 -> 0 | V62: =U62*C62 -> 0 | X62: =W62*C62 -> 0
F63: =E63*C63 -> 0 | H63: =G63*C63 -> 0 | J63: =I63*C63 -> 0 | L63: =K63*C63 -> 0 | P63: =O63*C63 -> 0 | R63: =Q63*C63 -> 0 | T63: =S63*C63 -> 0 | V63: =U63*C63 -> 0 | X63: =W63*C63 -> 0
F64: =E64*C64 -> 0 | H64: =G64*C64 -> 0 | J64: =I64*C64 -> 0 | L64: =K64*C64 -> 0 | P64: =O64*C64 -> 0 | R64: =Q64*C64 -> 0 | T64: =S64*C64 -> 0 | V64: =U64*C64 -> 0 | X64: =W64*C64 -> 0
F65: =E65*C65 -> 0 | H65: =G65*C65 -> 0 | J65: =I65*C65 -> 0 | L65: =K65*C65 -> 0 | P65: =O65*C65 -> 0 | R65: =Q65*C65 -> 0 | T65: =S65*C65 -> 0 | V65: =U65*C65 -> 0 | X65: =W65*C65 -> 0
E66: =E36 -> ELOY | F66: =SUM(F38:F65) -> 1 | G66: =G36 -> NUBIA | H66: =SUM(H38:H65) -> 0 | I66: =I36 -> MARCE | J66: =SUM(J38:J65) -> 0 | K66: =K36 -> ISELA | L66: =SUM(L38:L65) -> 0 | O66: =O36 -> VIKY | P66: =SUM(P38:P65) -> 0 | Q66: =Q36 -> 4 | R66: =SUM(R38:R65) -> 0 | S66: =S36 -> 5 | T66: =SUM(T38:T65) -> 0 | U66: =U36 -> 6 | V66: =SUM(V38:V65) -> 0 | W66: =W36 -> 7 | X66: =SUM(X38:X65) -> 0
B68: =B155 -> 46185
B69: VENTA DE FICHAS
B70: NOMBRE | E70: PRECIO | F70: PRODUCTO | H70: 60 | I70: 80 | J70: TOTAL | K70: VENTA | O70: COMISION | Q70: VENTA TOTAL
B71: =G36 -> NUBIA | E71: 120 | F71: MEDIA LAGER | J71: =H71+I71 -> 0 | K71: =J71*E71 -> 0 | O71: =H71*H70+I71*I70 -> 0
F72: MEDIA AZUL | J72: =H72+I72 -> 0 | K72: =J72*E71 -> 0 | O72: =H72*H70+I72*I70 -> 0
B73: PAGO DE COMISION | E73: 300 | F73: MEGA LAGER | K73: =H73*E73 -> 0 | O73: =H73*150 -> 0
B74: =O71+O72+O73+O74+O75 -> 0 | F74: MEGA AZUL | K74: =H74*E73 -> 0 | O74: =H74*150 -> 0 | Q74: =K71+K72+K73+K74+K75 -> 0
F75: MEGA ROJA | K75: =H75*E73 -> 0 | O75: =H75*150 -> 0
B76: NOMBRE | E76: PRECIO | F76: PRODUCTO | H76: 60 | I76: 80 | J76: TOTAL | K76: VENTA | O76: COMISION | Q76: VENTA TOTAL
B77: =I36 -> MARCE | E77: 120 | F77: MEDIA LAGER | J77: =H77+I77 -> 0 | K77: =J77*E77 -> 0 | O77: =H77*H76+I77*I76 -> 0
F78: MEDIA AZUL | J78: =H78+I78 -> 0 | K78: =J78*E77 -> 0 | O78: =H78*H76+I78*I76 -> 0
B79: PAGO DE COMISION | E79: 300 | F79: MEGA LAGER | K79: =H79*E79 -> 0 | O79: =H79*150 -> 0
B80: =O77+O78+O79+O80+O81 -> 0 | F80: MEGA AZUL | K80: =H80*E79 -> 0 | O80: =H80*150 -> 0 | Q80: =K77+K78+K79+K80+K81 -> 0
F81: MEGA ROJA | K81: =H81*E79 -> 0 | O81: =H81*150 -> 0
B82: NOMBRE | E82: PRECIO | F82: PRODUCTO | H82: 60 | I82: 80 | J82: TOTAL | K82: VENTA | O82: COMISION | Q82: VENTA TOTAL
B83: =K36 -> ISELA | E83: 120 | F83: MEDIA LAGER | J83: =H83+I83 -> 0 | K83: =J83*E83 -> 0 | O83: =H83*H82+I83*I82 -> 0
F84: MEDIA AZUL | J84: =H84+I84 -> 0 | K84: =J84*E83 -> 0 | O84: =H84*H82+I84*I82 -> 0
B85: PAGO DE COMISION | E85: 300 | F85: MEGA LAGER | K85: =H85*E85 -> 0 | O85: =H85*150 -> 0
B86: =O83+O84+O85+O86+O87 -> 0 | F86: MEGA AZUL | K86: =H86*E85 -> 0 | O86: =H86*150 -> 0 | Q86: =K83+K84+K85+K86+K87 -> 0
F87: MEGA ROJA | K87: =H87*E85 -> 0 | O87: =H87*150 -> 0
B88: NOMBRE | E88: PRECIO | F88: PRODUCTO | H88: 60 | I88: 80 | J88: TOTAL | K88: VENTA | O88: COMISION | Q88: VENTA TOTAL
B89: =O36 -> VIKY | E89: 120 | F89: MEDIA LAGER | J89: =H89+I89 -> 0 | K89: =J89*E89 -> 0 | O89: =H89*H88+I89*I88 -> 0
F90: MEDIA AZUL | J90: =H90+I90 -> 0 | K90: =J90*E89 -> 0 | O90: =H90*H88+I90*I88 -> 0
B91: PAGO DE COMISION | E91: 300 | F91: MEGA LAGER | K91: =H91*E91 -> 0 | O91: =H91*150 -> 0
B92: =O89+O90+O91+O92+O93 -> 0 | F92: MEGA AZUL | K92: =H92*E91 -> 0 | O92: =H92*150 -> 0 | Q92: =K89+K90+K91+K92+K93 -> 0
F93: MEGA ROJA | K93: =H93*E91 -> 0 | O93: =H93*150 -> 0
B94: NOMBRE | E94: PRECIO | F94: PRODUCTO | H94: 60 | I94: 80 | J94: TOTAL | K94: VENTA | O94: COMISION | Q94: VENTA TOTAL
B95: =Q36 -> 4 | E95: 120 | F95: MEDIA LAGER | J95: =H95+I95 -> 0 | K95: =J95*E95 -> 0 | O95: =H95*H94+I95*I94 -> 0
F96: MEDIA AZUL | J96: =H96+I96 -> 0 | K96: =J96*E95 -> 0 | O96: =H96*H94+I96*I94 -> 0
B97: PAGO DE COMISION | E97: 300 | F97: MEGA LAGER | K97: =H97*E97 -> 0 | O97: =H97*150 -> 0
B98: =O95+O96+O97+O98+O99 -> 0 | F98: MEGA AZUL | K98: =H98*E97 -> 0 | O98: =H98*150 -> 0 | Q98: =K95+K96+K97+K98+K99 -> 0
F99: MEGA ROJA | K99: =H99*E97 -> 0 | O99: =H99*150 -> 0
B100: NOMBRE | E100: PRECIO | F100: PRODUCTO | H100: 60 | I100: 80 | J100: TOTAL | K100: VENTA | O100: COMISION | Q100: VENTA TOTAL
B101: =S36 -> 5 | E101: 120 | F101: MEDIA LAGER | J101: =H101+I101 -> 0 | K101: =J101*E101 -> 0 | O101: =H101*H100+I101*I100 -> 0
F102: MEDIA AZUL | J102: =H102+I102 -> 0 | K102: =J102*E101 -> 0 | O102: =H102*H100+I102*I100 -> 0
B103: PAGO DE COMISION | E103: 300 | F103: MEGA LAGER | K103: =H103*E103 -> 0 | O103: =H103*150 -> 0
B104: =O101+O102+O103+O104+O105 -> 0 | F104: MEGA AZUL | K104: =H104*E103 -> 0 | O104: =H104*150 -> 0 | Q104: =K101+K102+K103+K104+K105 -> 0
F105: MEGA ROJA | K105: =H105*E103 -> 0 | O105: =H105*150 -> 0
B106: NOMBRE | E106: PRECIO | F106: PRODUCTO | H106: 60 | I106: 80 | J106: TOTAL | K106: VENTA | O106: COMISION | Q106: VENTA TOTAL
B107: =U36 -> 6 | E107: 120 | F107: MEDIA LAGER | J107: =H107+I107 -> 0 | K107: =J107*E107 -> 0 | O107: =H107*H106+I107*I106 -> 0
F108: MEDIA AZUL | J108: =H108+I108 -> 0 | K108: =J108*E107 -> 0 | O108: =H108*H106+I108*I106 -> 0
B109: PAGO DE COMISION | E109: 300 | F109: MEGA LAGER | K109: =H109*E109 -> 0 | O109: =H109*150 -> 0
B110: =O107+O108+O109+O110+O111 -> 0 | F110: MEGA AZUL | K110: =H110*E109 -> 0 | O110: =H110*150 -> 0 | Q110: =K107+K108+K109+K110+K111 -> 0
...

Sheet VIERNES 12
B1: =B155 -> 46185
B2: VENTA PUBLICO
B3: PRODUCTO | C3: $ COMPRA | D3: $ VENTA | E3: CANT | F3: $ | G3: CORTESIAS | I3: PRODUCTO | M3: $ COMPRA | N3: $ VENTA | O3: CANT | P3: $ | Q3: CORTESIAS
B4: MEDIA LAGER | C4: 15 | D4: 30 | F4: =E4*D4 -> 0 | H4: =G4*C4 -> 0 | I4: CIGARRO | M4: 6 | N4: 10 | P4: =O4*N4 -> 0
B5: MEDIA AZUL | C5: 14 | D5: 30 | F5: =E5*D5 -> 0 | H5: =G5*C5 -> 0 | I5: CACAHUATE | M5: 13 | N5: 25 | P5: =O5*N5 -> 0 | R5: =Q5*M5 -> 0
B6: MEDIA VICTORIA | C6: 17 | D6: 35 | F6: =E6*D6 -> 0 | H6: =G6*C6 -> 0 | I6: CHICARRON | M6: 11 | N6: 35 | P6: =O6*N6 -> 0 | R6: =Q6*M6 -> 0
B7: MEDIA CORONA | C7: 17 | D7: 35 | F7: =E7*D7 -> 0 | H7: =G7*C7 -> 0 | I7: SEMILLAS | M7: 10 | N7: 15 | P7: =O7*N7 -> 0 | R7: =Q7*M7 -> 0
B8: MEGA LAGER | C8: 37 | D8: 70 | F8: =E8*D8 -> 0 | H8: =G8*C8 -> 0 | I8: CANCION | M8: 0 | N8: 10 | P8: =O8*N8 -> 0 | R8: =Q8*M8 -> 0
B9: MEGA ROJA | C9: 35 | D9: 60 | F9: =E9*D9 -> 0 | H9: =G9*C9 -> 0 | I9: PAPAS | M9: 14.8 | N9: 35 | P9: =O9*N9 -> 0 | R9: =Q9*M9 -> 0
B10: MEGA AZUL | C10: 35 | D10: 60 | F10: =E10*D10 -> 0 | H10: =G10*C10 -> 0 | I10: COCA 355 | M10: 13 | N10: 20 | P10: =O10*N10 -> 0 | R10: =Q10*M10 -> 0
B11: MEGA VICTORIA | C11: 41 | D11: 80 | F11: =E11*D11 -> 0 | H11: =G11*C11 -> 0 | I11: PEÑAFIEL 355 | M11: 11 | N11: 20 | P11: =O11*N11 -> 0 | R11: =Q11*M11 -> 0
B12: MEGA CORONA | C12: 41 | D12: 80 | F12: =E12*D12 -> 0 | H12: =G12*C12 -> 0 | I12: TORONJA 355 | M12: 10 | N12: 20 | P12: =O12*N12 -> 0 | R12: =Q12*M12 -> 0
B13: CUBO MEDIA LAGER (6) | C13: =14*6 -> 84 | D13: 160 | F13: =E13*D13 -> 0 | I13: BOOS | M13: 40 | N13: 60 | P13: =O13*N13 -> 0
B14: CUBO MEDIA AZUL (6) | C14: =14*6 -> 84 | D14: 160 | F14: =E14*D14 -> 0 | I14: NEWMIX PALOMA | M14: 25 | N14: 45 | P14: =O14*N14 -> 0
B15: CUBO MEDIA VICTORIA (6) | C15: =17*6 -> 102 | D15: 180 | F15: =E15*D15 -> 0 | I15: NEWMIX VAMPIRO | M15: 25 | N15: 45 | P15: =O15*N15 -> 0
B16: CUBO MEDIA CORONA (6) | C16: =17*6 -> 102 | D16: 180 | F16: =E16*D16 -> 0 | I16: CLAMATO (Botella) | M16: 35 | N16: 50 | P16: =O16*N16 -> 0 | R16: =Q16*M16 -> 0
B17: PROMO MEGA LAGER (3) | C17: =37*3 -> 111 | D17: 195 | F17: =E17*D17 -> 0 | I17: CLAMATO (Preparado vaso) | M17: 27 | N17: 45 | P17: =O17*N17 -> 0 | R17: =Q17*M17 -> 0
B18: PROMO MEGA ROJA (3) | C18: =35*3 -> 105 | D18: 165 | F18: =E18*D18 -> 0 | I18: PREPARADO SALSAS (Vaso) | M18: 10 | N18: 25 | P18: =O18*N18 -> 0 | R18: =Q18*M18 -> 0
B19: PROMO MEGA AZUL (3) | C19: =35*3 -> 105 | D19: 165 | F19: =E19*D19 -> 0 | I19: SOPA | M19: 14 | N19: 35 | P19: =O19*N19 -> 0 | R19: =Q19*M19 -> 0
B20: PROMO MEGA VICTORIA (3) | C20: =41*3 -> 123 | D20: 225 | F20: =E20*D20 -> 0 | I20: BOTANA JAMON | M20: 40 | N20: 70 | P20: =O20*N20 -> 0 | R20: =Q20*M20 -> 0
B21: PROMO MEGA CORONA (3) | C21: =41*3 -> 123 | D21: 225 | F21: =E21*D21 -> 0 | I21: MANGUITO | M21: 8 | N21: 15 | P21: =O21*N21 -> 0 | R21: =Q21*M21 -> 0
B22: MICHE LAGER (2 MEDIAS) | C22: 40 | D22: 95 | F22: =E22*D22 -> 0 | I22: CHICLES | M22: 28 | N22: 50 | P22: =O22*N22 -> 0 | R22: =Q22*M22 -> 0
B23: MICHE AZUL (2 MEDIAS) | C23: 40 | D23: 95 | F23: =E23*D23 -> 0 | H23: =G23*C23 -> 0 | I23: DESCORCHE | N23: 300 | P23: =O23*N23 -> 0
B24: MICHE VICTORIA (2 MEDIAS) | C24: 45 | D24: 95 | F24: =E24*D24 -> 0 | H24: =G24*C24 -> 0 | I24: SALSA VALENTINA (CHICA) | M24: 17 | N24: 35 | P24: =O24*N24 -> 0 | R24: =Q24*M24 -> 0
B25: MICHE CORONA (2 MEDIAS) | C25: 45 | D25: 95 | F25: =E25*D25 -> 0 | H25: =G25*C25 -> 0 | I25: VASO ROTO | N25: 35 | P25: =O25*N25 -> 0
B26: COPA $50 | C26: 25 | D26: 50 | F26: =E26*D26 -> 0 | H26: =G26*C26 -> 0 | P26: =O26*N26 -> 0
B27: COPA $70 | C27: 30 | D27: 70 | F27: =E27*D27 -> 0 | H27: =G27*C27 -> 0 | P27: =O27*N27 -> 0
B28: COPA $100 | C28: 50 | D28: 100 | F28: =E28*D28 -> 0 | H28: =G28*C28 -> 0 | P28: =O28*N28 -> 0
B29: COPA $120 | C29: 70 | D29: 120 | F29: =E29*D29 -> 0 | H29: =G29*C29 -> 0 | P29: =O29*N29 -> 0
B30: COPA $150 | C30: 100 | D30: 150 | F30: =E30*D30 -> 0 | H30: =G30*C30 -> 0 | P30: =O30*N30 -> 0
B31: AZULITO | C31: 40 | D31: 95 | F31: =E31*D31 -> 0 | H31: =G31*C31 -> 0 | P31: =O31*N31 -> 0
B32: TOTAL DE VENTA | G32: =SUM(F4:F31,P4:P31) -> 0 | I32: TOTAL DE CORTESIAS | Q32: =SUM(H4:H31,R4:R31) -> 0
B34: =B155 -> 46185
B35: VENTA PERSONAL
B36: PRODUCTO | C36: $ COMPRA | D36: $ VENTA | E36: ELOY | G36: NUBIA | I36: MARCE | K36: ISELA | O36: VIKY | Q36: 4 | S36: 5 | U36: 6 | W36: 7
E37: CANT | F37: $ | G37: CANT | H37: $ | I37: CANT | J37: $ | K37: CANT | L37: $ | O37: CANT | P37: $ | Q37: CANT | R37: $ | S37: CANT | T37: $ | U37: CANT | V37: $ | W37: CANT | X37: $
B38: MEDIA LAGER | C38: 15 | D38: 30 | F38: =E38*C38 -> 0 | H38: =G38*C38 -> 0 | J38: =I38*C38 -> 0 | L38: =K38*C38 -> 0 | P38: =O38*C38 -> 0 | R38: =Q38*C38 -> 0 | T38: =S38*C38 -> 0 | V38: =U38*C38 -> 0 | X38: =W38*C38 -> 0
B39: MEDIA AZUL | C39: 14 | D39: 30 | F39: =E39*C39 -> 0 | H39: =G39*C39 -> 0 | J39: =I39*C39 -> 0 | L39: =K39*C39 -> 0 | P39: =O39*C39 -> 0 | R39: =Q39*C39 -> 0 | T39: =S39*C39 -> 0 | V39: =U39*C39 -> 0 | X39: =W39*C39 -> 0
B40: MEDIA VICTORIA | C40: 17 | D40: 35 | F40: =E40*C40 -> 0 | H40: =G40*C40 -> 0 | J40: =I40*C40 -> 0 | L40: =K40*C40 -> 0 | P40: =O40*C40 -> 0 | R40: =Q40*C40 -> 0 | T40: =S40*C40 -> 0 | V40: =U40*C40 -> 0 | X40: =W40*C40 -> 0
B41: MEDIA CORONA | C41: 17 | D41: 35 | F41: 1 | H41: =G41*C41 -> 0 | J41: =I41*C41 -> 0 | L41: =K41*C41 -> 0 | P41: =O41*C41 -> 0 | R41: =Q41*C41 -> 0 | T41: =S41*C41 -> 0 | V41: =U41*C41 -> 0 | X41: =W41*C41 -> 0
B42: MEGA LAGER | C42: 37 | D42: 70 | F42: =E42*C42 -> 0 | H42: =G42*C42 -> 0 | J42: =I42*C42 -> 0 | L42: =K42*C42 -> 0 | P42: =O42*C42 -> 0 | R42: =Q42*C42 -> 0 | T42: =S42*C42 -> 0 | V42: =U42*C42 -> 0 | X42: =W42*C42 -> 0
B43: MEGA ROJA | C43: 35 | D43: 60 | F43: =E43*C43 -> 0 | H43: =G43*C43 -> 0 | J43: =I43*C43 -> 0 | L43: =K43*C43 -> 0 | P43: =O43*C43 -> 0 | R43: =Q43*C43 -> 0 | T43: =S43*C43 -> 0 | V43: =U43*C43 -> 0 | X43: =W43*C43 -> 0
B44: MEGA AZUL | C44: 35 | D44: 60 | F44: =E44*C44 -> 0 | H44: =G44*C44 -> 0 | J44: =I44*C44 -> 0 | L44: =K44*C44 -> 0 | P44: =O44*C44 -> 0 | R44: =Q44*C44 -> 0 | T44: =S44*C44 -> 0 | V44: =U44*C44 -> 0 | X44: =W44*C44 -> 0
B45: MEGA VICTORIA | C45: 41 | D45: 80 | F45: =E45*C45 -> 0 | H45: =G45*C45 -> 0 | J45: =I45*C45 -> 0 | L45: =K45*C45 -> 0 | P45: =O45*C45 -> 0 | R45: =Q45*C45 -> 0 | T45: =S45*C45 -> 0 | V45: =U45*C45 -> 0 | X45: =W45*C45 -> 0
B46: MEGA CORONA | C46: 41 | D46: 80 | F46: =E46*C46 -> 0 | H46: =G46*C46 -> 0 | J46: =I46*C46 -> 0 | L46: =K46*C46 -> 0 | P46: =O46*C46 -> 0 | R46: =Q46*C46 -> 0 | T46: =S46*C46 -> 0 | V46: =U46*C46 -> 0 | X46: =W46*C46 -> 0
B47: CIGARRO | C47: 6 | D47: 10 | F47: =E47*C47 -> 0 | H47: =G47*C47 -> 0 | J47: =I47*C47 -> 0 | L47: =K47*C47 -> 0 | P47: =O47*C47 -> 0 | R47: =Q47*C47 -> 0 | T47: =S47*C47 -> 0 | V47: =U47*C47 -> 0 | X47: =W47*C47 -> 0
B48: CACAHUATE | C48: 13 | D48: 25 | F48: =E48*C48 -> 0 | H48: =G48*C48 -> 0 | J48: =I48*C48 -> 0 | L48: =K48*C48 -> 0 | P48: =O48*C48 -> 0 | R48: =Q48*C48 -> 0 | T48: =S48*C48 -> 0 | V48: =U48*C48 -> 0 | X48: =W48*C48 -> 0
B49: CHICARRON | C49: 11 | D49: 35 | F49: =E49*C49 -> 0 | H49: =G49*C49 -> 0 | J49: =I49*C49 -> 0 | L49: =K49*C49 -> 0 | P49: =O49*C49 -> 0 | R49: =Q49*C49 -> 0 | T49: =S49*C49 -> 0 | V49: =U49*C49 -> 0 | X49: =W49*C49 -> 0
B50: SEMILLAS | C50: 10 | D50: 15 | F50: =E50*C50 -> 0 | H50: =G50*C50 -> 0 | J50: =I50*C50 -> 0 | L50: =K50*C50 -> 0 | P50: =O50*C50 -> 0 | R50: =Q50*C50 -> 0 | T50: =S50*C50 -> 0 | V50: =U50*C50 -> 0 | X50: =W50*C50 -> 0
B51: PAPAS | C51: 14.8 | D51: 35 | F51: =E51*C51 -> 0 | H51: =G51*C51 -> 0 | J51: =I51*C51 -> 0 | L51: =K51*C51 -> 0 | P51: =O51*C51 -> 0 | R51: =Q51*C51 -> 0 | T51: =S51*C51 -> 0 | V51: =U51*C51 -> 0 | X51: =W51*C51 -> 0
B52: COCA 355 | C52: 13 | D52: 20 | F52: =E52*C52 -> 0 | H52: =G52*C52 -> 0 | J52: =I52*C52 -> 0 | L52: =K52*C52 -> 0 | P52: =O52*C52 -> 0 | R52: =Q52*C52 -> 0 | T52: =S52*C52 -> 0 | V52: =U52*C52 -> 0 | X52: =W52*C52 -> 0
B53: PEÑAFIEL 355 | C53: 11 | D53: 20 | F53: =E53*C53 -> 0 | H53: =G53*C53 -> 0 | J53: =I53*C53 -> 0 | L53: =K53*C53 -> 0 | P53: =O53*C53 -> 0 | R53: =Q53*C53 -> 0 | T53: =S53*C53 -> 0 | V53: =U53*C53 -> 0 | X53: =W53*C53 -> 0
... B62: CHICLES | C62: 28 | D62: 50 | F62: =E62*C62 -> 0 | H62: =G62*C62 -> 0 | J62: =I62*C62 -> 0 | L62: =K62*C62 -> 0 | P62: =O62*C62 -> 0 | R62: =Q62*C62 -> 0 | T62: =S62*C62 -> 0 | V62: =U62*C62 -> 0 | X62: =W62*C62 -> 0
F63: =E63*C63 -> 0 | H63: =G63*C63 -> 0 | J63: =I63*C63 -> 0 | L63: =K63*C63 -> 0 | P63: =O63*C63 -> 0 | R63: =Q63*C63 -> 0 | T63: =S63*C63 -> 0 | V63: =U63*C63 -> 0 | X63: =W63*C63 -> 0
F64: =E64*C64 -> 0 | H64: =G64*C64 -> 0 | J64: =I64*C64 -> 0 | L64: =K64*C64 -> 0 | P64: =O64*C64 -> 0 | R64: =Q64*C64 -> 0 | T64: =S64*C64 -> 0 | V64: =U64*C64 -> 0 | X64: =W64*C64 -> 0
F65: =E65*C65 -> 0 | H65: =G65*C65 -> 0 | J65: =I65*C65 -> 0 | L65: =K65*C65 -> 0 | P65: =O65*C65 -> 0 | R65: =Q65*C65 -> 0 | T65: =S65*C65 -> 0 | V65: =U65*C65 -> 0 | X65: =W65*C65 -> 0
E66: =E36 -> ELOY | F66: =SUM(F38:F65) -> 1 | G66: =G36 -> NUBIA | H66: =SUM(H38:H65) -> 0 | I66: =I36 -> MARCE | J66: =SUM(J38:J65) -> 0 | K66: =K36 -> ISELA | L66: =SUM(L38:L65) -> 0 | O66: =O36 -> VIKY | P66: =SUM(P38:P65) -> 0 | Q66: =Q36 -> 4 | R66: =SUM(R38:R65) -> 0 | S66: =S36 -> 5 | T66: =SUM(T38:T65) -> 0 | U66: =U36 -> 6 | V66: =SUM(V38:V65) -> 0 | W66: =W36 -> 7 | X66: =SUM(X38:X65) -> 0
B68: =B155 -> 46185
B69: VENTA DE FICHAS
B70: NOMBRE | E70: PRECIO | F70: PRODUCTO | H70: 60 | I70: 80 | J70: TOTAL | K70: VENTA | O70: COMISION | Q70: VENTA TOTAL
B71: =G36 -> NUBIA | E71: 120 | F71: MEDIA LAGER | J71: =H71+I71 -> 0 | K71: =J71*E71 -> 0 | O71: =H71*H70+I71*I70 -> 0
F72: MEDIA AZUL | J72: =H72+I72 -> 0 | K72: =J72*E71 -> 0 | O72: =H72*H70+I72*I70 -> 0
B73: PAGO DE COMISION | E73: 300 | F73: MEGA LAGER | K73: =H73*E73 -> 0 | O73: =H73*150 -> 0
B74: =O71+O72+O73+O74+O75 -> 0 | F74: MEGA AZUL | K74: =H74*E73 -> 0 | O74: =H74*150 -> 0 | Q74: =K71+K72+K73+K74+K75 -> 0
F75: MEGA ROJA | K75: =H75*E73 -> 0 | O75: =H75*150 -> 0
B76: NOMBRE | E76: PRECIO | F76: PRODUCTO | H76: 60 | I76: 80 | J76: TOTAL | K76: VENTA | O76: COMISION | Q76: VENTA TOTAL
B77: =I36 -> MARCE | E77: 120 | F77: MEDIA LAGER | J77: =H77+I77 -> 0 | K77: =J77*E77 -> 0 | O77: =H77*H76+I77*I76 -> 0
F78: MEDIA AZUL | J78: =H78+I78 -> 0 | K78: =J78*E77 -> 0 | O78: =H78*H76+I78*I76 -> 0
B79: PAGO DE COMISION | E79: 300 | F79: MEGA LAGER | K79: =H79*E79 -> 0 | O79: =H79*150 -> 0
B80: =O77+O78+O79+O80+O81 -> 0 | F80: MEGA AZUL | K80: =H80*E79 -> 0 | O80: =H80*150 -> 0 | Q80: =K77+K78+K79+K80+K81 -> 0
F81: MEGA ROJA | K81: =H81*E79 -> 0 | O81: =H81*150 -> 0
B82: NOMBRE | E82: PRECIO | F82: PRODUCTO | H82: 60 | I82: 80 | J82: TOTAL | K82: VENTA | O82: COMISION | Q82: VENTA TOTAL
B83: =K36 -> ISELA | E83: 120 | F83: MEDIA LAGER | J83: =H83+I83 -> 0 | K83: =J83*E83 -> 0 | O83: =H83*H82+I83*I82 -> 0
F84: MEDIA AZUL | J84: =H84+I84 -> 0 | K84: =J84*E83 -> 0 | O84: =H84*H82+I84*I82 -> 0
B85: PAGO DE COMISION | E85: 300 | F85: MEGA LAGER | K85: =H85*E85 -> 0 | O85: =H85*150 -> 0
B86: =O83+O84+O85+O86+O87 -> 0 | F86: MEGA AZUL | K86: =H86*E85 -> 0 | O86: =H86*150 -> 0 | Q86: =K83+K84+K85+K86+K87 -> 0
F87: MEGA ROJA | K87: =H87*E85 -> 0 | O87: =H87*150 -> 0
B88: NOMBRE | E88: PRECIO | F88: PRODUCTO | H88: 60 | I88: 80 | J88: TOTAL | K88: VENTA | O88: COMISION | Q88: VENTA TOTAL
B89: =O36 -> VIKY | E89: 120 | F89: MEDIA LAGER | J89: =H89+I89 -> 0 | K89: =J89*E89 -> 0 | O89: =H89*H88+I89*I88 -> 0
F90: MEDIA AZUL | J90: =H90+I90 -> 0 | K90: =J90*E89 -> 0 | O90: =H90*H88+I90*I88 -> 0
B91: PAGO DE COMISION | E91: 300 | F91: MEGA LAGER | K91: =H91*E91 -> 0 | O91: =H91*150 -> 0
B92: =O89+O90+O91+O92+O93 -> 0 | F92: MEGA AZUL | K92: =H92*E91 -> 0 | O92: =H92*150 -> 0 | Q92: =K89+K90+K91+K92+K93 -> 0
F93: MEGA ROJA | K93: =H93*E91 -> 0 | O93: =H93*150 -> 0
B94: NOMBRE | E94: PRECIO | F94: PRODUCTO | H94: 60 | I94: 80 | J94: TOTAL | K94: VENTA | O94: COMISION | Q94: VENTA TOTAL
B95: =Q36 -> 4 | E95: 120 | F95: MEDIA LAGER | J95: =H95+I95 -> 0 | K95: =J95*E95 -> 0 | O95: =H95*H94+I95*I94 -> 0
F96: MEDIA AZUL | J96: =H96+I96 -> 0 | K96: =J96*E95 -> 0 | O96: =H96*H94+I96*I94 -> 0
B97: PAGO DE COMISION | E97: 300 | F97: MEGA LAGER | K97: =H97*E97 -> 0 | O97: =H97*150 -> 0
B98: =O95+O96+O97+O98+O99 -> 0 | F98: MEGA AZUL | K98: =H98*E97 -> 0 | O98: =H98*150 -> 0 | Q98: =K95+K96+K97+K98+K99 -> 0
F99: MEGA ROJA | K99: =H99*E97 -> 0 | O99: =H99*150 -> 0
B100: NOMBRE | E100: PRECIO | F100: PRODUCTO | H100: 60 | I100: 80 | J100: TOTAL | K100: VENTA | O100: COMISION | Q100: VENTA TOTAL
B101: =S36 -> 5 | E101: 120 | F101: MEDIA LAGER | J101: =H101+I101 -> 0 | K101: =J101*E101 -> 0 | O101: =H101*H100+I101*I100 -> 0
F102: MEDIA AZUL | J102: =H102+I102 -> 0 | K102: =J102*E101 -> 0 | O102: =H102*H100+I102*I100 -> 0
B103: PAGO DE COMISION | E103: 300 | F103: MEGA LAGER | K103: =H103*E103 -> 0 | O103: =H103*150 -> 0
B104: =O101+O102+O103+O104+O105 -> 0 | F104: MEGA AZUL | K104: =H104*E103 -> 0 | O104: =H104*150 -> 0 | Q104: =K101+K102+K103+K104+K105 -> 0
F105: MEGA ROJA | K105: =H105*E103 -> 0 | O105: =H105*150 -> 0
B106: NOMBRE | E106: PRECIO | F106: PRODUCTO | H106: 60 | I106: 80 | J106: TOTAL | K106: VENTA | O106: COMISION | Q106: VENTA TOTAL
B107: =U36 -> 6 | E107: 120 | F107: MEDIA LAGER | J107: =H107+I107 -> 0 | K107: =J107*E107 -> 0 | O107: =H107*H106+I107*I106 -> 0
F108: MEDIA AZUL | J108: =H108+I108 -> 0 | K108: =J108*E107 -> 0 | O108: =H108*H106+I108*I106 -> 0
B109: PAGO DE COMISION | E109: 300 | F109: MEGA LAGER | K109: =H109*E109 -> 0 | O109: =H109*150 -> 0
B110: =O107+O108+O109+O110+O111 -> 0 | F110: MEGA AZUL | K110: =H110*E109 -> 0 | O110: =H110*150 -> 0 | Q110: =K107+K108+K109+K110+K111 -> 0
...

Sheet JUEVES 11
B1: =B155 -> 46184
B2: VENTA PUBLICO
B3: PRODUCTO | C3: $ COMPRA | D3: $ VENTA | E3: CANT | F3: $ | G3: CORTESIAS | I3: PRODUCTO | M3: $ COMPRA | N3: $ VENTA | O3: CANT | P3: $ | Q3: CORTESIAS
B4: MEDIA LAGER | C4: 15 | D4: 30 | E4: 9 | F4: =E4*D4 -> 270 | H4: =G4*C4 -> 0 | I4: CIGARRO | M4: 6 | N4: 10 | O4: 13 | P4: =O4*N4 -> 130
B5: MEDIA AZUL | C5: 14 | D5: 30 | F5: =E5*D5 -> 0 | H5: =G5*C5 -> 0 | I5: CACAHUATE | M5: 13 | N5: 25 | P5: =O5*N5 -> 0 | R5: =Q5*M5 -> 0
B6: MEDIA VICTORIA | C6: 17 | D6: 35 | F6: =E6*D6 -> 0 | G6: 2 | H6: =G6*C6 -> 34 | I6: CHICARRON | M6: 11 | N6: 35 | O6: 1 | P6: =O6*N6 -> 35 | R6: =Q6*M6 -> 0
B7: MEDIA CORONA | C7: 17 | D7: 35 | E7: 1 | F7: =E7*D7 -> 35 | H7: =G7*C7 -> 0 | I7: SEMILLAS | M7: 10 | N7: 15 | P7: =O7*N7 -> 0 | R7: =Q7*M7 -> 0
B8: MEGA LAGER | C8: 37 | D8: 70 | E8: 3 | F8: =E8*D8 -> 210 | G8: 3 | H8: =G8*C8 -> 111 | I8: CANCION | M8: 0 | N8: 10 | P8: =O8*N8 -> 0 | R8: =Q8*M8 -> 0
B9: MEGA ROJA | C9: 35 | D9: 60 | E9: 2 | F9: =E9*D9 -> 120 | H9: =G9*C9 -> 0 | I9: PAPAS | M9: 14.8 | N9: 35 | O9: 2 | P9: =O9*N9 -> 70 | R9: =Q9*M9 -> 0
B10: MEGA AZUL | C10: 35 | D10: 60 | E10: 4 | F10: =E10*D10 -> 240 | H10: =G10*C10 -> 0 | I10: COCA 355 | M10: 13 | N10: 20 | O10: 1 | P10: =O10*N10 -> 20 | R10: =Q10*M10 -> 0
B11: MEGA VICTORIA | C11: 41 | D11: 80 | F11: =E11*D11 -> 0 | H11: =G11*C11 -> 0 | I11: PEÑAFIEL 355 | M11: 11 | N11: 20 | P11: =O11*N11 -> 0 | R11: =Q11*M11 -> 0
B12: MEGA CORONA | C12: 41 | D12: 80 | F12: =E12*D12 -> 0 | H12: =G12*C12 -> 0 | I12: TORONJA 355 | M12: 10 | N12: 20 | P12: =O12*N12 -> 0 | R12: =Q12*M12 -> 0
B13: CUBO MEDIA LAGER (6) | C13: =14*6 -> 84 | D13: 160 | E13: 1 | F13: =E13*D13 -> 160 | I13: BOOS | M13: 40 | N13: 60 | P13: =O13*N13 -> 0
B14: CUBO MEDIA AZUL (6) | C14: =14*6 -> 84 | D14: 160 | F14: =E14*D14 -> 0 | I14: NEWMIX PALOMA | M14: 25 | N14: 45 | P14: =O14*N14 -> 0
B15: CUBO MEDIA VICTORIA (6) | C15: =17*6 -> 102 | D15: 180 | F15: =E15*D15 -> 0 | I15: NEWMIX VAMPIRO | M15: 25 | N15: 45 | P15: =O15*N15 -> 0
B16: CUBO MEDIA CORONA (6) | C16: =17*6 -> 102 | D16: 180 | F16: =E16*D16 -> 0 | I16: CLAMATO (Botella) | M16: 35 | N16: 50 | P16: =O16*N16 -> 0 | R16: =Q16*M16 -> 0
B17: PROMO MEGA LAGER (3) | C17: =37*3 -> 111 | D17: 195 | E17: 9 | F17: =E17*D17 -> 1755 | I17: CLAMATO (Preparado vaso) | M17: 27 | N17: 45 | P17: =O17*N17 -> 0 | R17: =Q17*M17 -> 0
B18: PROMO MEGA ROJA (3) | C18: =35*3 -> 105 | D18: 165 | E18: 3 | F18: =E18*D18 -> 495 | I18: PREPARADO SALSAS (Vaso) | M18: 10 | N18: 25 | P18: =O18*N18 -> 0 | R18: =Q18*M18 -> 0
B19: PROMO MEGA AZUL (3) | C19: =35*3 -> 105 | D19: 165 | E19: 1 | F19: =E19*D19 -> 165 | I19: SOPA | M19: 14 | N19: 35 | P19: =O19*N19 -> 0 | R19: =Q19*M19 -> 0
B20: PROMO MEGA VICTORIA (3) | C20: =41*3 -> 123 | D20: 225 | E20: 8 | F20: =E20*D20 -> 1800 | I20: BOTANA JAMON | M20: 40 | N20: 70 | P20: =O20*N20 -> 0 | R20: =Q20*M20 -> 0
B21: PROMO MEGA CORONA (3) | C21: =41*3 -> 123 | D21: 225 | F21: =E21*D21 -> 0 | I21: MANGUITO | M21: 8 | N21: 15 | P21: =O21*N21 -> 0 | R21: =Q21*M21 -> 0
B22: MICHE LAGER (2 MEDIAS) | C22: 40 | D22: 95 | F22: =E22*D22 -> 0 | I22: CHICLES | M22: 28 | N22: 50 | P22: =O22*N22 -> 0 | R22: =Q22*M22 -> 0
B23: MICHE AZUL (2 MEDIAS) | C23: 40 | D23: 95 | F23: =E23*D23 -> 0 | H23: =G23*C23 -> 0 | I23: DESCORCHE | N23: 300 | P23: =O23*N23 -> 0
B24: MICHE VICTORIA (2 MEDIAS) | C24: 45 | D24: 95 | F24: =E24*D24 -> 0 | H24: =G24*C24 -> 0 | I24: SALSA VALENTINA (CHICA) | M24: 17 | N24: 35 | P24: =O24*N24 -> 0 | R24: =Q24*M24 -> 0
B25: MICHE CORONA (2 MEDIAS) | C25: 45 | D25: 95 | F25: =E25*D25 -> 0 | H25: =G25*C25 -> 0 | I25: VASO ROTO | N25: 35 | P25: =O25*N25 -> 0
B26: COPA $50 | C26: 25 | D26: 50 | F26: =E26*D26 -> 0 | H26: =G26*C26 -> 0 | P26: =O26*N26 -> 0
B27: COPA $70 | C27: 30 | D27: 70 | F27: =E27*D27 -> 0 | H27: =G27*C27 -> 0 | P27: =O27*N27 -> 0
B28: COPA $100 | C28: 50 | D28: 100 | F28: =E28*D28 -> 0 | H28: =G28*C28 -> 0 | P28: =O28*N28 -> 0
B29: COPA $120 | C29: 70 | D29: 120 | F29: =E29*D29 -> 0 | H29: =G29*C29 -> 0 | P29: =O29*N29 -> 0
B30: COPA $150 | C30: 100 | D30: 150 | F30: =E30*D30 -> 0 | H30: =G30*C30 -> 0 | P30: =O30*N30 -> 0
B31: AZULITO | C31: 40 | D31: 95 | F31: =E31*D31 -> 0 | H31: =G31*C31 -> 0 | P31: =O31*N31 -> 0
B32: TOTAL DE VENTA | G32: =SUM(F4:F31,P4:P31) -> 5505 | I32: TOTAL DE CORTESIAS | Q32: =SUM(H4:H31,R4:R31) -> 145
B34: =B155 -> 46184
B35: VENTA PERSONAL
B36: PRODUCTO | C36: $ COMPRA | D36: $ VENTA | E36: ELOY | G36: NUBIA | I36: MARCE | K36: ISELA | O36: VIKY | Q36: 4 | S36: 5 | U36: 6 | W36: 7
E37: CANT | F37: $ | G37: CANT | H37: $ | I37: CANT | J37: $ | K37: CANT | L37: $ | O37: CANT | P37: $ | Q37: CANT | R37: $ | S37: CANT | T37: $ | U37: CANT | V37: $ | W37: CANT | X37: $
B38: MEDIA LAGER | C38: 15 | D38: 30 | E38: 2 | F38: =E38*C38 -> 30 | H38: =G38*C38 -> 0 | J38: =I38*C38 -> 0 | L38: =K38*C38 -> 0 | P38: =O38*C38 -> 0 | R38: =Q38*C38 -> 0 | T38: =S38*C38 -> 0 | V38: =U38*C38 -> 0 | X38: =W38*C38 -> 0
B39: MEDIA AZUL | C39: 14 | D39: 30 | F39: =E39*C39 -> 0 | H39: =G39*C39 -> 0 | J39: =I39*C39 -> 0 | K39: 1 | L39: =K39*C39 -> 14 | P39: =O39*C39 -> 0 | R39: =Q39*C39 -> 0 | T39: =S39*C39 -> 0 | V39: =U39*C39 -> 0 | X39: =W39*C39 -> 0
B40: MEDIA VICTORIA | C40: 17 | D40: 35 | F40: =E40*C40 -> 0 | H40: =G40*C40 -> 0 | J40: =I40*C40 -> 0 | L40: =K40*C40 -> 0 | P40: =O40*C40 -> 0 | R40: =Q40*C40 -> 0 | T40: =S40*C40 -> 0 | V40: =U40*C40 -> 0 | X40: =W40*C40 -> 0
B41: MEDIA CORONA | C41: 17 | D41: 35 | E41: 14 | F41: 1 | G41: 5 | H41: =G41*C41 -> 85 | J41: =I41*C41 -> 0 | L41: =K41*C41 -> 0 | P41: =O41*C41 -> 0 | R41: =Q41*C41 -> 0 | T41: =S41*C41 -> 0 | V41: =U41*C41 -> 0 | X41: =W41*C41 -> 0
B42: MEGA LAGER | C42: 37 | D42: 70 | F42: =E42*C42 -> 0 | G42: 5 | H42: =G42*C42 -> 185 | I42: 3 | J42: =I42*C42 -> 111 | L42: =K42*C42 -> 0 | O42: 4 | P42: =O42*C42 -> 148 | R42: =Q42*C42 -> 0 | T42: =S42*C42 -> 0 | V42: =U42*C42 -> 0 | X42: =W42*C42 -> 0
B43: MEGA ROJA | C43: 35 | D43: 60 | F43: =E43*C43 -> 0 | H43: =G43*C43 -> 0 | J43: =I43*C43 -> 0 | L43: =K43*C43 -> 0 | P43: =O43*C43 -> 0 | R43: =Q43*C43 -> 0 | T43: =S43*C43 -> 0 | V43: =U43*C43 -> 0 | X43: =W43*C43 -> 0
B44: MEGA AZUL | C44: 35 | D44: 60 | F44: =E44*C44 -> 0 | H44: =G44*C44 -> 0 | I44: 1 | J44: =I44*C44 -> 35 | K44: 3 | L44: =K44*C44 -> 105 | P44: =O44*C44 -> 0 | R44: =Q44*C44 -> 0 | T44: =S44*C44 -> 0 | V44: =U44*C44 -> 0 | X44: =W44*C44 -> 0
B45: MEGA VICTORIA | C45: 41 | D45: 80 | F45: =E45*C45 -> 0 | H45: =G45*C45 -> 0 | J45: =I45*C45 -> 0 | L45: =K45*C45 -> 0 | P45: =O45*C45 -> 0 | R45: =Q45*C45 -> 0 | T45: =S45*C45 -> 0 | V45: =U45*C45 -> 0 | X45: =W45*C45 -> 0
B46: MEGA CORONA | C46: 41 | D46: 80 | F46: =E46*C46 -> 0 | H46: =G46*C46 -> 0 | J46: =I46*C46 -> 0 | L46: =K46*C46 -> 0 | P46: =O46*C46 -> 0 | R46: =Q46*C46 -> 0 | T46: =S46*C46 -> 0 | V46: =U46*C46 -> 0 | X46: =W46*C46 -> 0
B47: CIGARRO | C47: 6 | D47: 10 | F47: =E47*C47 -> 0 | H47: =G47*C47 -> 0 | J47: =I47*C47 -> 0 | L47: =K47*C47 -> 0 | P47: =O47*C47 -> 0 | R47: =Q47*C47 -> 0 | T47: =S47*C47 -> 0 | V47: =U47*C47 -> 0 | X47: =W47*C47 -> 0
B48: CACAHUATE | C48: 13 | D48: 25 | F48: =E48*C48 -> 0 | H48: =G48*C48 -> 0 | J48: =I48*C48 -> 0 | L48: =K48*C48 -> 0 | P48: =O48*C48 -> 0 | R48: =Q48*C48 -> 0 | T48: =S48*C48 -> 0 | V48: =U48*C48 -> 0 | X48: =W48*C48 -> 0
B49: CHICARRON | C49: 11 | D49: 35 | F49: =E49*C49 -> 0 | H49: =G49*C49 -> 0 | J49: =I49*C49 -> 0 | L49: =K49*C49 -> 0 | P49: =O49*C49 -> 0 | R49: =Q49*C49 -> 0 | T49: =S49*C49 -> 0 | V49: =U49*C49 -> 0 | X49: =W49*C49 -> 0
B50: SEMILLAS | C50: 10 | D50: 15 | F50: =E50*C50 -> 0 | H50: =G50*C50 -> 0 | J50: =I50*C50 -> 0 | L50: =K50*C50 -> 0 | P50: =O50*C50 -> 0 | R50: =Q50*C50 -> 0 | T50: =S50*C50 -> 0 | V50: =U50*C50 -> 0 | X50: =W50*C50 -> 0
B51: PAPAS | C51: 14.8 | D51: 35 | F51: =E51*C51 -> 0 | H51: =G51*C51 -> 0 | J51: =I51*C51 -> 0 | L51: =K51*C51 -> 0 | P51: =O51*C51 -> 0 | R51: =Q51*C51 -> 0 | T51: =S51*C51 -> 0 | V51: =U51*C51 -> 0 | X51: =W51*C51 -> 0
B52: COCA 355 | C52: 13 | D52: 20 | F52: =E52*C52 -> 0 | G52: 1 | H52: =G52*C52 -> 13 | J52: =I52*C52 -> 0 | L52: =K52*C52 -> 0 | P52: =O52*C52 -> 0 | R52: =Q52*C52 -> 0 | T52: =S52*C52 -> 0 | V52: =U52*C52 -> 0 | X52: =W52*C52 -> 0
B53: PEÑAFIEL 355 | C53: 11 | D53: 20 | F53: =E53*C53 -> 0 | H53: =G53*C53 -> 0 | I53: 1 | J53: =I53*C53 -> 11 | L53: =K53*C53 -> 0 | P53: =O53*C53 -> 0 | R53: =Q53*C53 -> 0 | T53: =S53*C53 -> 0 | V53: =U53*C53 -> 0 | X53: =W53*C53 -> 0
B54: TORONJA 355 | C54: 10 | D54: 20 | F54: =E54*C54 -> 0 | H54: =G54*C54 -> 0 | J54: =I54*C54 -> 0 | L54: =K54*C54 -> 0 | P54: =O54*C54 -> 0 | R54: =Q54*C54 -> 0 | T54: =S54*C54 -> 0 | V54: =U54*C54 -> 0 | X54: =W54*C54 -> 0
B55: BOOS | C55: 40 | D55: 60 | F55: =E55*C55 -> 0 | H55: =G55*C55 -> 0 | J55: =I55*C55 -> 0 | L55: =K55*C55 -> 0 | P55: =O55*C55 -> 0 | R55: =Q55*C55 -> 0 | T55: =S55*C55 -> 0 | V55: =U55*C55 -> 0 | X55: =W55*C55 -> 0
B56: NEWMIX PALOMA | C56: 25 | D56: 45 | F56: =E56*C56 -> 0 | H56: =G56*C56 -> 0 | J56: =I56*C56 -> 0 | L56: =K56*C56 -> 0 | P56: =O56*C56 -> 0 | R56: =Q56*C56 -> 0 | T56: =S56*C56 -> 0 | V56: =U56*C56 -> 0 | X56: =W56*C56 -> 0
B57: NEWMIX VAMPIRO | C57: 25 | D57: 45 | F57: =E57*C57 -> 0 | H57: =G57*C57 -> 0 | J57: =I57*C57 -> 0 | L57: =K57*C57 -> 0 | P57: =O57*C57 -> 0 | R57: =Q57*C57 -> 0 | T57: =S57*C57 -> 0 | V57: =U57*C57 -> 0 | X57: =W57*C57 -> 0
B58: CLAMATO (Botella) | C58: 27 | D58: 45 | F58: =E58*C58 -> 0 | H58: =G58*C58 -> 0 | J58: =I58*C58 -> 0 | L58: =K58*C58 -> 0 | P58: =O58*C58 -> 0 | R58: =Q58*C58 -> 0 | T58: =S58*C58 -> 0 | V58: =U58*C58 -> 0 | X58: =W58*C58 -> 0
B59: SOPA | C59: 14 | D59: 35 | F59: =E59*C59 -> 0 | H59: =G59*C59 -> 0 | J59: =I59*C59 -> 0 | L59: =K59*C59 -> 0 | P59: =O59*C59 -> 0 | R59: =Q59*C59 -> 0 | T59: =S59*C59 -> 0 | V59: =U59*C59 -> 0 | X59: =W59*C59 -> 0
B60: BOTANA JAMON | C60: 40 | D60: 70 | F60: =E60*C60 -> 0 | H60: =G60*C60 -> 0 | J60: =I60*C60 -> 0 | L60: =K60*C60 -> 0 | P60: =O60*C60 -> 0 | R60: =Q60*C60 -> 0 | T60: =S60*C60 -> 0 | V60: =U60*C60 -> 0 | X60: =W60*C60 -> 0
B61: MANGUITO | C61: 8 | D61: 15 | F61: =E61*C61 -> 0 | G61: 2 | H61: =G61*C61 -> 16 | J61: =I61*C61 -> 0 | L61: =K61*C61 -> 0 | P61: =O61*C61 -> 0 | R61: =Q61*C61 -> 0 | T61: =S61*C61 -> 0 | V61: =U61*C61 -> 0 | X61: =W61*C61 -> 0
B62: CHICLES | C62: 28 | D62: 50 | F62: =E62*C62 -> 0 | H62: =G62*C62 -> 0 | J62: =I62*C62 -> 0 | L62: =K62*C62 -> 0 | P62: =O62*C62 -> 0 | R62: =Q62*C62 -> 0 | T62: =S62*C62 -> 0 | V62: =U62*C62 -> 0 | X62: =W62*C62 -> 0
F63: =E63*C63 -> 0 | H63: =G63*C63 -> 0 | J63: =I63*C63 -> 0 | L63: =K63*C63 -> 0 | P63: =O63*C63 -> 0 | R63: =Q63*C63 -> 0 | T63: =S63*C63 -> 0 | V63: =U63*C63 -> 0 | X63: =W63*C63 -> 0
F64: =E64*C64 -> 0 | H64: =G64*C64 -> 0 | J64: =I64*C64 -> 0 | L64: =K64*C64 -> 0 | P64: =O64*C64 -> 0 | R64: =Q64*C64 -> 0 | T64: =S64*C64 -> 0 | V64: =U64*C64 -> 0 | X64: =W64*C64 -> 0
F65: =E65*C65 -> 0 | H65: =G65*C65 -> 0 | J65: =I65*C65 -> 0 | L65: =K65*C65 -> 0 | P65: =O65*C65 -> 0 | R65: =Q65*C65 -> 0 | T65: =S65*C65 -> 0 | V65: =U65*C65 -> 0 | X65: =W65*C65 -> 0
E66: =E36 -> ELOY | F66: =SUM(F38:F65) -> 31 | G66: =G36 -> NUBIA | H66: =SUM(H38:H65) -> 299 | I66: =I36 -> MARCE | J66: =SUM(J38:J65) -> 157 | K66: =K36 -> ISELA | L66: =SUM(L38:L65) -> 119 | O66: =O36 -> VIKY | P66: =SUM(P38:P65) -> 148 | Q66: =Q36 -> 4 | R66: =SUM(R38:R65) -> 0 | S66: =S36 -> 5 | T66: =SUM(T38:T65) -> 0 | U66: =U36 -> 6 | V66: =SUM(V38:V65) -> 0 | W66: =W36 -> 7 | X66: =SUM(X38:X65) -> 0
B68: =B155 -> 46184
B69: VENTA DE FICHAS
B70: NOMBRE | E70: PRECIO | F70: PRODUCTO | H70: 60 | I70: 80 | J70: TOTAL | K70: VENTA | O70: COMISION | Q70: VENTA TOTAL
B71: =G36 -> NUBIA | E71: 120 | F71: MEDIA LAGER | J71: =H71+I71 -> 0 | K71: =J71*E71 -> 0 | O71: =H71*H70+I71*I70 -> 0
F72: MEDIA AZUL | J72: =H72+I72 -> 0 | K72: =J72*E71 -> 0 | O72: =H72*H70+I72*I70 -> 0
B73: PAGO DE COMISION | E73: 300 | F73: MEGA LAGER | K73: =H73*E73 -> 0 | O73: =H73*150 -> 0
B74: =O71+O72+O73+O74+O75 -> 0 | F74: MEGA AZUL | K74: =H74*E73 -> 0 | O74: =H74*150 -> 0 | Q74: =K71+K72+K73+K74+K75 -> 0
F75: MEGA ROJA | K75: =H75*E73 -> 0 | O75: =H75*150 -> 0
B76: NOMBRE | E76: PRECIO | F76: PRODUCTO | H76: 60 | I76: 80 | J76: TOTAL | K76: VENTA | O76: COMISION | Q76: VENTA TOTAL
B77: =I36 -> MARCE | E77: 120 | F77: MEDIA LAGER | J77: =H77+I77 -> 0 | K77: =J77*E77 -> 0 | O77: =H77*H76+I77*I76 -> 0
F78: MEDIA AZUL | J78: =H78+I78 -> 0 | K78: =J78*E77 -> 0 | O78: =H78*H76+I78*I76 -> 0
B79: PAGO DE COMISION | E79: 300 | F79: MEGA LAGER | K79: =H79*E79 -> 0 | O79: =H79*150 -> 0
B80: =O77+O78+O79+O80+O81 -> 0 | F80: MEGA AZUL | K80: =H80*E79 -> 0 | O80: =H80*150 -> 0 | Q80: =K77+K78+K79+K80+K81 -> 0
F81: MEGA ROJA | K81: =H81*E79 -> 0 | O81: =H81*150 -> 0
B82: NOMBRE | E82: PRECIO | F82: PRODUCTO | H82: 60 | I82: 80 | J82: TOTAL | K82: VENTA | O82: COMISION | Q82: VENTA TOTAL
B83: =K36 -> ISELA | E83: 120 | F83: MEDIA LAGER | J83: =H83+I83 -> 0 | K83: =J83*E83 -> 0 | O83: =H83*H82+I83*I82 -> 0
F84: MEDIA AZUL | H84: 13 | J84: =H84+I84 -> 13 | K84: =J84*E83 -> 1560 | O84: =H84*H82+I84*I82 -> 780
B85: PAGO DE COMISION | E85: 300 | F85: MEGA LAGER | K85: =H85*E85 -> 0 | O85: =H85*150 -> 0
B86: =O83+O84+O85+O86+O87 -> 780 | F86: MEGA AZUL | K86: =H86*E85 -> 0 | O86: =H86*150 -> 0 | Q86: =K83+K84+K85+K86+K87 -> 1560
F87: MEGA ROJA | K87: =H87*E85 -> 0 | O87: =H87*150 -> 0
B88: NOMBRE | E88: PRECIO | F88: PRODUCTO | H88: 60 | I88: 80 | J88: TOTAL | K88: VENTA | O88: COMISION | Q88: VENTA TOTAL
B89: =O36 -> VIKY | E89: 120 | F89: MEDIA LAGER | H89: 3 | J89: =H89+I89 -> 3 | K89: =J89*E89 -> 360 | O89: =H89*H88+I89*I88 -> 180
F90: MEDIA AZUL | J90: =H90+I90 -> 0 | K90: =J90*E89 -> 0 | O90: =H90*H88+I90*I88 -> 0
B91: PAGO DE COMISION | E91: 300 | F91: MEGA LAGER | K91: =H91*E91 -> 0 | O91: =H91*150 -> 0
B92: =O89+O90+O91+O92+O93 -> 180 | F92: MEGA AZUL | K92: =H92*E91 -> 0 | O92: =H92*150 -> 0 | Q92: =K89+K90+K91+K92+K93 -> 360
F93: MEGA ROJA | K93: =H93*E91 -> 0 | O93: =H93*150 -> 0
B94: NOMBRE | E94: PRECIO | F94: PRODUCTO | H94: 60 | I94: 80 | J94: TOTAL | K94: VENTA | O94: COMISION | Q94: VENTA TOTAL
B95: =Q36 -> 4 | E95: 120 | F95: MEDIA LAGER | J95: =H95+I95 -> 0 | K95: =J95*E95 -> 0 | O95: =H95*H94+I95*I94 -> 0
F96: MEDIA AZUL | J96: =H96+I96 -> 0 | K96: =J96*E95 -> 0 | O96: =H96*H94+I96*I94 -> 0
B97: PAGO DE COMISION | E97: 300 | F97: MEGA LAGER | K97: =H97*E97 -> 0 | O97: =H97*150 -> 0
B98: =O95+O96+O97+O98+O99 -> 0 | F98: MEGA AZUL | K98: =H98*E97 -> 0 | O98: =H98*150 -> 0 | Q98: =K95+K96+K97+K98+K99 -> 0
F99: MEGA ROJA | K99: =H99*E97 -> 0 | O99: =H99*150 -> 0
B100: NOMBRE | E100: PRECIO | F100: PRODUCTO | H100: 60 | I100: 80 | J100: TOTAL | K100: VENTA | O100: COMISION | Q100: VENTA TOTAL
B101: =S36 -> 5 | E101: 120 | F101: MEDIA LAGER | J101: =H101+I101 -> 0 | K101: =J101*E101 -> 0 | O101: =H101*H100+I101*I100 -> 0
F102: MEDIA AZUL | J102: =H102+I102 -> 0 | K102: =J102*E101 -> 0 | O102: =H102*H100+I102*I100 -> 0
...

Sheet MIERCOLES 10
B1: =B155 -> 46183
B2: VENTA PUBLICO
B3: PRODUCTO | C3: $ COMPRA | D3: $ VENTA | E3: CANT | F3: $ | G3: CORTESIAS | I3: PRODUCTO | M3: $ COMPRA | N3: $ VENTA | O3: CANT | P3: $ | Q3: CORTESIAS
B4: MEDIA LAGER | C4: 15 | D4: 30 | F4: =E4*D4 -> 0 | H4: =G4*C4 -> 0 | I4: CIGARRO | M4: 6 | N4: 10 | O4: 17 | P4: =O4*N4 -> 170
B5: MEDIA AZUL | C5: 14 | D5: 30 | F5: =E5*D5 -> 0 | H5: =G5*C5 -> 0 | I5: CACAHUATE | M5: 13 | N5: 25 | O5: 1 | P5: =O5*N5 -> 25 | R5: =Q5*M5 -> 0
B6: MEDIA VICTORIA | C6: 17 | D6: 35 | F6: =E6*D6 -> 0 | H6: =G6*C6 -> 0 | I6: CHICARRON | M6: 11 | N6: 35 | P6: =O6*N6 -> 0 | R6: =Q6*M6 -> 0
B7: MEDIA CORONA | C7: 17 | D7: 35 | E7: 1 | F7: =E7*D7 -> 35 | H7: =G7*C7 -> 0 | I7: SEMILLAS | M7: 10 | N7: 15 | P7: =O7*N7 -> 0 | R7: =Q7*M7 -> 0
B8: MEGA LAGER | C8: 37 | D8: 70 | E8: 2 | F8: =E8*D8 -> 140 | G8: 1 | H8: =G8*C8 -> 37 | I8: CANCION | M8: 0 | N8: 10 | O8: 3 | P8: =O8*N8 -> 30 | R8: =Q8*M8 -> 0
B9: MEGA ROJA | C9: 35 | D9: 60 | F9: =E9*D9 -> 0 | H9: =G9*C9 -> 0 | I9: PAPAS | M9: 14.8 | N9: 35 | P9: =O9*N9 -> 0 | R9: =Q9*M9 -> 0
B10: MEGA AZUL | C10: 35 | D10: 60 | E10: 1 | F10: =E10*D10 -> 60 | H10: =G10*C10 -> 0 | I10: COCA 355 | M10: 13 | N10: 20 | P10: =O10*N10 -> 0 | R10: =Q10*M10 -> 0
B11: MEGA VICTORIA | C11: 41 | D11: 80 | E11: 1 | F11: =E11*D11 -> 80 | H11: =G11*C11 -> 0 | I11: PEÑAFIEL 355 | M11: 11 | N11: 20 | P11: =O11*N11 -> 0 | R11: =Q11*M11 -> 0
B12: MEGA CORONA | C12: 41 | D12: 80 | E12: 1 | F12: =E12*D12 -> 80 | H12: =G12*C12 -> 0 | I12: TORONJA 355 | M12: 10 | N12: 20 | P12: =O12*N12 -> 0 | R12: =Q12*M12 -> 0
B13: CUBO MEDIA LAGER (6) | C13: =14*6 -> 84 | D13: 160 | F13: =E13*D13 -> 0 | I13: BOOS | M13: 40 | N13: 60 | P13: =O13*N13 -> 0
B14: CUBO MEDIA AZUL (6) | C14: =14*6 -> 84 | D14: 160 | F14: =E14*D14 -> 0 | I14: NEWMIX PALOMA | M14: 25 | N14: 45 | P14: =O14*N14 -> 0
B15: CUBO MEDIA VICTORIA (6) | C15: =17*6 -> 102 | D15: 180 | F15: =E15*D15 -> 0 | I15: NEWMIX VAMPIRO | M15: 25 | N15: 45 | P15: =O15*N15 -> 0
B16: CUBO MEDIA CORONA (6) | C16: =17*6 -> 102 | D16: 180 | F16: =E16*D16 -> 0 | I16: CLAMATO (Botella) | M16: 35 | N16: 50 | P16: =O16*N16 -> 0 | R16: =Q16*M16 -> 0
B17: PROMO MEGA LAGER (3) | C17: =37*3 -> 111 | D17: 195 | E17: 7 | F17: =E17*D17 -> 1365 | I17: CLAMATO (Preparado vaso) | M17: 27 | N17: 45 | P17: =O17*N17 -> 0 | R17: =Q17*M17 -> 0
B18: PROMO MEGA ROJA (3) | C18: =35*3 -> 105 | D18: 165 | E18: 3 | F18: =E18*D18 -> 495 | I18: PREPARADO SALSAS (Vaso) | M18: 10 | N18: 25 | P18: =O18*N18 -> 0 | R18: =Q18*M18 -> 0
B19: PROMO MEGA AZUL (3) | C19: =35*3 -> 105 | D19: 165 | E19: 1 | F19: =E19*D19 -> 165 | I19: SOPA | M19: 14 | N19: 35 | P19: =O19*N19 -> 0 | R19: =Q19*M19 -> 0
B20: PROMO MEGA VICTORIA (3) | C20: =41*3 -> 123 | D20: 225 | E20: 2 | F20: =E20*D20 -> 450 | I20: BOTANA JAMON | M20: 40 | N20: 70 | P20: =O20*N20 -> 0 | R20: =Q20*M20 -> 0
B21: PROMO MEGA CORONA (3) | C21: =41*3 -> 123 | D21: 225 | F21: =E21*D21 -> 0 | I21: MANGUITO | M21: 8 | N21: 15 | P21: =O21*N21 -> 0 | R21: =Q21*M21 -> 0
B22: MICHE LAGER (2 MEDIAS) | C22: 40 | D22: 95 | F22: =E22*D22 -> 0 | I22: CHICLES | M22: 28 | N22: 50 | P22: =O22*N22 -> 0 | R22: =Q22*M22 -> 0
B23: MICHE AZUL (2 MEDIAS) | C23: 40 | D23: 95 | F23: =E23*D23 -> 0 | H23: =G23*C23 -> 0 | I23: DESCORCHE | N23: 300 | P23: =O23*N23 -> 0
B24: MICHE VICTORIA (2 MEDIAS) | C24: 45 | D24: 95 | F24: =E24*D24 -> 0 | H24: =G24*C24 -> 0 | I24: SALSA VALENTINA (CHICA) | M24: 17 | N24: 35 | P24: =O24*N24 -> 0 | R24: =Q24*M24 -> 0
B25: MICHE CORONA (2 MEDIAS) | C25: 45 | D25: 95 | F25: =E25*D25 -> 0 | H25: =G25*C25 -> 0 | I25: VASO ROTO | N25: 35 | P25: =O25*N25 -> 0
B26: COPA $50 | C26: 25 | D26: 50 | F26: =E26*D26 -> 0 | H26: =G26*C26 -> 0 | P26: =O26*N26 -> 0
B27: COPA $70 | C27: 30 | D27: 70 | F27: =E27*D27 -> 0 | H27: =G27*C27 -> 0 | P27: =O27*N27 -> 0
B28: COPA $100 | C28: 50 | D28: 100 | F28: =E28*D28 -> 0 | H28: =G28*C28 -> 0 | P28: =O28*N28 -> 0
B29: COPA $120 | C29: 70 | D29: 120 | F29: =E29*D29 -> 0 | H29: =G29*C29 -> 0 | P29: =O29*N29 -> 0
B30: COPA $150 | C30: 100 | D30: 150 | F30: =E30*D30 -> 0 | H30: =G30*C30 -> 0 | P30: =O30*N30 -> 0
B31: AZULITO | C31: 40 | D31: 95 | F31: =E31*D31 -> 0 | H31: =G31*C31 -> 0 | P31: =O31*N31 -> 0
B32: TOTAL DE VENTA | G32: =SUM(F4:F31,P4:P31) -> 3095 | I32: TOTAL DE CORTESIAS | Q32: =SUM(H4:H31,R4:R31) -> 37
B34: =B155 -> 46183
B35: VENTA PERSONAL
B36: PRODUCTO | C36: $ COMPRA | D36: $ VENTA | E36: ELOY | G36: NUBIA | I36: MARCE | K36: ISELA | O36: VIKY | Q36: 4 | S36: 5 | U36: 6 | W36: 7
E37: CANT | F37: $ | G37: CANT | H37: $ | I37: CANT | J37: $ | K37: CANT | L37: $ | O37: CANT | P37: $ | Q37: CANT | R37: $ | S37: CANT | T37: $ | U37: CANT | V37: $ | W37: CANT | X37: $
B38: MEDIA LAGER | C38: 15 | D38: 30 | F38: =E38*C38 -> 0 | H38: =G38*C38 -> 0 | J38: =I38*C38 -> 0 | L38: =K38*C38 -> 0 | P38: =O38*C38 -> 0 | R38: =Q38*C38 -> 0 | T38: =S38*C38 -> 0 | V38: =U38*C38 -> 0 | X38: =W38*C38 -> 0
B39: MEDIA AZUL | C39: 14 | D39: 30 | F39: =E39*C39 -> 0 | H39: =G39*C39 -> 0 | J39: =I39*C39 -> 0 | L39: =K39*C39 -> 0 | P39: =O39*C39 -> 0 | R39: =Q39*C39 -> 0 | T39: =S39*C39 -> 0 | V39: =U39*C39 -> 0 | X39: =W39*C39 -> 0
B40: MEDIA VICTORIA | C40: 17 | D40: 35 | E40: 3 | F40: =E40*C40 -> 51 | H40: =G40*C40 -> 0 | J40: =I40*C40 -> 0 | L40: =K40*C40 -> 0 | P40: =O40*C40 -> 0 | R40: =Q40*C40 -> 0 | T40: =S40*C40 -> 0 | V40: =U40*C40 -> 0 | X40: =W40*C40 -> 0
B41: MEDIA CORONA | C41: 17 | D41: 35 | F41: 1 | H41: =G41*C41 -> 0 | J41: =I41*C41 -> 0 | L41: =K41*C41 -> 0 | P41: =O41*C41 -> 0 | R41: =Q41*C41 -> 0 | T41: =S41*C41 -> 0 | V41: =U41*C41 -> 0 | X41: =W41*C41 -> 0
B42: MEGA LAGER | C42: 37 | D42: 70 | F42: =E42*C42 -> 0 | H42: =G42*C42 -> 0 | I42: 2 | J42: =I42*C42 -> 74 | K42: 1 | L42: =K42*C42 -> 37 | P42: =O42*C42 -> 0 | R42: =Q42*C42 -> 0 | T42: =S42*C42 -> 0 | V42: =U42*C42 -> 0 | X42: =W42*C42 -> 0
B43: MEGA ROJA | C43: 35 | D43: 60 | F43: =E43*C43 -> 0 | H43: =G43*C43 -> 0 | J43: =I43*C43 -> 0 | L43: =K43*C43 -> 0 | P43: =O43*C43 -> 0 | R43: =Q43*C43 -> 0 | T43: =S43*C43 -> 0 | V43: =U43*C43 -> 0 | X43: =W43*C43 -> 0
B44: MEGA AZUL | C44: 35 | D44: 60 | F44: =E44*C44 -> 0 | H44: =G44*C44 -> 0 | I44: 1 | J44: =I44*C44 -> 35 | K44: 2 | L44: =K44*C44 -> 70 | P44: =O44*C44 -> 0 | R44: =Q44*C44 -> 0 | T44: =S44*C44 -> 0 | V44: =U44*C44 -> 0 | X44: =W44*C44 -> 0
B45: MEGA VICTORIA | C45: 41 | D45: 80 | F45: =E45*C45 -> 0 | H45: =G45*C45 -> 0 | J45: =I45*C45 -> 0 | L45: =K45*C45 -> 0 | P45: =O45*C45 -> 0 | R45: =Q45*C45 -> 0 | T45: =S45*C45 -> 0 | V45: =U45*C45 -> 0 | X45: =W45*C45 -> 0
B46: MEGA CORONA | C46: 41 | D46: 80 | F46: =E46*C46 -> 0 | H46: =G46*C46 -> 0 | J46: =I46*C46 -> 0 | L46: =K46*C46 -> 0 | P46: =O46*C46 -> 0 | R46: =Q46*C46 -> 0 | T46: =S46*C46 -> 0 | V46: =U46*C46 -> 0 | X46: =W46*C46 -> 0
B47: CIGARRO | C47: 6 | D47: 10 | E47: 4 | F47: =E47*C47 -> 24 | H47: =G47*C47 -> 0 | J47: =I47*C47 -> 0 | K47: 1 | L47: =K47*C47 -> 6 | P47: =O47*C47 -> 0 | R47: =Q47*C47 -> 0 | T47: =S47*C47 -> 0 | V47: =U47*C47 -> 0 | X47: =W47*C47 -> 0
B48: CACAHUATE | C48: 13 | D48: 25 | F48: =E48*C48 -> 0 | H48: =G48*C48 -> 0 | J48: =I48*C48 -> 0 | L48: =K48*C48 -> 0 | P48: =O48*C48 -> 0 | R48: =Q48*C48 -> 0 | T48: =S48*C48 -> 0 | V48: =U48*C48 -> 0 | X48: =W48*C48 -> 0
B49: CHICARRON | C49: 11 | D49: 35 | F49: =E49*C49 -> 0 | H49: =G49*C49 -> 0 | J49: =I49*C49 -> 0 | L49: =K49*C49 -> 0 | P49: =O49*C49 -> 0 | R49: =Q49*C49 -> 0 | T49: =S49*C49 -> 0 | V49: =U49*C49 -> 0 | X49: =W49*C49 -> 0
B50: SEMILLAS | C50: 10 | D50: 15 | F50: =E50*C50 -> 0 | H50: =G50*C50 -> 0 | J50: =I50*C50 -> 0 | L50: =K50*C50 -> 0 | P50: =O50*C50 -> 0 | R50: =Q50*C50 -> 0 | T50: =S50*C50 -> 0 | V50: =U50*C50 -> 0 | X50: =W50*C50 -> 0
B51: PAPAS | C51: 14.8 | D51: 35 | F51: =E51*C51 -> 0 | H51: =G51*C51 -> 0 | J51: =I51*C51 -> 0 | L51: =K51*C51 -> 0 | P51: =O51*C51 -> 0 | R51: =Q51*C51 -> 0 | T51: =S51*C51 -> 0 | V51: =U51*C51 -> 0 | X51: =W51*C51 -> 0
B52: COCA 355 | C52: 13 | D52: 20 | F52: =E52*C52 -> 0 | H52: =G52*C52 -> 0 | I52: 1 | J52: =I52*C52 -> 13 | L52: =K52*C52 -> 0 | P52: =O52*C52 -> 0 | R52: =Q52*C52 -> 0 | T52: =S52*C52 -> 0 | V52: =U52*C52 -> 0 | X52: =W52*C52 -> 0
B53: PEÑAFIEL 355 | C53: 11 | D53: 20 | F53: =E53*C53 -> 0 | H53: =G53*C53 -> 0 | J53: =I53*C53 -> 0 | L53: =K53*C53 -> 0 | P53: =O53*C53 -> 0 | R53: =Q53*C53 -> 0 | T53: =S53*C53 -> 0 | V53: =U53*C53 -> 0 | X53: =W53*C53 -> 0
B54: TORONJA 355 | C54: 10 | D54: 20 | F54: =E54*C54 -> 0 | H54: =G54*C54 -> 0 | J54: =I54*C54 -> 0 | L54: =K54*C54 -> 0 | P54: =O54*C54 -> 0 | R54: =Q54*C54 -> 0 | T54: =S54*C54 -> 0 | V54: =U54*C54 -> 0 | X54: =W54*C54 -> 0
B55: BOOS | C55: 40 | D55: 60 | F55: =E55*C55 -> 0 | H55: =G55*C55 -> 0 | J55: =I55*C55 -> 0 | L55: =K55*C55 -> 0 | P55: =O55*C55 -> 0 | R55: =Q55*C55 -> 0 | T55: =S55*C55 -> 0 | V55: =U55*C55 -> 0 | X55: =W55*C55 -> 0
B56: NEWMIX PALOMA | C56: 25 | D56: 45 | F56: =E56*C56 -> 0 | H56: =G56*C56 -> 0 | J56: =I56*C56 -> 0 | L56: =K56*C56 -> 0 | P56: =O56*C56 -> 0 | R56: =Q56*C56 -> 0 | T56: =S56*C56 -> 0 | V56: =U56*C56 -> 0 | X56: =W56*C56 -> 0
B57: NEWMIX VAMPIRO | C57: 25 | D57: 45 | F57: =E57*C57 -> 0 | H57: =G57*C57 -> 0 | J57: =I57*C57 -> 0 | L57: =K57*C57 -> 0 | P57: =O57*C57 -> 0 | R57: =Q57*C57 -> 0 | T57: =S57*C57 -> 0 | V57: =U57*C57 -> 0 | X57: =W57*C57 -> 0
B58: CLAMATO (Botella) | C58: 27 | D58: 45 | F58: =E58*C58 -> 0 | H58: =G58*C58 -> 0 | J58: =I58*C58 -> 0 | L58: =K58*C58 -> 0 | P58: =O58*C58 -> 0 | R58: =Q58*C58 -> 0 | T58: =S58*C58 -> 0 | V58: =U58*C58 -> 0 | X58: =W58*C58 -> 0
B59: SOPA | C59: 14 | D59: 35 | F59: =E59*C59 -> 0 | H59: =G59*C59 -> 0 | J59: =I59*C59 -> 0 | L59: =K59*C59 -> 0 | P59: =O59*C59 -> 0 | R59: =Q59*C59 -> 0 | T59: =S59*C59 -> 0 | V59: =U59*C59 -> 0 | X59: =W59*C59 -> 0
B60: BOTANA JAMON | C60: 40 | D60: 70 | F60: =E60*C60 -> 0 | H60: =G60*C60 -> 0 | J60: =I60*C60 -> 0 | L60: =K60*C60 -> 0 | P60: =O60*C60 -> 0 | R60: =Q60*C60 -> 0 | T60: =S60*C60 -> 0 | V60: =U60*C60 -> 0 | X60: =W60*C60 -> 0
B61: MANGUITO | C61: 8 | D61: 15 | F61: =E61*C61 -> 0 | H61: =G61*C61 -> 0 | J61: =I61*C61 -> 0 | L61: =K61*C61 -> 0 | P61: =O61*C61 -> 0 | R61: =Q61*C61 -> 0 | T61: =S61*C61 -> 0 | V61: =U61*C61 -> 0 | X61: =W61*C61 -> 0
B62: CHICLES | C62: 28 | D62: 50 | F62: =E62*C62 -> 0 | H62: =G62*C62 -> 0 | J62: =I62*C62 -> 0 | L62: =K62*C62 -> 0 | P62: =O62*C62 -> 0 | R62: =Q62*C62 -> 0 | T62: =S62*C62 -> 0 | V62: =U62*C62 -> 0 | X62: =W62*C62 -> 0
F63: =E63*C63 -> 0 | H63: =G63*C63 -> 0 | J63: =I63*C63 -> 0 | L63: =K63*C63 -> 0 | P63: =O63*C63 -> 0 | R63: =Q63*C63 -> 0 | T63: =S63*C63 -> 0 | V63: =U63*C63 -> 0 | X63: =W63*C63 -> 0
F64: =E64*C64 -> 0 | H64: =G64*C64 -> 0 | J64: =I64*C64 -> 0 | L64: =K64*C64 -> 0 | P64: =O64*C64 -> 0 | R64: =Q64*C64 -> 0 | T64: =S64*C64 -> 0 | V64: =U64*C64 -> 0 | X64: =W64*C64 -> 0
F65: =E65*C65 -> 0 | H65: =G65*C65 -> 0 | J65: =I65*C65 -> 0 | L65: =K65*C65 -> 0 | P65: =O65*C65 -> 0 | R65: =Q65*C65 -> 0 | T65: =S65*C65 -> 0 | V65: =U65*C65 -> 0 | X65: =W65*C65 -> 0
E66: =E36 -> ELOY | F66: =SUM(F38:F65) -> 76 | G66: =G36 -> NUBIA | H66: =SUM(H38:H65) -> 0 | I66: =I36 -> MARCE | J66: =SUM(J38:J65) -> 122 | K66: =K36 -> ISELA | L66: =SUM(L38:L65) -> 113 | O66: =O36 -> VIKY | P66: =SUM(P38:P65) -> 0 | Q66: =Q36 -> 4 | R66: =SUM(R38:R65) -> 0 | S66: =S36 -> 5 | T66: =SUM(T38:T65) -> 0 | U66: =U36 -> 6 | V66: =SUM(V38:V65) -> 0 | W66: =W36 -> 7 | X66: =SUM(X38:X65) -> 0
B68: =B155 -> 46183
B69: VENTA DE FICHAS
B70: NOMBRE | E70: PRECIO | F70: PRODUCTO | H70: 60 | I70: 80 | J70: TOTAL | K70: VENTA | O70: COMISION | Q70: VENTA TOTAL
B71: =G36 -> NUBIA | E71: 120 | F71: MEDIA LAGER | J71: =H71+I71 -> 0 | K71: =J71*E71 -> 0 | O71: =H71*H70+I71*I70 -> 0
F72: MEDIA AZUL | J72: =H72+I72 -> 0 | K72: =J72*E71 -> 0 | O72: =H72*H70+I72*I70 -> 0
B73: PAGO DE COMISION | E73: 300 | F73: MEGA LAGER | K73: =H73*E73 -> 0 | O73: =H73*150 -> 0
B74: =O71+O72+O73+O74+O75 -> 0 | F74: MEGA AZUL | K74: =H74*E73 -> 0 | O74: =H74*150 -> 0 | Q74: =K71+K72+K73+K74+K75 -> 0
F75: MEGA ROJA | K75: =H75*E73 -> 0 | O75: =H75*150 -> 0
B76: NOMBRE | E76: PRECIO | F76: PRODUCTO | H76: 60 | I76: 80 | J76: TOTAL | K76: VENTA | O76: COMISION | Q76: VENTA TOTAL
B77: =I36 -> MARCE | E77: 120 | F77: MEDIA LAGER | J77: =H77+I77 -> 0 | K77: =J77*E77 -> 0 | O77: =H77*H76+I77*I76 -> 0
F78: MEDIA AZUL | J78: =H78+I78 -> 0 | K78: =J78*E77 -> 0 | O78: =H78*H76+I78*I76 -> 0
B79: PAGO DE COMISION | E79: 300 | F79: MEGA LAGER | K79: =H79*E79 -> 0 | O79: =H79*150 -> 0
B80: =O77+O78+O79+O80+O81 -> 0 | F80: MEGA AZUL | K80: =H80*E79 -> 0 | O80: =H80*150 -> 0 | Q80: =K77+K78+K79+K80+K81 -> 0
F81: MEGA ROJA | K81: =H81*E79 -> 0 | O81: =H81*150 -> 0
B82: NOMBRE | E82: PRECIO | F82: PRODUCTO | H82: 60 | I82: 80 | J82: TOTAL | K82: VENTA | O82: COMISION | Q82: VENTA TOTAL
B83: =K36 -> ISELA | E83: 120 | F83: MEDIA LAGER | J83: =H83+I83 -> 0 | K83: =J83*E83 -> 0 | O83: =H83*H82+I83*I82 -> 0
F84: MEDIA AZUL | H84: 2 | J84: =H84+I84 -> 2 | K84: =J84*E83 -> 240 | O84: =H84*H82+I84*I82 -> 120
B85: PAGO DE COMISION | E85: 300 | F85: MEGA LAGER | K85: =H85*E85 -> 0 | O85: =H85*150 -> 0
B86: =O83+O84+O85+O86+O87 -> 120 | F86: MEGA AZUL | K86: =H86*E85 -> 0 | O86: =H86*150 -> 0 | Q86: =K83+K84+K85+K86+K87 -> 240
F87: MEGA ROJA | K87: =H87*E85 -> 0 | O87: =H87*150 -> 0
B88: NOMBRE | E88: PRECIO | F88: PRODUCTO | H88: 60 | I88: 80 | J88: TOTAL | K88: VENTA | O88: COMISION | Q88: VENTA TOTAL
B89: =O36 -> VIKY | E89: 120 | F89: MEDIA LAGER | J89: =H89+I89 -> 0 | K89: =J89*E89 -> 0 | O89: =H89*H88+I89*I88 -> 0
F90: MEDIA AZUL | J90: =H90+I90 -> 0 | K90: =J90*E89 -> 0 | O90: =H90*H88+I90*I88 -> 0
B91: PAGO DE COMISION | E91: 300 | F91: MEGA LAGER | K91: =H91*E91 -> 0 | O91: =H91*150 -> 0
B92: =O89+O90+O91+O92+O93 -> 0 | F92: MEGA AZUL | K92: =H92*E91 -> 0 | O92: =H92*150 -> 0 | Q92: =K89+K90+K91+K92+K93 -> 0
F93: MEGA ROJA | K93: =H93*E91 -> 0 | O93: =H93*150 -> 0
B94: NOMBRE | E94: PRECIO | F94: PRODUCTO | H94: 60 | I94: 80 | J94: TOTAL | K94: VENTA | O94: COMISION | Q94: VENTA TOTAL
B95: =Q36 -> 4 | E95: 120 | F95: MEDIA LAGER | J95: =H95+I95 -> 0 | K95: =J95*E95 -> 0 | O95: =H95*H94+I95*I94 -> 0
F96: MEDIA AZUL | J96: =H96+I96 -> 0 | K96: =J96*E95 -> 0 | O96: =H96*H94+I96*I94 -> 0
B97: PAGO DE COMISION | E97: 300 | F97: MEGA LAGER | K97: =H97*E97 -> 0 | O97: =H97*150 -> 0
B98: =O95+O96+O97+O98+O99 -> 0 | F98: MEGA AZUL | K98: =H98*E97 -> 0 | O98: =H98*150 -> 0 | Q98: =K95+K96+K97+K98+K99 -> 0
F99: MEGA ROJA | K99: =H99*E97 -> 0 | O99: =H99*150 -> 0
B100: NOMBRE | E100: PRECIO | F100: PRODUCTO | H100: 60 | I100: 80 | J100: TOTAL | K100: VENTA | O100: COMISION | Q100: VENTA TOTAL
B101: =S36 -> 5 | E101: 120 | F101: MEDIA LAGER | J101: =H101+I101 -> 0 | K101: =J101*E101 -> 0 | O101: =H101*H100+I101*I100 -> 0
F102: MEDIA AZUL | J102: =H102+I102 -> 0 | K102: =J102*E101 -> 0 | O102: =H102*H100+I102*I100 -> 0
...

Sheet MARTES 09
B1: =B155 -> 46182
B2: VENTA PUBLICO
B3: PRODUCTO | C3: $ COMPRA | D3: $ VENTA | E3: CANT | F3: $ | G3: CORTESIAS | I3: PRODUCTO | M3: $ COMPRA | N3: $ VENTA | O3: CANT | P3: $ | Q3: CORTESIAS
B4: MEDIA LAGER | C4: 15 | D4: 30 | F4: =E4*D4 -> 0 | H4: =G4*C4 -> 0 | I4: CIGARRO | M4: 6 | N4: 10 | O4: 4 | P4: =O4*N4 -> 40
B5: MEDIA AZUL | C5: 14 | D5: 30 | F5: =E5*D5 -> 0 | H5: =G5*C5 -> 0 | I5: CACAHUATE | M5: 13 | N5: 25 | O5: 1 | P5: =O5*N5 -> 25 | R5: =Q5*M5 -> 0
B6: MEDIA VICTORIA | C6: 17 | D6: 35 | F6: =E6*D6 -> 0 | H6: =G6*C6 -> 0 | I6: CHICARRON | M6: 11 | N6: 35 | P6: =O6*N6 -> 0 | R6: =Q6*M6 -> 0
B7: MEDIA CORONA | C7: 17 | D7: 35 | F7: =E7*D7 -> 0 | H7: =G7*C7 -> 0 | I7: SEMILLAS | M7: 10 | N7: 15 | P7: =O7*N7 -> 0 | R7: =Q7*M7 -> 0
B8: MEGA LAGER | C8: 37 | D8: 70 | E8: 2 | F8: =E8*D8 -> 140 | H8: =G8*C8 -> 0 | I8: CANCION | M8: 0 | N8: 10 | O8: 2 | P8: =O8*N8 -> 20 | R8: =Q8*M8 -> 0
B9: MEGA ROJA | C9: 35 | D9: 60 | E9: 1 | F9: =E9*D9 -> 60 | H9: =G9*C9 -> 0 | I9: PAPAS | M9: 14.8 | N9: 35 | P9: =O9*N9 -> 0 | R9: =Q9*M9 -> 0
B10: MEGA AZUL | C10: 35 | D10: 60 | E10: 2 | F10: =E10*D10 -> 120 | H10: =G10*C10 -> 0 | I10: COCA 355 | M10: 13 | N10: 20 | P10: =O10*N10 -> 0 | R10: =Q10*M10 -> 0
B11: MEGA VICTORIA | C11: 41 | D11: 80 | F11: =E11*D11 -> 0 | H11: =G11*C11 -> 0 | I11: PEÑAFIEL 355 | M11: 11 | N11: 20 | P11: =O11*N11 -> 0 | R11: =Q11*M11 -> 0
B12: MEGA CORONA | C12: 41 | D12: 80 | E12: 1 | F12: =E12*D12 -> 80 | H12: =G12*C12 -> 0 | I12: TORONJA 355 | M12: 10 | N12: 20 | P12: =O12*N12 -> 0 | R12: =Q12*M12 -> 0
B13: CUBO MEDIA LAGER (6) | C13: =14*6 -> 84 | D13: 160 | F13: =E13*D13 -> 0 | I13: BOOS | M13: 40 | N13: 60 | P13: =O13*N13 -> 0
B14: CUBO MEDIA AZUL (6) | C14: =14*6 -> 84 | D14: 160 | F14: =E14*D14 -> 0 | I14: NEWMIX PALOMA | M14: 25 | N14: 45 | P14: =O14*N14 -> 0
B15: CUBO MEDIA VICTORIA (6) | C15: =17*6 -> 102 | D15: 180 | F15: =E15*D15 -> 0 | I15: NEWMIX VAMPIRO | M15: 25 | N15: 45 | P15: =O15*N15 -> 0
B16: CUBO MEDIA CORONA (6) | C16: =17*6 -> 102 | D16: 180 | F16: =E16*D16 -> 0 | I16: CLAMATO (Botella) | M16: 35 | N16: 50 | P16: =O16*N16 -> 0 | R16: =Q16*M16 -> 0
B17: PROMO MEGA LAGER (3) | C17: =37*3 -> 111 | D17: 195 | E17: 7 | F17: =E17*D17 -> 1365 | I17: CLAMATO (Preparado vaso) | M17: 27 | N17: 45 | O17: 1 | P17: =O17*N17 -> 45 | R17: =Q17*M17 -> 0
B18: PROMO MEGA ROJA (3) | C18: =35*3 -> 105 | D18: 165 | E18: 5 | F18: =E18*D18 -> 825 | I18: PREPARADO SALSAS (Vaso) | M18: 10 | N18: 25 | P18: =O18*N18 -> 0 | R18: =Q18*M18 -> 0
B19: PROMO MEGA AZUL (3) | C19: =35*3 -> 105 | D19: 165 | E19: 2 | F19: =E19*D19 -> 330 | I19: SOPA | M19: 14 | N19: 35 | P19: =O19*N19 -> 0 | R19: =Q19*M19 -> 0
B20: PROMO MEGA VICTORIA (3) | C20: =41*3 -> 123 | D20: 225 | F20: =E20*D20 -> 0 | I20: BOTANA JAMON | M20: 40 | N20: 70 | P20: =O20*N20 -> 0 | R20: =Q20*M20 -> 0
B21: PROMO MEGA CORONA (3) | C21: =41*3 -> 123 | D21: 225 | F21: =E21*D21 -> 0 | I21: MANGUITO | M21: 8 | N21: 15 | P21: =O21*N21 -> 0 | R21: =Q21*M21 -> 0
B22: MICHE LAGER (2 MEDIAS) | C22: 40 | D22: 95 | F22: =E22*D22 -> 0 | I22: CHICLES | M22: 28 | N22: 50 | P22: =O22*N22 -> 0 | R22: =Q22*M22 -> 0
B23: MICHE AZUL (2 MEDIAS) | C23: 40 | D23: 95 | F23: =E23*D23 -> 0 | H23: =G23*C23 -> 0 | I23: DESCORCHE | N23: 300 | P23: =O23*N23 -> 0
B24: MICHE VICTORIA (2 MEDIAS) | C24: 45 | D24: 95 | F24: =E24*D24 -> 0 | H24: =G24*C24 -> 0 | I24: SALSA VALENTINA (CHICA) | M24: 17 | N24: 35 | P24: =O24*N24 -> 0 | R24: =Q24*M24 -> 0
B25: MICHE CORONA (2 MEDIAS) | C25: 45 | D25: 95 | F25: =E25*D25 -> 0 | H25: =G25*C25 -> 0 | I25: VASO ROTO | N25: 35 | P25: =O25*N25 -> 0
B26: COPA $50 | C26: 25 | D26: 50 | F26: =E26*D26 -> 0 | H26: =G26*C26 -> 0 | P26: =O26*N26 -> 0
B27: COPA $70 | C27: 30 | D27: 70 | F27: =E27*D27 -> 0 | H27: =G27*C27 -> 0 | P27: =O27*N27 -> 0
B28: COPA $100 | C28: 50 | D28: 100 | F28: =E28*D28 -> 0 | H28: =G28*C28 -> 0 | P28: =O28*N28 -> 0
B29: COPA $120 | C29: 70 | D29: 120 | F29: =E29*D29 -> 0 | H29: =G29*C29 -> 0 | P29: =O29*N29 -> 0
B30: COPA $150 | C30: 100 | D30: 150 | F30: =E30*D30 -> 0 | H30: =G30*C30 -> 0 | P30: =O30*N30 -> 0
B31: AZULITO | C31: 40 | D31: 95 | F31: =E31*D31 -> 0 | H31: =G31*C31 -> 0 | P31: =O31*N31 -> 0
B32: TOTAL DE VENTA | G32: =SUM(F4:F31,P4:P31) -> 3050 | I32: TOTAL DE CORTESIAS | Q32: =SUM(H4:H31,R4:R31) -> 0
B34: =B155 -> 46182
B35: VENTA PERSONAL
B36: PRODUCTO | C36: $ COMPRA | D36: $ VENTA | E36: ELOY | G36: NUBIA | I36: MARCE | K36: ISELA | O36: VIKY | Q36: 4 | S36: 5 | U36: 6 | W36: 7
E37: CANT | F37: $ | G37: CANT | H37: $ | I37: CANT | J37: $ | K37: CANT | L37: $ | O37: CANT | P37: $ | Q37: CANT | R37: $ | S37: CANT | T37: $ | U37: CANT | V37: $ | W37: CANT | X37: $
B38: MEDIA LAGER | C38: 15 | D38: 30 | F38: =E38*C38 -> 0 | H38: =G38*C38 -> 0 | J38: =I38*C38 -> 0 | L38: =K38*C38 -> 0 | P38: =O38*C38 -> 0 | R38: =Q38*C38 -> 0 | T38: =S38*C38 -> 0 | V38: =U38*C38 -> 0 | X38: =W38*C38 -> 0
B39: MEDIA AZUL | C39: 14 | D39: 30 | F39: =E39*C39 -> 0 | H39: =G39*C39 -> 0 | J39: =I39*C39 -> 0 | L39: =K39*C39 -> 0 | P39: =O39*C39 -> 0 | R39: =Q39*C39 -> 0 | T39: =S39*C39 -> 0 | V39: =U39*C39 -> 0 | X39: =W39*C39 -> 0
B40: MEDIA VICTORIA | C40: 17 | D40: 35 | E40: 9 | F40: =E40*C40 -> 153 | H40: =G40*C40 -> 0 | J40: =I40*C40 -> 0 | L40: =K40*C40 -> 0 | P40: =O40*C40 -> 0 | R40: =Q40*C40 -> 0 | T40: =S40*C40 -> 0 | V40: =U40*C40 -> 0 | X40: =W40*C40 -> 0
B41: MEDIA CORONA | C41: 17 | D41: 35 | F41: 1 | H41: =G41*C41 -> 0 | J41: =I41*C41 -> 0 | L41: =K41*C41 -> 0 | P41: =O41*C41 -> 0 | R41: =Q41*C41 -> 0 | T41: =S41*C41 -> 0 | V41: =U41*C41 -> 0 | X41: =W41*C41 -> 0
B42: MEGA LAGER | C42: 37 | D42: 70 | F42: =E42*C42 -> 0 | H42: =G42*C42 -> 0 | J42: =I42*C42 -> 0 | L42: =K42*C42 -> 0 | P42: =O42*C42 -> 0 | R42: =Q42*C42 -> 0 | T42: =S42*C42 -> 0 | V42: =U42*C42 -> 0 | X42: =W42*C42 -> 0
B43: MEGA ROJA | C43: 35 | D43: 60 | F43: =E43*C43 -> 0 | H43: =G43*C43 -> 0 | J43: =I43*C43 -> 0 | L43: =K43*C43 -> 0 | P43: =O43*C43 -> 0 | R43: =Q43*C43 -> 0 | T43: =S43*C43 -> 0 | V43: =U43*C43 -> 0 | X43: =W43*C43 -> 0
B44: MEGA AZUL | C44: 35 | D44: 60 | F44: =E44*C44 -> 0 | H44: =G44*C44 -> 0 | I44: 3 | J44: =I44*C44 -> 105 | K44: 3 | L44: =K44*C44 -> 105 | P44: =O44*C44 -> 0 | R44: =Q44*C44 -> 0 | T44: =S44*C44 -> 0 | V44: =U44*C44 -> 0 | X44: =W44*C44 -> 0
B45: MEGA VICTORIA | C45: 41 | D45: 80 | F45: =E45*C45 -> 0 | H45: =G45*C45 -> 0 | J45: =I45*C45 -> 0 | L45: =K45*C45 -> 0 | P45: =O45*C45 -> 0 | R45: =Q45*C45 -> 0 | T45: =S45*C45 -> 0 | V45: =U45*C45 -> 0 | X45: =W45*C45 -> 0
B46: MEGA CORONA | C46: 41 | D46: 80 | F46: =E46*C46 -> 0 | H46: =G46*C46 -> 0 | J46: =I46*C46 -> 0 | L46: =K46*C46 -> 0 | P46: =O46*C46 -> 0 | R46: =Q46*C46 -> 0 | T46: =S46*C46 -> 0 | V46: =U46*C46 -> 0 | X46: =W46*C46 -> 0
B47: CIGARRO | C47: 6 | D47: 10 | F47: =E47*C47 -> 0 | H47: =G47*C47 -> 0 | J47: =I47*C47 -> 0 | K47: 2 | L47: =K47*C47 -> 12 | P47: =O47*C47 -> 0 | R47: =Q47*C47 -> 0 | T47: =S47*C47 -> 0 | V47: =U47*C47 -> 0 | X47: =W47*C47 -> 0
B48: CACAHUATE | C48: 13 | D48: 25 | F48: =E48*C48 -> 0 | H48: =G48*C48 -> 0 | J48: =I48*C48 -> 0 | L48: =K48*C48 -> 0 | P48: =O48*C48 -> 0 | R48: =Q48*C48 -> 0 | T48: =S48*C48 -> 0 | V48: =U48*C48 -> 0 | X48: =W48*C48 -> 0
B49: CHICARRON | C49: 11 | D49: 35 | F49: =E49*C49 -> 0 | H49: =G49*C49 -> 0 | J49: =I49*C49 -> 0 | L49: =K49*C49 -> 0 | P49: =O49*C49 -> 0 | R49: =Q49*C49 -> 0 | T49: =S49*C49 -> 0 | V49: =U49*C49 -> 0 | X49: =W49*C49 -> 0
B50: SEMILLAS | C50: 10 | D50: 15 | F50: =E50*C50 -> 0 | H50: =G50*C50 -> 0 | J50: =I50*C50 -> 0 | L50: =K50*C50 -> 0 | P50: =O50*C50 -> 0 | R50: =Q50*C50 -> 0 | T50: =S50*C50 -> 0 | V50: =U50*C50 -> 0 | X50: =W50*C50 -> 0
B51: PAPAS | C51: 14.8 | D51: 35 | F51: =E51*C51 -> 0 | H51: =G51*C51 -> 0 | J51: =I51*C51 -> 0 | L51: =K51*C51 -> 0 | P51: =O51*C51 -> 0 | R51: =Q51*C51 -> 0 | T51: =S51*C51 -> 0 | V51: =U51*C51 -> 0 | X51: =W51*C51 -> 0
B52: COCA 355 | C52: 13 | D52: 20 | F52: =E52*C52 -> 0 | H52: =G52*C52 -> 0 | J52: =I52*C52 -> 0 | L52: =K52*C52 -> 0 | P52: =O52*C52 -> 0 | R52: =Q52*C52 -> 0 | T52: =S52*C52 -> 0 | V52: =U52*C52 -> 0 | X52: =W52*C52 -> 0
B53: PEÑAFIEL 355 | C53: 11 | D53: 20 | F53: =E53*C53 -> 0 | H53: =G53*C53 -> 0 | J53: =I53*C53 -> 0 | L53: =K53*C53 -> 0 | P53: =O53*C53 -> 0 | R53: =Q53*C53 -> 0 | T53: =S53*C53 -> 0 | V53: =U53*C53 -> 0 | X53: =W53*C53 -> 0
B54: TORONJA 355 | C54: 10 | D54: 20 | F54: =E54*C54 -> 0 | H54: =G54*C54 -> 0 | J54: =I54*C54 -> 0 | L54: =K54*C54 -> 0 | P54: =O54*C54 -> 0 | R54: =Q54*C54 -> 0 | T54: =S54*C54 -> 0 | V54: =U54*C54 -> 0 | X54: =W54*C54 -> 0
B55: BOOS | C55: 40 | D55: 60 | F55: =E55*C55 -> 0 | H55: =G55*C55 -> 0 | J55: =I55*C55 -> 0 | L55: =K55*C55 -> 0 | P55: =O55*C55 -> 0 | R55: =Q55*C55 -> 0 | T55: =S55*C55 -> 0 | V55: =U55*C55 -> 0 | X55: =W55*C55 -> 0
B56: NEWMIX PALOMA | C56: 25 | D56: 45 | F56: =E56*C56 -> 0 | H56: =G56*C56 -> 0 | J56: =I56*C56 -> 0 | L56: =K56*C56 -> 0 | P56: =O56*C56 -> 0 | R56: =Q56*C56 -> 0 | T56: =S56*C56 -> 0 | V56: =U56*C56 -> 0 | X56: =W56*C56 -> 0
B57: NEWMIX VAMPIRO | C57: 25 | D57: 45 | F57: =E57*C57 -> 0 | H57: =G57*C57 -> 0 | J57: =I57*C57 -> 0 | L57: =K57*C57 -> 0 | P57: =O57*C57 -> 0 | R57: =Q57*C57 -> 0 | T57: =S57*C57 -> 0 | V57: =U57*C57 -> 0 | X57: =W57*C57 -> 0
B58: CLAMATO (Botella) | C58: 27 | D58: 45 | F58: =E58*C58 -> 0 | H58: =G58*C58 -> 0 | J58: =I58*C58 -> 0 | L58: =K58*C58 -> 0 | P58: =O58*C58 -> 0 | R58: =Q58*C58 -> 0 | T58: =S58*C58 -> 0 | V58: =U58*C58 -> 0 | X58: =W58*C58 -> 0
B59: SOPA | C59: 14 | D59: 35 | F59: =E59*C59 -> 0 | H59: =G59*C59 -> 0 | J59: =I59*C59 -> 0 | L59: =K59*C59 -> 0 | P59: =O59*C59 -> 0 | R59: =Q59*C59 -> 0 | T59: =S59*C59 -> 0 | V59: =U59*C59 -> 0 | X59: =W59*C59 -> 0
B60: BOTANA JAMON | C60: 40 | D60: 70 | F60: =E60*C60 -> 0 | H60: =G60*C60 -> 0 | J60: =I60*C60 -> 0 | L60: =K60*C60 -> 0 | P60: =O60*C60 -> 0 | R60: =Q60*C60 -> 0 | T60: =S60*C60 -> 0 | V60: =U60*C60 -> 0 | X60: =W60*C60 -> 0
B61: MANGUITO | C61: 8 | D61: 15 | F61: =E61*C61 -> 0 | H61: =G61*C61 -> 0 | J61: =I61*C61 -> 0 | K61: 1 | L61: =K61*C61 -> 8 | P61: =O61*C61 -> 0 | R61: =Q61*C61 -> 0 | T61: =S61*C61 -> 0 | V61: =U61*C61 -> 0 | X61: =W61*C61 -> 0
B62: CHICLES | C62: 28 | D62: 50 | F62: =E62*C62 -> 0 | H62: =G62*C62 -> 0 | J62: =I62*C62 -> 0 | L62: =K62*C62 -> 0 | P62: =O62*C62 -> 0 | R62: =Q62*C62 -> 0 | T62: =S62*C62 -> 0 | V62: =U62*C62 -> 0 | X62: =W62*C62 -> 0
F63: =E63*C63 -> 0 | H63: =G63*C63 -> 0 | J63: =I63*C63 -> 0 | L63: =K63*C63 -> 0 | P63: =O63*C63 -> 0 | R63: =Q63*C63 -> 0 | T63: =S63*C63 -> 0 | V63: =U63*C63 -> 0 | X63: =W63*C63 -> 0
F64: =E64*C64 -> 0 | H64: =G64*C64 -> 0 | J64: =I64*C64 -> 0 | L64: =K64*C64 -> 0 | P64: =O64*C64 -> 0 | R64: =Q64*C64 -> 0 | T64: =S64*C64 -> 0 | V64: =U64*C64 -> 0 | X64: =W64*C64 -> 0
F65: =E65*C65 -> 0 | H65: =G65*C65 -> 0 | J65: =I65*C65 -> 0 | L65: =K65*C65 -> 0 | P65: =O65*C65 -> 0 | R65: =Q65*C65 -> 0 | T65: =S65*C65 -> 0 | V65: =U65*C65 -> 0 | X65: =W65*C65 -> 0
E66: =E36 -> ELOY | F66: =SUM(F38:F65) -> 154 | G66: =G36 -> NUBIA | H66: =SUM(H38:H65) -> 0 | I66: =I36 -> MARCE | J66: =SUM(J38:J65) -> 105 | K66: =K36 -> ISELA | L66: =SUM(L38:L65) -> 125 | O66: =O36 -> VIKY | P66: =SUM(P38:P65) -> 0 | Q66: =Q36 -> 4 | R66: =SUM(R38:R65) -> 0 | S66: =S36 -> 5 | T66: =SUM(T38:T65) -> 0 | U66: =U36 -> 6 | V66: =SUM(V38:V65) -> 0 | W66: =W36 -> 7 | X66: =SUM(X38:X65) -> 0
B68: =B155 -> 46182
B69: VENTA DE FICHAS
B70: NOMBRE | E70: PRECIO | F70: PRODUCTO | H70: 60 | I70: 80 | J70: TOTAL | K70: VENTA | O70: COMISION | Q70: VENTA TOTAL
B71: =G36 -> NUBIA | E71: 120 | F71: MEDIA LAGER | J71: =H71+I71 -> 0 | K71: =J71*E71 -> 0 | O71: =H71*H70+I71*I70 -> 0
F72: MEDIA AZUL | J72: =H72+I72 -> 0 | K72: =J72*E71 -> 0 | O72: =H72*H70+I72*I70 -> 0
B73: PAGO DE COMISION | E73: 300 | F73: MEGA LAGER | K73: =H73*E73 -> 0 | O73: =H73*150 -> 0
B74: =O71+O72+O73+O74+O75 -> 0 | F74: MEGA AZUL | K74: =H74*E73 -> 0 | O74: =H74*150 -> 0 | Q74: =K71+K72+K73+K74+K75 -> 0
F75: MEGA ROJA | K75: =H75*E73 -> 0 | O75: =H75*150 -> 0
B76: NOMBRE | E76: PRECIO | F76: PRODUCTO | H76: 60 | I76: 80 | J76: TOTAL | K76: VENTA | O76: COMISION | Q76: VENTA TOTAL
B77: =I36 -> MARCE | E77: 120 | F77: MEDIA LAGER | J77: =H77+I77 -> 0 | K77: =J77*E77 -> 0 | O77: =H77*H76+I77*I76 -> 0
F78: MEDIA AZUL | J78: =H78+I78 -> 0 | K78: =J78*E77 -> 0 | O78: =H78*H76+I78*I76 -> 0
B79: PAGO DE COMISION | E79: 300 | F79: MEGA LAGER | K79: =H79*E79 -> 0 | O79: =H79*150 -> 0
B80: =O77+O78+O79+O80+O81 -> 0 | F80: MEGA AZUL | K80: =H80*E79 -> 0 | O80: =H80*150 -> 0 | Q80: =K77+K78+K79+K80+K81 -> 0
F81: MEGA ROJA | K81: =H81*E79 -> 0 | O81: =H81*150 -> 0
B82: NOMBRE | E82: PRECIO | F82: PRODUCTO | H82: 60 | I82: 80 | J82: TOTAL | K82: VENTA | O82: COMISION | Q82: VENTA TOTAL
B83: =K36 -> ISELA | E83: 120 | F83: MEDIA LAGER | J83: =H83+I83 -> 0 | K83: =J83*E83 -> 0 | O83: =H83*H82+I83*I82 -> 0
F84: MEDIA AZUL | H84: 3 | J84: =H84+I84 -> 3 | K84: =J84*E83 -> 360 | O84: =H84*H82+I84*I82 -> 180
B85: PAGO DE COMISION | E85: 300 | F85: MEGA LAGER | K85: =H85*E85 -> 0 | O85: =H85*150 -> 0
B86: =O83+O84+O85+O86+O87 -> 180 | F86: MEGA AZUL | K86: =H86*E85 -> 0 | O86: =H86*150 -> 0 | Q86: =K83+K84+K85+K86+K87 -> 360
F87: MEGA ROJA | K87: =H87*E85 -> 0 | O87: =H87*150 -> 0
B88: NOMBRE | E88: PRECIO | F88: PRODUCTO | H88: 60 | I88: 80 | J88: TOTAL | K88: VENTA | O88: COMISION | Q88: VENTA TOTAL
B89: =O36 -> VIKY | E89: 120 | F89: MEDIA LAGER | J89: =H89+I89 -> 0 | K89: =J89*E89 -> 0 | O89: =H89*H88+I89*I88 -> 0
F90: MEDIA AZUL | J90: =H90+I90 -> 0 | K90: =J90*E89 -> 0 | O90: =H90*H88+I90*I88 -> 0
B91: PAGO DE COMISION | E91: 300 | F91: MEGA LAGER | K91: =H91*E91 -> 0 | O91: =H91*150 -> 0
B92: =O89+O90+O91+O92+O93 -> 0 | F92: MEGA AZUL | K92: =H92*E91 -> 0 | O92: =H92*150 -> 0 | Q92: =K89+K90+K91+K92+K93 -> 0
F93: MEGA ROJA | K93: =H93*E91 -> 0 | O93: =H93*150 -> 0
B94: NOMBRE | E94: PRECIO | F94: PRODUCTO | H94: 60 | I94: 80 | J94: TOTAL | K94: VENTA | O94: COMISION | Q94: VENTA TOTAL
B95: =Q36 -> 4 | E95: 120 | F95: MEDIA LAGER | J95: =H95+I95 -> 0 | K95: =J95*E95 -> 0 | O95: =H95*H94+I95*I94 -> 0
F96: MEDIA AZUL | J96: =H96+I96 -> 0 | K96: =J96*E95 -> 0 | O96: =H96*H94+I96*I94 -> 0
B97: PAGO DE COMISION | E97: 300 | F97: MEGA LAGER | K97: =H97*E97 -> 0 | O97: =H97*150 -> 0
B98: =O95+O96+O97+O98+O99 -> 0 | F98: MEGA AZUL | K98: =H98*E97 -> 0 | O98: =H98*150 -> 0 | Q98: =K95+K96+K97+K98+K99 -> 0
F99: MEGA ROJA | K99: =H99*E97 -> 0 | O99: =H99*150 -> 0
B100: NOMBRE | E100: PRECIO | F100: PRODUCTO | H100: 60 | I100: 80 | J100: TOTAL | K100: VENTA | O100: COMISION | Q100: VENTA TOTAL
B101: =S36 -> 5 | E101: 120 | F101: MEDIA LAGER | J101: =H101+I101 -> 0 | K101: =J101*E101 -> 0 | O101: =H101*H100+I101*I100 -> 0
F102: MEDIA AZUL | J102: =H102+I102 -> 0 | K102: =J102*E101 -> 0 | O102: =H102*H100+I102*I100 -> 0
...

Sheet LUNES 08
B1: =B155 -> 46181
B2: VENTA PUBLICO
B3: PRODUCTO | C3: $ COMPRA | D3: $ VENTA | E3: CANT | F3: $ | G3: CORTESIAS | I3: PRODUCTO | M3: $ COMPRA | N3: $ VENTA | O3: CANT | P3: $ | Q3: CORTESIAS
B4: MEDIA LAGER | C4: 15 | D4: 30 | E4: 1 | F4: =E4*D4 -> 30 | H4: =G4*C4 -> 0 | I4: CIGARRO | M4: 6 | N4: 10 | O4: 2 | P4: =O4*N4 -> 20
B5: MEDIA AZUL | C5: 14 | D5: 30 | F5: =E5*D5 -> 0 | H5: =G5*C5 -> 0 | I5: CACAHUATE | M5: 13 | N5: 25 | O5: 6 | P5: =O5*N5 -> 150 | R5: =Q5*M5 -> 0
B6: MEDIA VICTORIA | C6: 17 | D6: 35 | E6: 3 | F6: =E6*D6 -> 105 | H6: =G6*C6 -> 0 | I6: CHICARRON | M6: 11 | N6: 35 | P6: =O6*N6 -> 0 | R6: =Q6*M6 -> 0
B7: MEDIA CORONA | C7: 17 | D7: 35 | E7: 6 | F7: =E7*D7 -> 210 | H7: =G7*C7 -> 0 | I7: SEMILLAS | M7: 10 | N7: 15 | P7: =O7*N7 -> 0 | R7: =Q7*M7 -> 0
B8: MEGA LAGER | C8: 37 | D8: 70 | E8: 2 | F8: =E8*D8 -> 140 | H8: =G8*C8 -> 0 | I8: CANCION | M8: 0 | N8: 10 | P8: =O8*N8 -> 0 | R8: =Q8*M8 -> 0
B9: MEGA ROJA | C9: 35 | D9: 60 | E9: 2 | F9: =E9*D9 -> 120 | H9: =G9*C9 -> 0 | I9: PAPAS | M9: 14.8 | N9: 35 | P9: =O9*N9 -> 0 | R9: =Q9*M9 -> 0
B10: MEGA AZUL | C10: 35 | D10: 60 | E10: 1 | F10: =E10*D10 -> 60 | H10: =G10*C10 -> 0 | I10: COCA 355 | M10: 13 | N10: 20 | P10: =O10*N10 -> 0 | R10: =Q10*M10 -> 0
B11: MEGA VICTORIA | C11: 41 | D11: 80 | F11: =E11*D11 -> 0 | H11: =G11*C11 -> 0 | I11: PEÑAFIEL 355 | M11: 11 | N11: 20 | P11: =O11*N11 -> 0 | R11: =Q11*M11 -> 0
B12: MEGA CORONA | C12: 41 | D12: 80 | E12: 2 | F12: =E12*D12 -> 160 | H12: =G12*C12 -> 0 | I12: TORONJA 355 | M12: 10 | N12: 20 | P12: =O12*N12 -> 0 | R12: =Q12*M12 -> 0
B13: CUBO MEDIA LAGER (6) | C13: =14*6 -> 84 | D13: 160 | E13: 1 | F13: =E13*D13 -> 160 | I13: BOOS | M13: 40 | N13: 60 | P13: =O13*N13 -> 0
B14: CUBO MEDIA AZUL (6) | C14: =14*6 -> 84 | D14: 160 | F14: =E14*D14 -> 0 | I14: NEWMIX PALOMA | M14: 25 | N14: 45 | P14: =O14*N14 -> 0
B15: CUBO MEDIA VICTORIA (6) | C15: =17*6 -> 102 | D15: 180 | E15: 1 | F15: =E15*D15 -> 180 | I15: NEWMIX VAMPIRO | M15: 25 | N15: 45 | P15: =O15*N15 -> 0
B16: CUBO MEDIA CORONA (6) | C16: =17*6 -> 102 | D16: 180 | F16: =E16*D16 -> 0 | I16: CLAMATO (Botella) | M16: 35 | N16: 50 | O16: 1 | P16: =O16*N16 -> 50 | R16: =Q16*M16 -> 0
B17: PROMO MEGA LAGER (3) | C17: =37*3 -> 111 | D17: 195 | F17: =E17*D17 -> 0 | I17: CLAMATO (Preparado vaso) | M17: 27 | N17: 45 | P17: =O17*N17 -> 0 | R17: =Q17*M17 -> 0
B18: PROMO MEGA ROJA (3) | C18: =35*3 -> 105 | D18: 165 | E18: 1 | F18: =E18*D18 -> 165 | I18: PREPARADO SALSAS (Vaso) | M18: 10 | N18: 25 | P18: =O18*N18 -> 0 | R18: =Q18*M18 -> 0
B19: PROMO MEGA AZUL (3) | C19: =35*3 -> 105 | D19: 165 | F19: =E19*D19 -> 0 | I19: SOPA | M19: 14 | N19: 35 | P19: =O19*N19 -> 0 | R19: =Q19*M19 -> 0
B20: PROMO MEGA VICTORIA (3) | C20: =41*3 -> 123 | D20: 225 | F20: =E20*D20 -> 0 | I20: BOTANA JAMON | M20: 40 | N20: 70 | P20: =O20*N20 -> 0 | R20: =Q20*M20 -> 0
B21: PROMO MEGA CORONA (3) | C21: =41*3 -> 123 | D21: 225 | E21: 2 | F21: =E21*D21 -> 450 | I21: MANGUITO | M21: 8 | N21: 15 | P21: =O21*N21 -> 0 | R21: =Q21*M21 -> 0
B22: MICHE LAGER (2 MEDIAS) | C22: 40 | D22: 95 | F22: =E22*D22 -> 0 | I22: CHICLES | M22: 28 | N22: 50 | P22: =O22*N22 -> 0 | R22: =Q22*M22 -> 0
B23: MICHE AZUL (2 MEDIAS) | C23: 40 | D23: 95 | F23: =E23*D23 -> 0 | H23: =G23*C23 -> 0 | I23: DESCORCHE | N23: 300 | P23: =O23*N23 -> 0
B24: MICHE VICTORIA (2 MEDIAS) | C24: 45 | D24: 95 | F24: =E24*D24 -> 0 | H24: =G24*C24 -> 0 | I24: SALSA VALENTINA (CHICA) | M24: 17 | N24: 35 | P24: =O24*N24 -> 0 | R24: =Q24*M24 -> 0
B25: MICHE CORONA (2 MEDIAS) | C25: 45 | D25: 95 | F25: =E25*D25 -> 0 | H25: =G25*C25 -> 0 | I25: VASO ROTO | N25: 35 | P25: =O25*N25 -> 0
B26: COPA $50 | C26: 25 | D26: 50 | F26: =E26*D26 -> 0 | H26: =G26*C26 -> 0 | P26: =O26*N26 -> 0
B27: COPA $70 | C27: 30 | D27: 70 | F27: =E27*D27 -> 0 | H27: =G27*C27 -> 0 | P27: =O27*N27 -> 0
B28: COPA $100 | C28: 50 | D28: 100 | F28: =E28*D28 -> 0 | H28: =G28*C28 -> 0 | P28: =O28*N28 -> 0
B29: COPA $120 | C29: 70 | D29: 120 | F29: =E29*D29 -> 0 | H29: =G29*C29 -> 0 | P29: =O29*N29 -> 0
B30: COPA $150 | C30: 100 | D30: 150 | F30: =E30*D30 -> 0 | H30: =G30*C30 -> 0 | P30: =O30*N30 -> 0
B31: AZULITO | C31: 40 | D31: 95 | F31: =E31*D31 -> 0 | H31: =G31*C31 -> 0 | P31: =O31*N31 -> 0
B32: TOTAL DE VENTA | G32: =SUM(F4:F31,P4:P31) -> 2000 | I32: TOTAL DE CORTESIAS | Q32: =SUM(H4:H31,R4:R31) -> 0
B34: =B155 -> 46181
B35: VENTA PERSONAL
B36: PRODUCTO | C36: $ COMPRA | D36: $ VENTA | E36: ELOY | G36: NUBIA | I36: MARCE | K36: ISELA | O36: VIKY | Q36: 4 | S36: 5 | U36: 6 | W36: 7
E37: CANT | F37: $ | G37: CANT | H37: $ | I37: CANT | J37: $ | K37: CANT | L37: $ | O37: CANT | P37: $ | Q37: CANT | R37: $ | S37: CANT | T37: $ | U37: CANT | V37: $ | W37: CANT | X37: $
B38: MEDIA LAGER | C38: 15 | D38: 30 | F38: =E38*C38 -> 0 | H38: =G38*C38 -> 0 | J38: =I38*C38 -> 0 | L38: =K38*C38 -> 0 | P38: =O38*C38 -> 0 | R38: =Q38*C38 -> 0 | T38: =S38*C38 -> 0 | V38: =U38*C38 -> 0 | X38: =W38*C38 -> 0
B39: MEDIA AZUL | C39: 14 | D39: 30 | F39: =E39*C39 -> 0 | H39: =G39*C39 -> 0 | J39: =I39*C39 -> 0 | L39: =K39*C39 -> 0 | P39: =O39*C39 -> 0 | R39: =Q39*C39 -> 0 | T39: =S39*C39 -> 0 | V39: =U39*C39 -> 0 | X39: =W39*C39 -> 0
B40: MEDIA VICTORIA | C40: 17 | D40: 35 | E40: 6 | F40: =E40*C40 -> 102 | H40: =G40*C40 -> 0 | J40: =I40*C40 -> 0 | L40: =K40*C40 -> 0 | P40: =O40*C40 -> 0 | R40: =Q40*C40 -> 0 | T40: =S40*C40 -> 0 | V40: =U40*C40 -> 0 | X40: =W40*C40 -> 0
B41: MEDIA CORONA | C41: 17 | D41: 35 | F41: 1 | H41: =G41*C41 -> 0 | J41: =I41*C41 -> 0 | L41: =K41*C41 -> 0 | P41: =O41*C41 -> 0 | R41: =Q41*C41 -> 0 | T41: =S41*C41 -> 0 | V41: =U41*C41 -> 0 | X41: =W41*C41 -> 0
B42: MEGA LAGER | C42: 37 | D42: 70 | F42: =E42*C42 -> 0 | H42: =G42*C42 -> 0 | I42: 2 | J42: =I42*C42 -> 74 | L42: =K42*C42 -> 0 | P42: =O42*C42 -> 0 | R42: =Q42*C42 -> 0 | T42: =S42*C42 -> 0 | V42: =U42*C42 -> 0 | X42: =W42*C42 -> 0
B43: MEGA ROJA | C43: 35 | D43: 60 | F43: =E43*C43 -> 0 | H43: =G43*C43 -> 0 | J43: =I43*C43 -> 0 | L43: =K43*C43 -> 0 | P43: =O43*C43 -> 0 | R43: =Q43*C43 -> 0 | T43: =S43*C43 -> 0 | V43: =U43*C43 -> 0 | X43: =W43*C43 -> 0
B44: MEGA AZUL | C44: 35 | D44: 60 | F44: =E44*C44 -> 0 | H44: =G44*C44 -> 0 | J44: =I44*C44 -> 0 | L44: =K44*C44 -> 0 | P44: =O44*C44 -> 0 | R44: =Q44*C44 -> 0 | T44: =S44*C44 -> 0 | V44: =U44*C44 -> 0 | X44: =W44*C44 -> 0
B45: MEGA VICTORIA | C45: 41 | D45: 80 | F45: =E45*C45 -> 0 | H45: =G45*C45 -> 0 | J45: =I45*C45 -> 0 | L45: =K45*C45 -> 0 | P45: =O45*C45 -> 0 | R45: =Q45*C45 -> 0 | T45: =S45*C45 -> 0 | V45: =U45*C45 -> 0 | X45: =W45*C45 -> 0
B46: MEGA CORONA | C46: 41 | D46: 80 | F46: =E46*C46 -> 0 | H46: =G46*C46 -> 0 | J46: =I46*C46 -> 0 | L46: =K46*C46 -> 0 | P46: =O46*C46 -> 0 | R46: =Q46*C46 -> 0 | T46: =S46*C46 -> 0 | V46: =U46*C46 -> 0 | X46: =W46*C46 -> 0
B47: CIGARRO | C47: 6 | D47: 10 | F47: =E47*C47 -> 0 | H47: =G47*C47 -> 0 | J47: =I47*C47 -> 0 | L47: =K47*C47 -> 0 | P47: =O47*C47 -> 0 | R47: =Q47*C47 -> 0 | T47: =S47*C47 -> 0 | V47: =U47*C47 -> 0 | X47: =W47*C47 -> 0
B48: CACAHUATE | C48: 13 | D48: 25 | F48: =E48*C48 -> 0 | H48: =G48*C48 -> 0 | J48: =I48*C48 -> 0 | L48: =K48*C48 -> 0 | P48: =O48*C48 -> 0 | R48: =Q48*C48 -> 0 | T48: =S48*C48 -> 0 | V48: =U48*C48 -> 0 | X48: =W48*C48 -> 0
B49: CHICARRON | C49: 11 | D49: 35 | F49: =E49*C49 -> 0 | H49: =G49*C49 -> 0 | J49: =I49*C49 -> 0 | L49: =K49*C49 -> 0 | P49: =O49*C49 -> 0 | R49: =Q49*C49 -> 0 | T49: =S49*C49 -> 0 | V49: =U49*C49 -> 0 | X49: =W49*C49 -> 0
B50: SEMILLAS | C50: 10 | D50: 15 | F50: =E50*C50 -> 0 | H50: =G50*C50 -> 0 | J50: =I50*C50 -> 0 | L50: =K50*C50 -> 0 | P50: =O50*C50 -> 0 | R50: =Q50*C50 -> 0 | T50: =S50*C50 -> 0 | V50: =U50*C50 -> 0 | X50: =W50*C50 -> 0
B51: PAPAS | C51: 14.8 | D51: 35 | F51: =E51*C51 -> 0 | H51: =G51*C51 -> 0 | J51: =I51*C51 -> 0 | L51: =K51*C51 -> 0 | P51: =O51*C51 -> 0 | R51: =Q51*C51 -> 0 | T51: =S51*C51 -> 0 | V51: =U51*C51 -> 0 | X51: =W51*C51 -> 0
B52: COCA 355 | C52: 13 | D52: 20 | F52: =E52*C52 -> 0 | H52: =G52*C52 -> 0 | J52: =I52*C52 -> 0 | L52: =K52*C52 -> 0 | P52: =O52*C52 -> 0 | R52: =Q52*C52 -> 0 | T52: =S52*C52 -> 0 | V52: =U52*C52 -> 0 | X52: =W52*C52 -> 0
B53: PEÑAFIEL 355 | C53: 11 | D53: 20 | F53: =E53*C53 -> 0 | H53: =G53*C53 -> 0 | J53: =I53*C53 -> 0 | L53: =K53*C53 -> 0 | P53: =O53*C53 -> 0 | R53: =Q53*C53 -> 0 | T53: =S53*C53 -> 0 | V53: =U53*C53 -> 0 | X53: =W53*C53 -> 0
B54: TORONJA 355 | C54: 10 | D54: 20 | F54: =E54*C54 -> 0 | H54: =G54*C54 -> 0 | J54: =I54*C54 -> 0 | L54: =K54*C54 -> 0 | P54: =O54*C54 -> 0 | R54: =Q54*C54 -> 0 | T54: =S54*C54 -> 0 | V54: =U54*C54 -> 0 | X54: =W54*C54 -> 0
... B62: CHICLES | C62: 28 | D62: 50 | F62: =E62*C62 -> 0 | H62: =G62*C62 -> 0 | J62: =I62*C62 -> 0 | L62: =K62*C62 -> 0 | P62: =O62*C62 -> 0 | R62: =Q62*C62 -> 0 | T62: =S62*C62 -> 0 | V62: =U62*C62 -> 0 | X62: =W62*C62 -> 0
F63: =E63*C63 -> 0 | H63: =G63*C63 -> 0 | J63: =I63*C63 -> 0 | L63: =K63*C63 -> 0 | P63: =O63*C63 -> 0 | R63: =Q63*C63 -> 0 | T63: =S63*C63 -> 0 | V63: =U63*C63 -> 0 | X63: =W63*C63 -> 0
F64: =E64*C64 -> 0 | H64: =G64*C64 -> 0 | J64: =I64*C64 -> 0 | L64: =K64*C64 -> 0 | P64: =O64*C64 -> 0 | R64: =Q64*C64 -> 0 | T64: =S64*C64 -> 0 | V64: =U64*C64 -> 0 | X64: =W64*C64 -> 0
F65: =E65*C65 -> 0 | H65: =G65*C65 -> 0 | J65: =I65*C65 -> 0 | L65: =K65*C65 -> 0 | P65: =O65*C65 -> 0 | R65: =Q65*C65 -> 0 | T65: =S65*C65 -> 0 | V65: =U65*C65 -> 0 | X65: =W65*C65 -> 0
E66: =E36 -> ELOY | F66: =SUM(F38:F65) -> 103 | G66: =G36 -> NUBIA | H66: =SUM(H38:H65) -> 0 | I66: =I36 -> MARCE | J66: =SUM(J38:J65) -> 74 | K66: =K36 -> ISELA | L66: =SUM(L38:L65) -> 0 | O66: =O36 -> VIKY | P66: =SUM(P38:P65) -> 0 | Q66: =Q36 -> 4 | R66: =SUM(R38:R65) -> 0 | S66: =S36 -> 5 | T66: =SUM(T38:T65) -> 0 | U66: =U36 -> 6 | V66: =SUM(V38:V65) -> 0 | W66: =W36 -> 7 | X66: =SUM(X38:X65) -> 0
B68: =B155 -> 46181
B69: VENTA DE FICHAS
B70: NOMBRE | E70: PRECIO | F70: PRODUCTO | H70: 60 | I70: 80 | J70: TOTAL | K70: VENTA | O70: COMISION | Q70: VENTA TOTAL
B71: =G36 -> NUBIA | E71: 120 | F71: MEDIA LAGER | J71: =H71+I71 -> 0 | K71: =J71*E71 -> 0 | O71: =H71*H70+I71*I70 -> 0
F72: MEDIA AZUL | J72: =H72+I72 -> 0 | K72: =J72*E71 -> 0 | O72: =H72*H70+I72*I70 -> 0
B73: PAGO DE COMISION | E73: 300 | F73: MEGA LAGER | K73: =H73*E73 -> 0 | O73: =H73*150 -> 0
B74: =O71+O72+O73+O74+O75 -> 0 | F74: MEGA AZUL | K74: =H74*E73 -> 0 | O74: =H74*150 -> 0 | Q74: =K71+K72+K73+K74+K75 -> 0
F75: MEGA ROJA | K75: =H75*E73 -> 0 | O75: =H75*150 -> 0
B76: NOMBRE | E76: PRECIO | F76: PRODUCTO | H76: 60 | I76: 80 | J76: TOTAL | K76: VENTA | O76: COMISION | Q76: VENTA TOTAL
B77: =I36 -> MARCE | E77: 120 | F77: MEDIA LAGER | J77: =H77+I77 -> 0 | K77: =J77*E77 -> 0 | O77: =H77*H76+I77*I76 -> 0
F78: MEDIA AZUL | J78: =H78+I78 -> 0 | K78: =J78*E77 -> 0 | O78: =H78*H76+I78*I76 -> 0
B79: PAGO DE COMISION | E79: 300 | F79: MEGA LAGER | K79: =H79*E79 -> 0 | O79: =H79*150 -> 0
B80: =O77+O78+O79+O80+O81 -> 0 | F80: MEGA AZUL | K80: =H80*E79 -> 0 | O80: =H80*150 -> 0 | Q80: =K77+K78+K79+K80+K81 -> 0
F81: MEGA ROJA | K81: =H81*E79 -> 0 | O81: =H81*150 -> 0
B82: NOMBRE | E82: PRECIO | F82: PRODUCTO | H82: 60 | I82: 80 | J82: TOTAL | K82: VENTA | O82: COMISION | Q82: VENTA TOTAL
B83: =K36 -> ISELA | E83: 120 | F83: MEDIA LAGER | J83: =H83+I83 -> 0 | K83: =J83*E83 -> 0 | O83: =H83*H82+I83*I82 -> 0
F84: MEDIA AZUL | J84: =H84+I84 -> 0 | K84: =J84*E83 -> 0 | O84: =H84*H82+I84*I82 -> 0
B85: PAGO DE COMISION | E85: 300 | F85: MEGA LAGER | K85: =H85*E85 -> 0 | O85: =H85*150 -> 0
B86: =O83+O84+O85+O86+O87 -> 0 | F86: MEGA AZUL | K86: =H86*E85 -> 0 | O86: =H86*150 -> 0 | Q86: =K83+K84+K85+K86+K87 -> 0
F87: MEGA ROJA | K87: =H87*E85 -> 0 | O87: =H87*150 -> 0
B88: NOMBRE | E88: PRECIO | F88: PRODUCTO | H88: 60 | I88: 80 | J88: TOTAL | K88: VENTA | O88: COMISION | Q88: VENTA TOTAL
B89: =O36 -> VIKY | E89: 120 | F89: MEDIA LAGER | J89: =H89+I89 -> 0 | K89: =J89*E89 -> 0 | O89: =H89*H88+I89*I88 -> 0
F90: MEDIA AZUL | J90: =H90+I90 -> 0 | K90: =J90*E89 -> 0 | O90: =H90*H88+I90*I88 -> 0
B91: PAGO DE COMISION | E91: 300 | F91: MEGA LAGER | K91: =H91*E91 -> 0 | O91: =H91*150 -> 0
B92: =O89+O90+O91+O92+O93 -> 0 | F92: MEGA AZUL | K92: =H92*E91 -> 0 | O92: =H92*150 -> 0 | Q92: =K89+K90+K91+K92+K93 -> 0
F93: MEGA ROJA | K93: =H93*E91 -> 0 | O93: =H93*150 -> 0
B94: NOMBRE | E94: PRECIO | F94: PRODUCTO | H94: 60 | I94: 80 | J94: TOTAL | K94: VENTA | O94: COMISION | Q94: VENTA TOTAL
B95: =Q36 -> 4 | E95: 120 | F95: MEDIA LAGER | J95: =H95+I95 -> 0 | K95: =J95*E95 -> 0 | O95: =H95*H94+I95*I94 -> 0
F96: MEDIA AZUL | J96: =H96+I96 -> 0 | K96: =J96*E95 -> 0 | O96: =H96*H94+I96*I94 -> 0
B97: PAGO DE COMISION | E97: 300 | F97: MEGA LAGER | K97: =H97*E97 -> 0 | O97: =H97*150 -> 0
B98: =O95+O96+O97+O98+O99 -> 0 | F98: MEGA AZUL | K98: =H98*E97 -> 0 | O98: =H98*150 -> 0 | Q98: =K95+K96+K97+K98+K99 -> 0
F99: MEGA ROJA | K99: =H99*E97 -> 0 | O99: =H99*150 -> 0
B100: NOMBRE | E100: PRECIO | F100: PRODUCTO | H100: 60 | I100: 80 | J100: TOTAL | K100: VENTA | O100: COMISION | Q100: VENTA TOTAL
B101: =S36 -> 5 | E101: 120 | F101: MEDIA LAGER | J101: =H101+I101 -> 0 | K101: =J101*E101 -> 0 | O101: =H101*H100+I101*I100 -> 0
F102: MEDIA AZUL | J102: =H102+I102 -> 0 | K102: =J102*E101 -> 0 | O102: =H102*H100+I102*I100 -> 0
B103: PAGO DE COMISION | E103: 300 | F103: MEGA LAGER | K103: =H103*E103 -> 0 | O103: =H103*150 -> 0
B104: =O101+O102+O103+O104+O105 -> 0 | F104: MEGA AZUL | K104: =H104*E103 -> 0 | O104: =H104*150 -> 0 | Q104: =K101+K102+K103+K104+K105 -> 0
F105: MEGA ROJA | K105: =H105*E103 -> 0 | O105: =H105*150 -> 0
B106: NOMBRE | E106: PRECIO | F106: PRODUCTO | H106: 60 | I106: 80 | J106: TOTAL | K106: VENTA | O106: COMISION | Q106: VENTA TOTAL
B107: =U36 -> 6 | E107: 120 | F107: MEDIA LAGER | J107: =H107+I107 -> 0 | K107: =J107*E107 -> 0 | O107: =H107*H106+I107*I106 -> 0
F108: MEDIA AZUL | J108: =H108+I108 -> 0 | K108: =J108*E107 -> 0 | O108: =H108*H106+I108*I106 -> 0
B109: PAGO DE COMISION | E109: 300 | F109: MEGA LAGER | K109: =H109*E109 -> 0 | O109: =H109*150 -> 0
...

Sheet DOMINGO 07
B1: =B155 -> 46180
B2: VENTA PUBLICO
B3: PRODUCTO | C3: $ COMPRA | D3: $ VENTA | E3: CANT | F3: $ | G3: CORTESIAS | I3: PRODUCTO | M3: $ COMPRA | N3: $ VENTA | O3: CANT | P3: $ | Q3: CORTESIAS
B4: MEDIA LAGER | C4: 15 | D4: 30 | F4: =E4*D4 -> 0 | H4: =G4*C4 -> 0 | I4: CIGARRO | M4: 6 | N4: 10 | P4: =O4*N4 -> 0
B5: MEDIA AZUL | C5: 14 | D5: 30 | F5: =E5*D5 -> 0 | H5: =G5*C5 -> 0 | I5: CACAHUATE | M5: 13 | N5: 25 | P5: =O5*N5 -> 0 | R5: =Q5*M5 -> 0
B6: MEDIA VICTORIA | C6: 17 | D6: 35 | E6: 2 | F6: =E6*D6 -> 70 | H6: =G6*C6 -> 0 | I6: CHICARRON | M6: 11 | N6: 35 | P6: =O6*N6 -> 0 | R6: =Q6*M6 -> 0
B7: MEDIA CORONA | C7: 17 | D7: 35 | E7: 1 | F7: =E7*D7 -> 35 | H7: =G7*C7 -> 0 | I7: SEMILLAS | M7: 10 | N7: 15 | O7: 1 | P7: =O7*N7 -> 15 | R7: =Q7*M7 -> 0
B8: MEGA LAGER | C8: 37 | D8: 70 | E8: 5 | F8: =E8*D8 -> 350 | H8: =G8*C8 -> 0 | I8: CANCION | M8: 0 | N8: 10 | O8: 13 | P8: =O8*N8 -> 130 | R8: =Q8*M8 -> 0
B9: MEGA ROJA | C9: 35 | D9: 60 | E9: 11 | F9: =E9*D9 -> 660 | H9: =G9*C9 -> 0 | I9: PAPAS | M9: 14.8 | N9: 35 | P9: =O9*N9 -> 0 | R9: =Q9*M9 -> 0
B10: MEGA AZUL | C10: 35 | D10: 60 | F10: =E10*D10 -> 0 | H10: =G10*C10 -> 0 | I10: COCA 355 | M10: 13 | N10: 20 | P10: =O10*N10 -> 0 | R10: =Q10*M10 -> 0
B11: MEGA VICTORIA | C11: 41 | D11: 80 | E11: 5 | F11: =E11*D11 -> 400 | H11: =G11*C11 -> 0 | I11: PEÑAFIEL 355 | M11: 11 | N11: 20 | P11: =O11*N11 -> 0 | R11: =Q11*M11 -> 0
B12: MEGA CORONA | C12: 41 | D12: 80 | F12: =E12*D12 -> 0 | H12: =G12*C12 -> 0 | I12: TORONJA 355 | M12: 10 | N12: 20 | P12: =O12*N12 -> 0 | R12: =Q12*M12 -> 0
B13: CUBO MEDIA LAGER (6) | C13: =14*6 -> 84 | D13: 160 | F13: =E13*D13 -> 0 | I13: BOOS | M13: 40 | N13: 60 | P13: =O13*N13 -> 0
B14: CUBO MEDIA AZUL (6) | C14: =14*6 -> 84 | D14: 160 | F14: =E14*D14 -> 0 | I14: NEWMIX PALOMA | M14: 25 | N14: 45 | P14: =O14*N14 -> 0
B15: CUBO MEDIA VICTORIA (6) | C15: =17*6 -> 102 | D15: 180 | F15: =E15*D15 -> 0 | I15: NEWMIX VAMPIRO | M15: 25 | N15: 45 | P15: =O15*N15 -> 0
B16: CUBO MEDIA CORONA (6) | C16: =17*6 -> 102 | D16: 180 | F16: =E16*D16 -> 0 | I16: CLAMATO (Botella) | M16: 35 | N16: 50 | P16: =O16*N16 -> 0 | R16: =Q16*M16 -> 0
B17: PROMO MEGA LAGER (3) | C17: =37*3 -> 111 | D17: 195 | F17: =E17*D17 -> 0 | I17: CLAMATO (Preparado vaso) | M17: 27 | N17: 45 | P17: =O17*N17 -> 0 | R17: =Q17*M17 -> 0
B18: PROMO MEGA ROJA (3) | C18: =35*3 -> 105 | D18: 165 | F18: =E18*D18 -> 0 | I18: PREPARADO SALSAS (Vaso) | M18: 10 | N18: 25 | P18: =O18*N18 -> 0 | R18: =Q18*M18 -> 0
B19: PROMO MEGA AZUL (3) | C19: =35*3 -> 105 | D19: 165 | F19: =E19*D19 -> 0 | I19: SOPA | M19: 14 | N19: 35 | P19: =O19*N19 -> 0 | R19: =Q19*M19 -> 0
B20: PROMO MEGA VICTORIA (3) | C20: =41*3 -> 123 | D20: 225 | F20: =E20*D20 -> 0 | I20: BOTANA JAMON | M20: 40 | N20: 70 | P20: =O20*N20 -> 0 | R20: =Q20*M20 -> 0
B21: PROMO MEGA CORONA (3) | C21: =41*3 -> 123 | D21: 225 | F21: =E21*D21 -> 0 | I21: MANGUITO | M21: 8 | N21: 15 | P21: =O21*N21 -> 0 | R21: =Q21*M21 -> 0
B22: MICHE LAGER (2 MEDIAS) | C22: 40 | D22: 95 | F22: =E22*D22 -> 0 | I22: CHICLES | M22: 28 | N22: 50 | P22: =O22*N22 -> 0 | R22: =Q22*M22 -> 0
B23: MICHE AZUL (2 MEDIAS) | C23: 40 | D23: 95 | F23: =E23*D23 -> 0 | H23: =G23*C23 -> 0 | I23: DESCORCHE | N23: 300 | P23: =O23*N23 -> 0
B24: MICHE VICTORIA (2 MEDIAS) | C24: 45 | D24: 95 | F24: =E24*D24 -> 0 | H24: =G24*C24 -> 0 | I24: SALSA VALENTINA (CHICA) | M24: 17 | N24: 35 | P24: =O24*N24 -> 0 | R24: =Q24*M24 -> 0
B25: MICHE CORONA (2 MEDIAS) | C25: 45 | D25: 95 | F25: =E25*D25 -> 0 | H25: =G25*C25 -> 0 | I25: VASO ROTO | N25: 35 | P25: =O25*N25 -> 0
B26: COPA $50 | C26: 25 | D26: 50 | F26: =E26*D26 -> 0 | H26: =G26*C26 -> 0 | P26: =O26*N26 -> 0
B27: COPA $70 | C27: 30 | D27: 70 | F27: =E27*D27 -> 0 | H27: =G27*C27 -> 0 | P27: =O27*N27 -> 0
B28: COPA $100 | C28: 50 | D28: 100 | F28: =E28*D28 -> 0 | H28: =G28*C28 -> 0 | P28: =O28*N28 -> 0
B29: COPA $120 | C29: 70 | D29: 120 | F29: =E29*D29 -> 0 | H29: =G29*C29 -> 0 | P29: =O29*N29 -> 0
B30: COPA $150 | C30: 100 | D30: 150 | F30: =E30*D30 -> 0 | H30: =G30*C30 -> 0 | P30: =O30*N30 -> 0
B31: AZULITO | C31: 40 | D31: 95 | F31: =E31*D31 -> 0 | H31: =G31*C31 -> 0 | P31: =O31*N31 -> 0
B32: TOTAL DE VENTA | G32: =SUM(F4:F31,P4:P31) -> 1660 | I32: TOTAL DE CORTESIAS | Q32: =SUM(H4:H31,R4:R31) -> 0
B34: =B155 -> 46180
B35: VENTA PERSONAL
B36: PRODUCTO | C36: $ COMPRA | D36: $ VENTA | E36: ELOY | G36: NUBIA | I36: MARCE | K36: ISELA | O36: VIKY | Q36: 4 | S36: 5 | U36: 6 | W36: 7
E37: CANT | F37: $ | G37: CANT | H37: $ | I37: CANT | J37: $ | K37: CANT | L37: $ | O37: CANT | P37: $ | Q37: CANT | R37: $ | S37: CANT | T37: $ | U37: CANT | V37: $ | W37: CANT | X37: $
B38: MEDIA LAGER | C38: 15 | D38: 30 | F38: =E38*C38 -> 0 | H38: =G38*C38 -> 0 | J38: =I38*C38 -> 0 | L38: =K38*C38 -> 0 | P38: =O38*C38 -> 0 | R38: =Q38*C38 -> 0 | T38: =S38*C38 -> 0 | V38: =U38*C38 -> 0 | X38: =W38*C38 -> 0
B39: MEDIA AZUL | C39: 14 | D39: 30 | F39: =E39*C39 -> 0 | H39: =G39*C39 -> 0 | J39: =I39*C39 -> 0 | L39: =K39*C39 -> 0 | P39: =O39*C39 -> 0 | R39: =Q39*C39 -> 0 | T39: =S39*C39 -> 0 | V39: =U39*C39 -> 0 | X39: =W39*C39 -> 0
B40: MEDIA VICTORIA | C40: 17 | D40: 35 | E40: 8 | F40: =E40*C40 -> 136 | H40: =G40*C40 -> 0 | J40: =I40*C40 -> 0 | L40: =K40*C40 -> 0 | P40: =O40*C40 -> 0 | R40: =Q40*C40 -> 0 | T40: =S40*C40 -> 0 | V40: =U40*C40 -> 0 | X40: =W40*C40 -> 0
B41: MEDIA CORONA | C41: 17 | D41: 35 | F41: 1 | H41: =G41*C41 -> 0 | J41: =I41*C41 -> 0 | L41: =K41*C41 -> 0 | P41: =O41*C41 -> 0 | R41: =Q41*C41 -> 0 | T41: =S41*C41 -> 0 | V41: =U41*C41 -> 0 | X41: =W41*C41 -> 0
B42: MEGA LAGER | C42: 37 | D42: 70 | F42: =E42*C42 -> 0 | H42: =G42*C42 -> 0 | I42: 2 | J42: =I42*C42 -> 74 | L42: =K42*C42 -> 0 | P42: =O42*C42 -> 0 | R42: =Q42*C42 -> 0 | T42: =S42*C42 -> 0 | V42: =U42*C42 -> 0 | X42: =W42*C42 -> 0
B43: MEGA ROJA | C43: 35 | D43: 60 | F43: =E43*C43 -> 0 | H43: =G43*C43 -> 0 | J43: =I43*C43 -> 0 | L43: =K43*C43 -> 0 | P43: =O43*C43 -> 0 | R43: =Q43*C43 -> 0 | T43: =S43*C43 -> 0 | V43: =U43*C43 -> 0 | X43: =W43*C43 -> 0
B44: MEGA AZUL | C44: 35 | D44: 60 | E44: 1 | F44: =E44*C44 -> 35 | H44: =G44*C44 -> 0 | J44: =I44*C44 -> 0 | L44: =K44*C44 -> 0 | P44: =O44*C44 -> 0 | R44: =Q44*C44 -> 0 | T44: =S44*C44 -> 0 | V44: =U44*C44 -> 0 | X44: =W44*C44 -> 0
B45: MEGA VICTORIA | C45: 41 | D45: 80 | F45: =E45*C45 -> 0 | H45: =G45*C45 -> 0 | J45: =I45*C45 -> 0 | L45: =K45*C45 -> 0 | P45: =O45*C45 -> 0 | R45: =Q45*C45 -> 0 | T45: =S45*C45 -> 0 | V45: =U45*C45 -> 0 | X45: =W45*C45 -> 0
B46: MEGA CORONA | C46: 41 | D46: 80 | F46: =E46*C46 -> 0 | H46: =G46*C46 -> 0 | J46: =I46*C46 -> 0 | L46: =K46*C46 -> 0 | P46: =O46*C46 -> 0 | R46: =Q46*C46 -> 0 | T46: =S46*C46 -> 0 | V46: =U46*C46 -> 0 | X46: =W46*C46 -> 0
B47: CIGARRO | C47: 6 | D47: 10 | F47: =E47*C47 -> 0 | H47: =G47*C47 -> 0 | J47: =I47*C47 -> 0 | L47: =K47*C47 -> 0 | P47: =O47*C47 -> 0 | R47: =Q47*C47 -> 0 | T47: =S47*C47 -> 0 | V47: =U47*C47 -> 0 | X47: =W47*C47 -> 0
B48: CACAHUATE | C48: 13 | D48: 25 | F48: =E48*C48 -> 0 | H48: =G48*C48 -> 0 | J48: =I48*C48 -> 0 | L48: =K48*C48 -> 0 | P48: =O48*C48 -> 0 | R48: =Q48*C48 -> 0 | T48: =S48*C48 -> 0 | V48: =U48*C48 -> 0 | X48: =W48*C48 -> 0
B49: CHICARRON | C49: 11 | D49: 35 | F49: =E49*C49 -> 0 | H49: =G49*C49 -> 0 | J49: =I49*C49 -> 0 | L49: =K49*C49 -> 0 | P49: =O49*C49 -> 0 | R49: =Q49*C49 -> 0 | T49: =S49*C49 -> 0 | V49: =U49*C49 -> 0 | X49: =W49*C49 -> 0
B50: SEMILLAS | C50: 10 | D50: 15 | F50: =E50*C50 -> 0 | H50: =G50*C50 -> 0 | J50: =I50*C50 -> 0 | L50: =K50*C50 -> 0 | P50: =O50*C50 -> 0 | R50: =Q50*C50 -> 0 | T50: =S50*C50 -> 0 | V50: =U50*C50 -> 0 | X50: =W50*C50 -> 0
B51: PAPAS | C51: 14.8 | D51: 35 | F51: =E51*C51 -> 0 | H51: =G51*C51 -> 0 | J51: =I51*C51 -> 0 | L51: =K51*C51 -> 0 | P51: =O51*C51 -> 0 | R51: =Q51*C51 -> 0 | T51: =S51*C51 -> 0 | V51: =U51*C51 -> 0 | X51: =W51*C51 -> 0
B52: COCA 355 | C52: 13 | D52: 20 | F52: =E52*C52 -> 0 | G52: 1 | H52: =G52*C52 -> 13 | J52: =I52*C52 -> 0 | L52: =K52*C52 -> 0 | P52: =O52*C52 -> 0 | R52: =Q52*C52 -> 0 | T52: =S52*C52 -> 0 | V52: =U52*C52 -> 0 | X52: =W52*C52 -> 0
B53: PEÑAFIEL 355 | C53: 11 | D53: 20 | F53: =E53*C53 -> 0 | H53: =G53*C53 -> 0 | J53: =I53*C53 -> 0 | L53: =K53*C53 -> 0 | P53: =O53*C53 -> 0 | R53: =Q53*C53 -> 0 | T53: =S53*C53 -> 0 | V53: =U53*C53 -> 0 | X53: =W53*C53 -> 0
B54: TORONJA 355 | C54: 10 | D54: 20 | F54: =E54*C54 -> 0 | H54: =G54*C54 -> 0 | J54: =I54*C54 -> 0 | L54: =K54*C54 -> 0 | P54: =O54*C54 -> 0 | R54: =Q54*C54 -> 0 | T54: =S54*C54 -> 0 | V54: =U54*C54 -> 0 | X54: =W54*C54 -> 0
B55: BOOS | C55: 40 | D55: 60 | F55: =E55*C55 -> 0 | H55: =G55*C55 -> 0 | J55: =I55*C55 -> 0 | L55: =K55*C55 -> 0 | P55: =O55*C55 -> 0 | R55: =Q55*C55 -> 0 | T55: =S55*C55 -> 0 | V55: =U55*C55 -> 0 | X55: =W55*C55 -> 0
B56: NEWMIX PALOMA | C56: 25 | D56: 45 | F56: =E56*C56 -> 0 | H56: =G56*C56 -> 0 | J56: =I56*C56 -> 0 | L56: =K56*C56 -> 0 | P56: =O56*C56 -> 0 | R56: =Q56*C56 -> 0 | T56: =S56*C56 -> 0 | V56: =U56*C56 -> 0 | X56: =W56*C56 -> 0
B57: NEWMIX VAMPIRO | C57: 25 | D57: 45 | F57: =E57*C57 -> 0 | H57: =G57*C57 -> 0 | J57: =I57*C57 -> 0 | L57: =K57*C57 -> 0 | P57: =O57*C57 -> 0 | R57: =Q57*C57 -> 0 | T57: =S57*C57 -> 0 | V57: =U57*C57 -> 0 | X57: =W57*C57 -> 0
B58: CLAMATO (Botella) | C58: 27 | D58: 45 | F58: =E58*C58 -> 0 | H58: =G58*C58 -> 0 | J58: =I58*C58 -> 0 | L58: =K58*C58 -> 0 | P58: =O58*C58 -> 0 | R58: =Q58*C58 -> 0 | T58: =S58*C58 -> 0 | V58: =U58*C58 -> 0 | X58: =W58*C58 -> 0
B59: SOPA | C59: 14 | D59: 35 | F59: =E59*C59 -> 0 | H59: =G59*C59 -> 0 | J59: =I59*C59 -> 0 | L59: =K59*C59 -> 0 | P59: =O59*C59 -> 0 | R59: =Q59*C59 -> 0 | T59: =S59*C59 -> 0 | V59: =U59*C59 -> 0 | X59: =W59*C59 -> 0
B60: BOTANA JAMON | C60: 40 | D60: 70 | F60: =E60*C60 -> 0 | H60: =G60*C60 -> 0 | J60: =I60*C60 -> 0 | L60: =K60*C60 -> 0 | P60: =O60*C60 -> 0 | R60: =Q60*C60 -> 0 | T60: =S60*C60 -> 0 | V60: =U60*C60 -> 0 | X60: =W60*C60 -> 0
B61: MANGUITO | C61: 8 | D61: 15 | F61: =E61*C61 -> 0 | H61: =G61*C61 -> 0 | J61: =I61*C61 -> 0 | L61: =K61*C61 -> 0 | P61: =O61*C61 -> 0 | R61: =Q61*C61 -> 0 | T61: =S61*C61 -> 0 | V61: =U61*C61 -> 0 | X61: =W61*C61 -> 0
B62: CHICLES | C62: 28 | D62: 50 | F62: =E62*C62 -> 0 | H62: =G62*C62 -> 0 | J62: =I62*C62 -> 0 | L62: =K62*C62 -> 0 | P62: =O62*C62 -> 0 | R62: =Q62*C62 -> 0 | T62: =S62*C62 -> 0 | V62: =U62*C62 -> 0 | X62: =W62*C62 -> 0
F63: =E63*C63 -> 0 | H63: =G63*C63 -> 0 | J63: =I63*C63 -> 0 | L63: =K63*C63 -> 0 | P63: =O63*C63 -> 0 | R63: =Q63*C63 -> 0 | T63: =S63*C63 -> 0 | V63: =U63*C63 -> 0 | X63: =W63*C63 -> 0
F64: =E64*C64 -> 0 | H64: =G64*C64 -> 0 | J64: =I64*C64 -> 0 | L64: =K64*C64 -> 0 | P64: =O64*C64 -> 0 | R64: =Q64*C64 -> 0 | T64: =S64*C64 -> 0 | V64: =U64*C64 -> 0 | X64: =W64*C64 -> 0
F65: =E65*C65 -> 0 | H65: =G65*C65 -> 0 | J65: =I65*C65 -> 0 | L65: =K65*C65 -> 0 | P65: =O65*C65 -> 0 | R65: =Q65*C65 -> 0 | T65: =S65*C65 -> 0 | V65: =U65*C65 -> 0 | X65: =W65*C65 -> 0
E66: =E36 -> ELOY | F66: =SUM(F38:F65) -> 172 | G66: =G36 -> NUBIA | H66: =SUM(H38:H65) -> 13 | I66: =I36 -> MARCE | J66: =SUM(J38:J65) -> 74 | K66: =K36 -> ISELA | L66: =SUM(L38:L65) -> 0 | O66: =O36 -> VIKY | P66: =SUM(P38:P65) -> 0 | Q66: =Q36 -> 4 | R66: =SUM(R38:R65) -> 0 | S66: =S36 -> 5 | T66: =SUM(T38:T65) -> 0 | U66: =U36 -> 6 | V66: =SUM(V38:V65) -> 0 | W66: =W36 -> 7 | X66: =SUM(X38:X65) -> 0
B68: =B155 -> 46180
B69: VENTA DE FICHAS
B70: NOMBRE | E70: PRECIO | F70: PRODUCTO | H70: 60 | I70: 80 | J70: TOTAL | K70: VENTA | O70: COMISION | Q70: VENTA TOTAL
B71: =G36 -> NUBIA | E71: 120 | F71: MEDIA LAGER | J71: =H71+I71 -> 0 | K71: =J71*E71 -> 0 | O71: =H71*H70+I71*I70 -> 0
F72: MEDIA AZUL | J72: =H72+I72 -> 0 | K72: =J72*E71 -> 0 | O72: =H72*H70+I72*I70 -> 0
B73: PAGO DE COMISION | E73: 300 | F73: MEGA LAGER | K73: =H73*E73 -> 0 | O73: =H73*150 -> 0
B74: =O71+O72+O73+O74+O75 -> 0 | F74: MEGA AZUL | K74: =H74*E73 -> 0 | O74: =H74*150 -> 0 | Q74: =K71+K72+K73+K74+K75 -> 0
F75: MEGA ROJA | K75: =H75*E73 -> 0 | O75: =H75*150 -> 0
B76: NOMBRE | E76: PRECIO | F76: PRODUCTO | H76: 60 | I76: 80 | J76: TOTAL | K76: VENTA | O76: COMISION | Q76: VENTA TOTAL
B77: =I36 -> MARCE | E77: 120 | F77: MEDIA LAGER | J77: =H77+I77 -> 0 | K77: =J77*E77 -> 0 | O77: =H77*H76+I77*I76 -> 0
F78: MEDIA AZUL | J78: =H78+I78 -> 0 | K78: =J78*E77 -> 0 | O78: =H78*H76+I78*I76 -> 0
B79: PAGO DE COMISION | E79: 300 | F79: MEGA LAGER | K79: =H79*E79 -> 0 | O79: =H79*150 -> 0
B80: =O77+O78+O79+O80+O81 -> 0 | F80: MEGA AZUL | K80: =H80*E79 -> 0 | O80: =H80*150 -> 0 | Q80: =K77+K78+K79+K80+K81 -> 0
F81: MEGA ROJA | K81: =H81*E79 -> 0 | O81: =H81*150 -> 0
B82: NOMBRE | E82: PRECIO | F82: PRODUCTO | H82: 60 | I82: 80 | J82: TOTAL | K82: VENTA | O82: COMISION | Q82: VENTA TOTAL
B83: =K36 -> ISELA | E83: 120 | F83: MEDIA LAGER | J83: =H83+I83 -> 0 | K83: =J83*E83 -> 0 | O83: =H83*H82+I83*I82 -> 0
F84: MEDIA AZUL | J84: =H84+I84 -> 0 | K84: =J84*E83 -> 0 | O84: =H84*H82+I84*I82 -> 0
B85: PAGO DE COMISION | E85: 300 | F85: MEGA LAGER | K85: =H85*E85 -> 0 | O85: =H85*150 -> 0
B86: =O83+O84+O85+O86+O87 -> 0 | F86: MEGA AZUL | K86: =H86*E85 -> 0 | O86: =H86*150 -> 0 | Q86: =K83+K84+K85+K86+K87 -> 0
F87: MEGA ROJA | K87: =H87*E85 -> 0 | O87: =H87*150 -> 0
B88: NOMBRE | E88: PRECIO | F88: PRODUCTO | H88: 60 | I88: 80 | J88: TOTAL | K88: VENTA | O88: COMISION | Q88: VENTA TOTAL
B89: =O36 -> VIKY | E89: 120 | F89: MEDIA LAGER | J89: =H89+I89 -> 0 | K89: =J89*E89 -> 0 | O89: =H89*H88+I89*I88 -> 0
F90: MEDIA AZUL | J90: =H90+I90 -> 0 | K90: =J90*E89 -> 0 | O90: =H90*H88+I90*I88 -> 0
B91: PAGO DE COMISION | E91: 300 | F91: MEGA LAGER | K91: =H91*E91 -> 0 | O91: =H91*150 -> 0
B92: =O89+O90+O91+O92+O93 -> 0 | F92: MEGA AZUL | K92: =H92*E91 -> 0 | O92: =H92*150 -> 0 | Q92: =K89+K90+K91+K92+K93 -> 0
F93: MEGA ROJA | K93: =H93*E91 -> 0 | O93: =H93*150 -> 0
B94: NOMBRE | E94: PRECIO | F94: PRODUCTO | H94: 60 | I94: 80 | J94: TOTAL | K94: VENTA | O94: COMISION | Q94: VENTA TOTAL
B95: =Q36 -> 4 | E95: 120 | F95: MEDIA LAGER | J95: =H95+I95 -> 0 | K95: =J95*E95 -> 0 | O95: =H95*H94+I95*I94 -> 0
F96: MEDIA AZUL | J96: =H96+I96 -> 0 | K96: =J96*E95 -> 0 | O96: =H96*H94+I96*I94 -> 0
B97: PAGO DE COMISION | E97: 300 | F97: MEGA LAGER | K97: =H97*E97 -> 0 | O97: =H97*150 -> 0
B98: =O95+O96+O97+O98+O99 -> 0 | F98: MEGA AZUL | K98: =H98*E97 -> 0 | O98: =H98*150 -> 0 | Q98: =K95+K96+K97+K98+K99 -> 0
F99: MEGA ROJA | K99: =H99*E97 -> 0 | O99: =H99*150 -> 0
B100: NOMBRE | E100: PRECIO | F100: PRODUCTO | H100: 60 | I100: 80 | J100: TOTAL | K100: VENTA | O100: COMISION | Q100: VENTA TOTAL
B101: =S36 -> 5 | E101: 120 | F101: MEDIA LAGER | J101: =H101+I101 -> 0 | K101: =J101*E101 -> 0 | O101: =H101*H100+I101*I100 -> 0
F102: MEDIA AZUL | J102: =H102+I102 -> 0 | K102: =J102*E101 -> 0 | O102: =H102*H100+I102*I100 -> 0
...
